Workbook

Sheet sueldos
A1: QN | B1: MES | C1: MES NO. | D1: NOMBRE | E1: Total sueldo (N) | F1: Total prestaciones (N) | G1: Total cuotas patrón (N) | H1: vales 1 (N) | I1: vales 2 (N) | J1: Puntualidad (lira) | K1: Excedente (lira) | L1: Comisión (lira) | M1: Provisiones | N1: Praxx | O1: NOMBRE BIEN | P1: Total | Q1: PROVISION | R1: TOTAL2 | S1: Departamento
A2: 1 | B2: agosto | C2: 8 | D2: RUIZ ZARATE GAEL | E2: 5115 | F2: 1023 | G2: 7753.72 | H2: 300 | J2: 800 | K2: 5657.22 | L2: 258.29 | O2: RUIZ ZARATE GAEL | P2: 20907.23 | R2: 20907.23 | S2: Estafeta
A3: 1 | B3: agosto | C3: 8 | D3: LOPEZ HERNANDEZ RAUL IVAN | E3: 5616.6 | F3: 1404.15 | G3: 8776.25 | H3: 200 | J3: 560 | K3: 1086.32 | L3: 65.85 | O3: LOPEZ HERNANDEZ RAUL IVAN | P3: 17709.17 | R3: 17709.17 | S3: TAP/IMILE
A4: 1 | B4: agosto | C4: 8 | D4: RUBIO MACIAS CARLOS ANDRES | E4: 7077.15 | F4: 1415.43 | G4: 10613.46 | H4: 350 | J4: 2000 | K4: 5003.81 | L4: 280.15 | O4: RUBIO MACIAS CARLOS ANDRES | P4: 26740 | R4: 26740 | S4: Staff
A5: 1 | B5: agosto | C5: 8 | D5: JUAREZ SANDOVAL ROCIO | E5: 4725.6 | F5: 2677.84 | G5: 8900.92 | H5: 350 | J5: 800 | K5: 6706.79 | L5: 300.27 | O5: JUAREZ SANDOVAL ROCIO | P5: 24461.42 | R5: 24461.42 | S5: Staff
A6: 1 | B6: agosto | C6: 8 | D6: MEDINA SANCHEZ LUIS | E6: 5979 | F6: 1195.8 | G6: 8957.99 | H6: 200 | J6: 800 | K6: 3077.21 | L6: 155.09 | O6: MEDINA SANCHEZ LUIS | P6: 20365.09 | R6: 20365.09 | S6: Staff
A7: 1 | B7: agosto | C7: 8 | D7: ZUÑIGA GONZALEZ EMMANUEL | E7: 4725.6 | F7: 945.12 | G7: 7116.22 | H7: 200 | J7: 1320 | K7: 5733.1 | L7: 282.12 | O7: ZUÑIGA GONZALEZ EMMANUEL | P7: 20322.16 | R7: 20322.16 | S7: Staff
A8: 1 | B8: agosto | C8: 8 | D8: CAMARGO CASTRO BEATRIZ SELENE | E8: 5017.05 | F8: 997.41 | G8: 7524.08 | H8: 300 | K8: 0 | L8: 0 | O8: CAMARGO CASTRO BEATRIZ SELENE | P8: 13838.54 | R8: 13838.54 | S8: Staff
A9: 1 | B9: agosto | C9: 8 | D9: MUÑOZ SEGURA KARINA | E9: 3780.48 | F9: 2362.8 | G9: 7600.62 | H9: 200 | I9: 378.05 | K9: 0 | L9: 0 | O9: MUÑOZ SEGURA KARINA | P9: 14321.95 | R9: 14321.95 | S9: Staff
A10: 1 | B10: agosto | C10: 8 | D10: PEREZ RIOS WILLIAMS ALEXANDER | E10: 3361.5 | F10: 4407.3 | G10: 9469.07 | H10: 300 | J10: 520 | K10: 1121.33 | L10: 65.65 | O10: PEREZ RIOS WILLIAMS ALEXANDER | P10: 19244.85 | R10: 19244.85 | S10: Staff
A11: 1 | B11: agosto | C11: 8 | D11: ALEMAN LOPEZ LUIS ALBERTO | E11: 5115 | F11: 1023 | G11: 7692.34 | H11: 350 | J11: 800 | K11: 4487.22 | L11: 211.49 | O11: ALEMAN LOPEZ LUIS ALBERTO | P11: 19679.05 | R11: 19679.05 | S11: Veracruz
A12: 1 | B12: agosto | C12: 8 | D12: ROSAS LOBERA PATRICIA | E12: 4725.6 | F12: - | G12: 6450.8 | K12: 0 | L12: 0 | O12: ROSAS LOBERA PATRICIA | P12: 11176.4 | R12: 11176.4 | S12: Amazon 1
A13: 1 | B13: agosto | C13: 8 | D13: PEREZ LAGUNAS WENDY PAOLA | E13: 5115 | F13: 1023 | G13: 7753.72 | H13: 300 | J13: 600 | K13: 1987.22 | L13: 103.49 | O13: PEREZ LAGUNAS WENDY PAOLA | P13: 16882.43 | R13: 16882.43 | S13: Toluca
A14: 1 | B14: agosto | C14: 8 | D14: GARCIA BECERRIL YARASKA YETZEL | E14: 4491.48 | F14: 2221.17 | G14: 8382.14 | H14: 300 | I14: 480 | K14: 0 | L14: 0 | O14: GARCIA BECERRIL YARASKA YETZEL | P14: 15874.79 | R14: 15874.79 | S14: Staff
A15: 1 | B15: agosto | C15: 8 | D15: RENDON MORALES MANUEL ALEJANDRO | E15: 4725.6 | F15: 945.12 | G15: 7172.92 | H15: 350 | J15: 800 | K15: 4772.84 | L15: 222.91 | O15: RENDON MORALES MANUEL ALEJANDRO | P15: 18989.39 | R15: 18989.39 | S15: Staff
A16: 1 | B16: agosto | C16: 8 | D16: ARRIAGA ROSAS CADERIN | E16: 4725.6 | F16: 945.12 | G16: 7168.18 | H16: 300 | J16: 480 | K16: 772.84 | L16: 50.11 | O16: ARRIAGA ROSAS CADERIN | P16: 14441.85 | R16: 14441.85 | S16: Toluca
A17: 1 | B17: agosto | C17: 8 | D17: MORA ARROYO MARIA ELBA | E17: 4985.11 | F17: 1763.96 | G17: 8454.42 | H17: 200 | J17: 1200 | K17: 7768.29 | L17: 358.73 | O17: MORA ARROYO MARIA ELBA | P17: 24730.51 | R17: 24730.51 | S17: Staff
A18: 1 | B18: agosto | C18: 8 | D18: AGUERO GONZALEZ JUAN CARLOS | E18: 4725.6 | F18: 1181.4 | G18: 7418.65 | H18: 350 | J18: 600 | K18: 2424.25 | L18: 120.97 | O18: AGUERO GONZALEZ JUAN CARLOS | P18: 16820.87 | R18: 16820.87 | S18: TAP/IMILE
A19: 1 | B19: agosto | C19: 8 | D19: ACACIO LARA MANUEL | E19: 5753.85 | F19: 3068.72 | G19: 10677.14 | H19: 300 | J19: 760 | K19: 4609.35 | L19: 214.77 | O19: ACACIO LARA MANUEL | P19: 25383.83 | R19: 25383.83 | S19: staff
A20: 1 | B20: agosto | C20: 8 | D20: ARELLANO HERNANDEZ OLGA LIDIA | E20: 5753.85 | F20: 990.77 | G20: 8516.07 | H20: 350 | J20: 640 | K20: 1994.11 | L20: 105.36 | O20: ARELLANO HERNANDEZ OLGA LIDIA | P20: 18350.16 | R20: 18350.16 | S20: imile aifa
A21: 1 | B21: agosto | C21: 8 | D21: ROJAS MORALES ANASTACIO | E21: 4492.56 | F21: 1377.62 | G21: 7577.92 | H21: 300 | J21: 420 | K21: 0 | L21: 16.8 | O21: ROJAS MORALES ANASTACIO | P21: 14184.9 | R21: 14184.9 | S21: Toluca
A22: 1 | B22: agosto | C22: 8 | D22: GARCIA GONZALEZ WENDY GUADALUPE | E22: 5017.05 | F22: 1003.41 | G22: 7591.73 | H22: 300 | J22: 480 | K22: 588.78 | L22: 42.75 | O22: GARCIA GONZALEZ WENDY GUADALUPE | P22: 15023.72 | R22: 15023.72 | S22: Toluca
A23: 1 | B23: agosto | C23: 8 | D23: ARANDA MARTINEZ JOSE RAUL | E23: 3051 | F23: 2644.2 | G23: 7286.96 | H23: 300 | J23: 480 | K23: 879.32 | L23: 54.37 | O23: ARANDA MARTINEZ JOSE RAUL | P23: 14695.85 | R23: 14695.85 | S23: Toluca
A24: 1 | B24: agosto | C24: 8 | D24: COLIN MORALES ARMANDO | E24: 7152.6 | F24: 1788.15 | G24: 11570.55 | H24: 300 | J24: 652 | K24: 430.69 | L24: 43.31 | O24: COLIN MORALES ARMANDO | P24: 21937.3 | R24: 21937.3 | S24: Staff
A25: 1 | B25: agosto | C25: 8 | D25: CAMPOS ROMERO CRISTINA | E25: 4682.58 | F25: 1270.99 | G25: 7520.9 | H25: 300 | J25: 480 | K25: 647.95 | L25: 45.12 | O25: CAMPOS ROMERO CRISTINA | P25: 14947.54 | R25: 14947.54 | S25: Staff
A26: 1 | B26: agosto | C26: 8 | D26: GONZALEZ ROJAS EDUARDO | E26: 3361.59 | F26: 2913.38 | G26: 7994.75 | H26: 200 | J26: 520 | K26: 882.08 | L26: 56.08 | O26: GONZALEZ ROJAS EDUARDO | P26: 15927.88 | R26: 15927.88 | S26: Toluca
A27: 1 | B27: agosto | C27: 8 | D27: ALBAVERA LAGUNAS JORGE | E27: 4410.98 | F27: 1076.03 | G27: 6979.62 | H27: 300 | K27: 886.7 | L27: 35.47 | O27: ALBAVERA LAGUNAS JORGE | P27: 13688.8 | R27: 13688.8 | S27: imile aifa
A28: 1 | B28: agosto | C28: 8 | D28: CORTES ZEPEDA RENE | E28: 4445.52 | F28: 1985.71 | G28: 8150.72 | H28: 350 | J28: 880 | K28: 16449.64 | L28: 693.19 | O28: CORTES ZEPEDA RENE | P28: 32954.78 | R28: 32954.78 | S28: Estafeta
A29: 1 | B29: agosto | C29: 8 | D29: HERRERA MONDRAGON ZUREYMA DENYSSE | E29: 5026.8 | F29: 705.36 | G29: 7291.26 | H29: 300 | J29: 460 | K29: 500 | L29: 38.4 | O29: HERRERA MONDRAGON ZUREYMA DENYSSE | P29: 14321.82 | R29: 14321.82 | S29: Staff
A30: 1 | B30: agosto | C30: 8 | D30: GARCIA BRISEÑO DARIO ABRAHAM | E30: 4725.6 | F30: 945.12 | G30: 7172.92 | H30: 350 | J30: 880 | K30: 3332.27 | L30: 168.49 | O30: GARCIA BRISEÑO DARIO ABRAHAM | P30: 17574.4 | R30: 17574.4 | S30: Toluca
A31: 1 | B31: agosto | C31: 8 | D31: FLORES GARCIA SOFIA | E31: 4347.2 | F31: 1538.24 | G31: 7448.5 | H31: 300 | J31: 540 | K31: 1458.18 | L31: 79.93 | O31: FLORES GARCIA SOFIA | P31: 15712.05 | R31: 15712.05 | S31: STAFF
A32: 1 | B32: agosto | C32: 8 | D32: MENDOZA CASIMIRO PAULA | E32: 4725.6 | F32: - | G32: 6186.46 | H32: 200 | I32: 378.05 | K32: 0 | L32: 0 | O32: MENDOZA CASIMIRO PAULA | P32: 11490.11 | R32: 11490.11 | S32: Toluca
A33: 1 | B33: agosto | C33: 8 | D33: RAMIREZ MUÑOZ LETICIA | E33: 0 | F33: - | G33: - | H33: - | K33: 0 | L33: 0 | O33: RAMIREZ MUÑOZ LETICIA | P33: 0 | R33: 0 | S33: Staff
A34: 1 | B34: agosto | C34: 8 | D34: SANCHEZ GONZALEZ BRIAN ALEXIS | E34: 4725.6 | F34: 390.94 | G34: 6541.87 | H34: 300 | K34: 0 | L34: 0 | O34: SANCHEZ GONZALEZ BRIAN ALEXIS | P34: 11958.41 | R34: 11958.41 | S34: Staff
A35: 1 | B35: agosto | C35: 8 | D35: MARTINEZ DEL RIO EDUARDO ALEXEI | E35: 5016.9 | F35: 703.38 | G35: 7274.43 | H35: 300 | J35: 520 | K35: 325 | L35: 33.8 | O35: MARTINEZ DEL RIO EDUARDO ALEXEI | P35: 14173.51 | R35: 14173.51 | S35: Staff
A36: 1 | B36: agosto | C36: 8 | D36: GARCIA OCAMPO JAZMIN | E36: 5616.3 | F36: 1123.26 | G36: 8483.75 | H36: 300 | J36: 620 | K36: 1745.27 | L36: 94.61 | O36: GARCIA OCAMPO JAZMIN | P36: 17983.19 | R36: 17983.19 | S36: laredo
A37: 1 | B37: agosto | C37: 8 | D37: MONROY CAMPOS JOSE ANGEL | E37: 5015.85 | F37: 733.17 | G37: 7306.59 | H37: 300 | J37: 480 | K37: 879.22 | L37: 54.37 | O37: MONROY CAMPOS JOSE ANGEL | P37: 14769.2 | R37: 14769.2 | S37: Toluca
A38: 1 | B38: agosto | C38: 8 | D38: CHAVEZ AGUILAR LORENA | E38: 4725.6 | F38: 512 | G38: 6717.73 | H38: 300 | J38: 480 | K38: 1000 | L38: 59.2 | O38: CHAVEZ AGUILAR LORENA | P38: 13794.53 | R38: 13794.53 | S38: Toluca
A39: 1 | B39: agosto | C39: 8 | D39: HERNANDEZ AGUILAR ANGELICA CELINA | E39: 7077 | F39: 1415.4 | G39: 10698.17 | H39: 350 | J39: 2496 | K39: 11850 | L39: 573.84 | O39: HERNANDEZ AGUILAR ANGELICA CELINA | P39: 17230.205 | Q39: 0 | R39: 17230.205 | S39: estafeta
D40: HERNANDEZ AGUILAR ANGELICA CELINA | O40: HERNANDEZ AGUILAR ANGELICA CELINA | P40: 17230.205 | Q40: 0 | R40: 17230.205 | S40: imile aifa
A41: 1 | B41: agosto | C41: 8 | D41: CARBAJAL CASTRO JESUS | E41: 4725.6 | F41: - | G41: 6447.56 | H41: 200 | I41: 378.05 | K41: 0 | L41: 0 | O41: CARBAJAL CASTRO JESUS | P41: 11751.21 | R41: 11751.21 | S41: Tránsito
A42: 1 | B42: agosto | C42: 8 | D42: VILLANUEVA ESPINOSA IVAN | E42: 5016 | F42: 823.2 | G42: 7343.35 | H42: 200 | I42: 420 | K42: 0 | L42: 0 | O42: VILLANUEVA ESPINOSA IVAN | P42: 13802.55 | R42: 13802.55 | S42: CDMX
A43: 1 | B43: agosto | C43: 8 | D43: OLIVARES RANGEL JESUS ALBERTO | E43: 5605.05 | F43: 284.36 | G43: 7909.49 | H43: 300 | J43: 420 | K43: 0 | L43: 16.8 | O43: OLIVARES RANGEL JESUS ALBERTO | P43: 14535.7 | R43: 14535.7 | S43: Tránsito
A44: 1 | B44: agosto | C44: 8 | D44: ORTIZ MEJIA HELLEN ANAIS | E44: 4725.6 | F44: 945.12 | G44: 7167.05 | H44: 200 | J44: 480 | K44: 210.34 | L44: 27.61 | O44: ORTIZ MEJIA HELLEN ANAIS | P44: 13755.72 | R44: 13755.72 | S44: Toluca
A45: 1 | B45: agosto | C45: 8 | D45: CANO MATIAS FELIPE ALVARO | E45: 5017.8 | F45: 2663.42 | G45: 9261.62 | H45: 200 | K45: 0 | L45: 0 | O45: CANO MATIAS FELIPE ALVARO | P45: 17142.84 | R45: 17142.84 | S45: CDMX
A46: 1 | B46: agosto | C46: 8 | D46: GARCIA CARRASCO JUAN PABLO | E46: 2341.22 | F46: 3143.92 | G46: 7308.38 | H46: 350 | J46: 480.07 | K46: 210.5 | L46: 27.62 | O46: GARCIA CARRASCO JUAN PABLO | P46: 13861.71 | R46: 13861.71 | S46: CDMX
A47: 1 | B47: agosto | C47: 8 | D47: LOPEZ IZQUIERDO BRUNO ISAIAS | E47: 4681.6 | F47: 2273.92 | G47: 8491.82 | H47: 350 | K47: 2480.7 | L47: 99.23 | O47: LOPEZ IZQUIERDO BRUNO ISAIAS | P47: 18377.27 | R47: 18377.27 | S47: imile aifa
A48: 1 | B48: agosto | C48: 8 | D48: ARCHUNDIA CONTRERAS MARIA GUADALUPE | E48: 5753.85 | F48: 1150.77 | G48: 8684.06 | H48: 350 | J48: 800 | K48: 3860.86 | L48: 186.43 | O48: ARCHUNDIA CONTRERAS MARIA GUADALUPE | P48: 20785.97 | R48: 20785.97 | S48: Toluca
A49: 1 | B49: agosto | C49: 8 | D49: MORENO RAMIREZ ELISA YAELI | E49: 4725.6 | F49: 945.12 | G49: 7172.92 | H49: 200 | J49: 1800 | K49: 7007.15 | L49: 352.29 | O49: MORENO RAMIREZ ELISA YAELI | P49: 22203.08 | R49: 22203.08 | S49: Staff
A50: 1 | B50: agosto | C50: 8 | D50: LOMELIN CATARINO BRAYAN | E50: 4725.6 | F50: 62 | G50: 6509.91 | H50: 766.05 | K50: 0 | L50: 0 | O50: LOMELIN CATARINO BRAYAN | P50: 12063.56 | R50: 12063.56 | S50: Amazon 2
A51: 1 | B51: agosto | C51: 8 | D51: BOLAÑOS BALCAZAR JOSE LUIS | E51: 4095.78 | F51: 1449.28 | G51: 7290.17 | H51: 300 | K51: 3739.38 | L51: 149.58 | O51: BOLAÑOS BALCAZAR JOSE LUIS | P51: 17024.19 | R51: 17024.19 | S51: Veracruz
A52: 1 | B52: agosto | C52: 8 | D52: MUNGUIA MUNGUIA JOSE JUAN | E52: 4725.9 | F52: 442.71 | G52: 6593.23 | H52: 350 | J52: 560 | K52: 9474.03 | L52: 401.36 | O52: MUNGUIA MUNGUIA JOSE JUAN | P52: 22547.23 | R52: 22547.23 | S52: Estafeta
A53: 1 | B53: agosto | C53: 8 | D53: CRUZ CRUZ GREGORY ANUAR | E53: 4725.6 | F53: - | G53: 6446.05 | H53: 766.05 | K53: 0 | L53: 0 | O53: CRUZ CRUZ GREGORY ANUAR | P53: 11937.7 | R53: 11937.7 | S53: Amazon 1
A54: 1 | B54: agosto | C54: 8 | D54: PEREZ CHAVEZ PAMELA BERENICE | E54: 4725.6 | F54: 1235.12 | G54: 7409.05 | H54: 300 | K54: 0 | L54: 0 | O54: PEREZ CHAVEZ PAMELA BERENICE | P54: 13669.77 | R54: 13669.77 | S54: Staff
A55: 1 | B55: agosto | C55: 8 | D55: CRUZ CRUZ JESUS ISSBOSE | E55: 4725.6 | F55: - | G55: 6446.05 | H55: 766.05 | K55: 0 | L55: 0 | O55: CRUZ CRUZ JESUS ISSBOSE | P55: 11937.7 | R55: 11937.7 | S55: Amazon 1
A56: 1 | B56: agosto | C56: 8 | D56: RODRIGUEZ HERNANDEZ JAVIER | E56: 4725.6 | F56: - | G56: 6136.87 | H56: 200 | I56: 378.05 | K56: 0 | L56: 0 | O56: RODRIGUEZ HERNANDEZ JAVIER | P56: 11440.52 | R56: 11440.52 | S56: AIFA
A57: 1 | B57: agosto | C57: 8 | D57: DELGADO SANDOVAL OSCAR DIEGO | E57: 4725.6 | F57: 80 | G57: 6273.2 | H57: 300 | I57: 378.05 | K57: 0 | L57: 0 | O57: DELGADO SANDOVAL OSCAR DIEGO | P57: 11756.85 | R57: 11756.85 | S57: Staff
A58: 1 | B58: agosto | C58: 8 | D58: ORTEGA MONROY ALEXIS | E58: 4725.6 | F58: 445.12 | G58: 6649.38 | H58: 300 | I58: 400 | K58: 0 | L58: 0 | O58: ORTEGA MONROY ALEXIS | P58: 12520.1 | R58: 12520.1 | S58: imile aifa
A59: 1 | B59: agosto | C59: 8 | D59: MORA GUTIERREZ IAN FABIAN | E59: 4725.6 | F59: - | G59: 6136.87 | H59: 200 | K59: 0 | L59: 0 | O59: MORA GUTIERREZ IAN FABIAN | P59: 11062.47 | R59: 11062.47 | S59: AIFA
A60: 1 | B60: agosto | C60: 8 | D60: BRENIS AMADOR DANNYEL ANTONIO | E60: 4410.84 | F60: 582.17 | G60: 6412.36 | H60: 300 | K60: 2405.49 | L60: 96.22 | O60: BRENIS AMADOR DANNYEL ANTONIO | P60: 14207.08 | R60: 14207.08 | S60: CDMX
A61: 1 | B61: agosto | C61: 8 | D61: PELAEZ CASTELLANOS MARIO RUBEN | E61: 5016.75 | F61: - | G61: 6822.39 | H61: 200 | I61: 378.05 | K61: 0 | L61: 0 | O61: PELAEZ CASTELLANOS MARIO RUBEN | P61: 12417.19 | R61: 12417.19 | S61: DHL
A62: 1 | B62: agosto | C62: 8 | D62: PEREZ BELMONT ANA CRISTINA | E62: 4725.6 | F62: 724.7 | G62: 6883.31 | H62: 300 | I62: 420 | K62: 0 | L62: 0 | O62: PEREZ BELMONT ANA CRISTINA | P62: 13053.61 | R62: 13053.61 | S62: CDMX
A63: 1 | B63: agosto | C63: 8 | D63: CASTELLANOS JIMENEZ SHELSY VALERIA | E63: 4725.6 | F63: 110 | G63: 6250.17 | H63: 300 | I63: 380 | K63: 0 | L63: 0 | O63: CASTELLANOS JIMENEZ SHELSY VALERIA | P63: 11765.77 | R63: 11765.77 | S63: Staff
A64: 1 | B64: agosto | C64: 8 | D64: REYES GARCIA DANIELA | E64: 4725.6 | F64: 715.12 | G64: 6873.45 | H64: 300 | K64: 4714.66 | L64: 188.59 | O64: REYES GARCIA DANIELA | P64: 17517.42 | R64: 17517.42 | S64: Staff
A65: 1 | B65: agosto | C65: 8 | D65: GUILLEN ROJAS ADRIAN ZURIEL | E65: 4725.6 | F65: 60.7 | G65: 6508.58 | H65: 766.05 | K65: 0 | L65: 0 | O65: GUILLEN ROJAS ADRIAN ZURIEL | P65: 12060.93 | R65: 12060.93 | S65: Amazon 2
A66: 1 | B66: agosto | C66: 8 | D66: HERNANDEZ MARTINEZ ALMA LILIA | E66: 4725.6 | F66: 447.12 | G66: 6597.41 | H66: 350 | J66: 600 | K66: 2774.4 | L66: 134.98 | O66: HERNANDEZ MARTINEZ ALMA LILIA | P66: 15629.51 | R66: 15629.51 | S66: Staff
A67: 1 | B67: agosto | C67: 8 | D67: JIMENEZ CORTES JOSE ALFREDO | E67: 4999.95 | F67: - | G67: 6472.04 | H67: 300 | J67: 720 | K67: 4230.93 | L67: 198.04 | O67: JIMENEZ CORTES JOSE ALFREDO | P67: 16920.96 | R67: 16920.96 | S67: Tránsito
A68: 1 | B68: agosto | C68: 8 | D68: MARTINEZ LOPEZ LUIS HECTOR | E68: 4399.92 | F68: 879.98 | G68: 6881.29 | H68: 200 | K68: 0 | L68: 0 | O68: MARTINEZ LOPEZ LUIS HECTOR | P68: 12361.19 | R68: 12361.19 | S68: imile aifa
A69: 1 | B69: agosto | C69: 8 | D69: HERNANDEZ HERNANDEZ ANGEL ENRIQUE | E69: 4433.24 | F69: 1365.81 | G69: 7247.19 | H69: 200 | K69: 0 | L69: 0 | O69: HERNANDEZ HERNANDEZ ANGEL ENRIQUE | P69: 13246.24 | R69: 13246.24 | S69: imile aifa
A70: 1 | B70: agosto | C70: 8 | D70: COYOLI ALBARRAN JORGE ALBERTO | E70: 4410.56 | F70: 80 | G70: 6203.96 | H70: 714.98 | K70: 0 | L70: 0 | O70: COYOLI ALBARRAN JORGE ALBERTO | P70: 11409.5 | R70: 11409.5 | S70: Amazon 2
A71: 1 | B71: agosto | C71: 8 | D71: PALOMO GUILLERMO JORGE ALAN | E71: 6500 | F71: 1060 | G71: 9454.15 | H71: 350 | J71: 880 | K71: 4340.12 | L71: 208.8 | O71: PALOMO GUILLERMO JORGE ALAN | P71: 22793.07 | R71: 22793.07 | S71: imile aifa
A72: 1 | B72: agosto | C72: 8 | D72: MEJIA SILVESTRE JAZAEL | E72: 5000 | F72: 300 | G72: 6781.1 | H72: 300 | J72: 500 | K72: 1250 | L72: 70 | O72: MEJIA SILVESTRE JAZAEL | P72: 14201.1 | R72: 14201.1 | S72: imile aifa
A73: 1 | B73: agosto | C73: 8 | D73: CABALLERO CAMACHO JUAN AXEL | E73: 4749.9 | F73: 249.98 | G73: 6424.04 | I73: 380 | K73: 0 | L73: 0 | O73: CABALLERO CAMACHO JUAN AXEL | P73: 11803.92 | R73: 11803.92 | S73: toluca
A74: 1 | B74: agosto | C74: 8 | D74: GONZALEZ ALARCON MARIO ANDRES | E74: 4433.24 | F74: 382.33 | G74: 6234.2 | H74: 200 | K74: 0 | L74: 0 | O74: GONZALEZ ALARCON MARIO ANDRES | P74: 11249.77 | R74: 11249.77 | S74: imile aifa
A75: 1 | B75: agosto | C75: 8 | D75: GARCIA PACHECO ORLANDO ALEXIS | E75: 4749.9 | F75: 309.15 | G75: 6484.98 | H75: 200 | I75: 380 | K75: 0 | L75: 0 | O75: GARCIA PACHECO ORLANDO ALEXIS | P75: 12124.03 | R75: 12124.03 | S75: imile aifa
A76: 1 | B76: agosto | C76: 8 | D76: GUERRERO ROSAS CAMILO | E76: 5000 | F76: 992 | G76: 7493.86 | H76: 300 | I76: 440 | K76: 0 | L76: 0 | O76: GUERRERO ROSAS CAMILO | P76: 14225.86 | R76: 14225.86 | S76: Veracruz
A77: 1 | B77: agosto | C77: 8 | D77: MEDINA ALMARAZ EMANUEL ALBERTO | E77: 4749.9 | F77: 629.15 | G77: 6814.58 | H77: 200 | K77: 0 | L77: 0 | O77: MEDINA ALMARAZ EMANUEL ALBERTO | P77: 12393.63 | R77: 12393.63 | S77: imile aifa
A78: 1 | B78: agosto | C78: 8 | D78: CORDERO RODRIGUEZ BRAULIO ANGEL | E78: 4725.6 | F78: - | G78: 6136.87 | H78: 200 | K78: 0 | L78: 0 | O78: CORDERO RODRIGUEZ BRAULIO ANGEL | P78: 11062.47 | R78: 11062.47 | S78: Cdmx
A79: 1 | B79: agosto | C79: 8 | D79: GALLARDO SILES DIANA ITZEL | E79: 4725.6 | F79: - | G79: 6136.87 | H79: 300 | K79: 0 | L79: 0 | O79: GALLARDO SILES DIANA ITZEL | P79: 11162.47 | R79: 11162.47 | S79: staff
A80: 1 | B80: agosto | C80: 8 | D80: PALOMARES HINOJOSA MONICA | E80: 4749.9 | F80: 225.12 | G80: 6398.43 | H80: 300 | I80: 380 | K80: 0 | L80: 0 | O80: PALOMARES HINOJOSA MONICA | P80: 12053.45 | R80: 12053.45 | S80: Toluca
A81: 1 | B81: agosto | C81: 8 | D81: LOPEZ RODRIGUEZ IRIS JOSELINE | E81: 1583.34 | F81: 2394.52 | G81: 4097.2 | K81: 0 | L81: 0 | O81: LOPEZ RODRIGUEZ IRIS JOSELINE | P81: 8075.06 | R81: 8075.06 | S81: imile aifa
A82: 1 | B82: agosto | C82: 8 | D82: HERNANDEZ ESTRADA PEDRO JESUS | E82: 0 | F82: 2231.5 | G82: 2298.45 | H82: - | K82: 0 | L82: 0 | O82: HERNANDEZ ESTRADA PEDRO JESUS | P82: 4529.95 | R82: 4529.95 | S82: Amazon 1
A83: 1 | B83: agosto | C83: 8 | D83: ARCEO GUZMAN VIOLETA ELIDETH | E83: 4749.9 | F83: 390.33 | G83: 6568.6 | H83: 200 | I83: 380 | K83: 0 | L83: 0 | O83: ARCEO GUZMAN VIOLETA ELIDETH | P83: 12288.83 | R83: 12288.83 | S83: imile aifa
A84: 1 | B84: agosto | C84: 8 | D84: REYES HERNANDEZ GERARDO | E84: 4725.6 | F84: - | G84: 6446.05 | H84: 766.05 | K84: 0 | L84: 0 | O84: REYES HERNANDEZ GERARDO | P84: 11937.7 | R84: 11937.7 | S84: Estafeta
A85: 1 | B85: agosto | C85: 8 | D85: SANCHEZ SANCHEZ LAURA PAULINA | E85: 4750.05 | F85: 950.01 | G85: 7145.25 | I85: 480 | J85: 480 | K85: 866.67 | L85: 53.87 | O85: SANCHEZ SANCHEZ LAURA PAULINA | P85: 14725.85 | R85: 14725.85 | S85: imile aifa
A86: 1 | B86: agosto | C86: 8 | D86: SOLORZANO SORIANO ADOLFO | E86: 4116.71 | F86: 380.34 | G86: 5906.15 | I86: 329.33 | K86: 0 | L86: 0 | O86: SOLORZANO SORIANO ADOLFO | P86: 10732.53 | R86: 10732.53 | S86: imile aifa
A87: 1 | B87: agosto | C87: 8 | D87: OTERO PEÑALOZA DANIELA | E87: 4725.6 | F87: - | G87: 6136.87 | K87: 4774.4 | L87: 190.98 | O87: OTERO PEÑALOZA DANIELA | P87: 15827.85 | R87: 15827.85 | S87: STAFF
A88: 1 | B88: agosto | C88: 8 | D88: PINEDA LOPEZ WILBER RUBEN | E88: 2850 | F88: 1587.68 | G88: 4570.81 | K88: 0 | L88: 0 | O88: PINEDA LOPEZ WILBER RUBEN | P88: 9008.49 | R88: 9008.49 | S88: imile aifa
A89: 1 | B89: agosto | C89: 8 | D89: HERNANDEZ RIVERA GERARDO | E89: 4750.05 | F89: 309.17 | G89: 6485.19 | I89: 380 | K89: 0 | L89: 0 | O89: HERNANDEZ RIVERA GERARDO | P89: 11924.41 | R89: 11924.41 | S89: imile aifa
A90: 1 | B90: agosto | C90: 8 | D90: SILVA SANCHEZ JAVIER | E90: 4750.05 | F90: 304.67 | G90: 6480.55 | I90: 380 | K90: 0 | L90: 0 | O90: SILVA SANCHEZ JAVIER | P90: 11915.27 | R90: 11915.27 | S90: imile aifa
A91: 1 | B91: agosto | C91: 8 | D91: GRAJALES OCHOA JOAN | E91: 5000 | F91: - | G91: 6799.23 | J91: 560 | K91: 2226.64 | L91: 111.47 | O91: GRAJALES OCHOA JOAN | P91: 14697.34 | R91: 14697.34 | S91: Veracruz
A92: 1 | B92: agosto | C92: 8 | D92: ARAGON BEDWELL HAZEL | E92: 4750.01 | F92: 220.12 | G92: 6393.41 | K92: 0 | L92: 0 | O92: ARAGON BEDWELL HAZEL | P92: 11363.54 | R92: 11363.54 | S92: staff
A93: 1 | B93: agosto | C93: 8 | D93: MORALES PICHARDO MIREN JOYCE | E93: 4750.01 | F93: 305.67 | G93: 6481.52 | K93: 0 | L93: 0 | O93: MORALES PICHARDO MIREN JOYCE | P93: 11537.2 | R93: 11537.2 | S93: imile aifa
A94: 1 | B94: agosto | C94: 8 | D94: GARCIA GARCIA JUAN MANUEL | E94: 4433.34 | F94: 224 | G94: 6071.24 | K94: 0 | L94: 0 | O94: GARCIA GARCIA JUAN MANUEL | P94: 10728.58 | R94: 10728.58 | S94: imile aifa
A95: 1 | B95: agosto | C95: 8 | D95: LOPEZ FERNANDEZ JOSEFINA | E95: 4725.6 | F95: 2791.12 | G95: 9011.73 | J95: 560 | K95: 46.94 | L95: 24.28 | O95: LOPEZ FERNANDEZ JOSEFINA | P95: 17159.67 | R95: 17159.67 | S95: Veracruz
A96: 1 | B96: agosto | C96: 8 | D96: ISLAS PRIETO LUIS HECTOR | E96: 4750.01 | F96: 220.12 | G96: 6393.41 | I96: 380 | K96: 0 | L96: 0 | O96: ISLAS PRIETO LUIS HECTOR | P96: 11743.54 | R96: 11743.54 | S96: imile aifa
A97: 1 | B97: agosto | C97: 8 | D97: LLAMAS MANCILLA MARIBEL | E97: 4725.6 | F97: 220 | G97: 6363.47 | I97: 378.05 | K97: 0 | L97: 0 | O97: LLAMAS MANCILLA MARIBEL | P97: 11687.12 | R97: 11687.12 | S97: staff
A98: 1 | B98: agosto | C98: 8 | D98: ROMERO SANCHEZ HUGO ARMANDO | E98: 4750 | F98: 224 | G98: 6397.4 | K98: 0 | L98: 0 | O98: ROMERO SANCHEZ HUGO ARMANDO | P98: 11371.4 | R98: 11371.4 | S98: imile aifa
A99: 1 | B99: agosto | C99: 8 | D99: SERVIN MALDONADO EVELIN PAOLA | E99: 4725.6 | F99: 225.2 | G99: 6368.83 | I99: 378.05 | K99: 0 | L99: 0 | O99: SERVIN MALDONADO EVELIN PAOLA | P99: 11697.68 | R99: 11697.68 | S99: Cdmx
A100: 1 | B100: agosto | C100: 8 | D100: ZUÑIGA RAMIREZ ALFONSO FRANCISCO | E100: 4116.67 | F100: 190 | G100: 5525.63 | I100: 329.33 | K100: 0 | L100: 0 | O100: ZUÑIGA RAMIREZ ALFONSO FRANCISCO | P100: 10161.63 | R100: 10161.63 | S100: imile aifa
...

Sheet emitidas
A1: TipoCambio | B1: Moneda | C1: ReceptorNombre | D1: Descripcion | E1: Importe | F1: DescuentoConcepto | G1: REFERENCIA | H1: ADUANA | I1: CC | J1: TIPO | K1: MONTO
B2: MXN | C2: PROMINENT FLUID CONTROLS DE MEXICO | D2: TRANSPORTE | E2: 4150 | F2: 0 | G2: JMA6000224 | H2: TRANSITO | I2: {=INDEX(CC!C:C,MATCH(1,(CC!A:A=H2)*(CC!B:B=J2),0))} -> 602 | J2: PROPIOS | K2: 4150
B3: MXN | C3: CIPSA INDUSTRIAS | D3: CAPTURA DE VUCEM | E3: 339.06 | F3: 0 | G3: JIT6111043 | H3: TOLUCA | I3: {=INDEX(CC!C:C,MATCH(1,(CC!A:A=H3)*(CC!B:B=J3),0))} -> 1002 | J3: PROPIOS | K3: 339.06
C4: CIPSA INDUSTRIAS | D4: MANIFESTACION DE VALOR | E4: 1500 | F4: 0 | G4: JIT6111043 | H4: TOLUCA | I4: {=INDEX(CC!C:C,MATCH(1,(CC!A:A=H4)*(CC!B:B=J4),0))} -> 1002 | J4: PROPIOS | K4: 1500
C5: CIPSA INDUSTRIAS | D5: MANIOBRAS AA | E5: 4305.53 | F5: 0 | G5: JIT6111043 | H5: TOLUCA | I5: {=INDEX(CC!C:C,MATCH(1,(CC!A:A=H5)*(CC!B:B=J5),0))} -> 1002 | J5: PROPIOS | K5: 4305.53
C6: CIPSA INDUSTRIAS | D6: CONTRAPRESTACIÓN | E6: 36.29 | F6: 0 | G6: JIT6111043 | H6: TOLUCA | I6: {=INDEX(CC!C:C,MATCH(1,(CC!A:A=H6)*(CC!B:B=J6),0))} -> 1002 | J6: PROPIOS | K6: 36.29
C7: CIPSA INDUSTRIAS | D7: ASESORIA ADUANAL | E7: 4666.05 | F7: 0 | G7: JIT6111043 | H7: TOLUCA | I7: {=INDEX(CC!C:C,MATCH(1,(CC!A:A=H7)*(CC!B:B=J7),0))} -> 1002 | J7: PROPIOS | K7: 4666.05
B8: MXN | C8: JARB Y ASOCIADOS | D8: MANIFESTACION DE VALOR | E8: 1000 | F8: 0 | G8: ARA6000161 | H8: AIFA | I8: {=INDEX(CC!C:C,MATCH(1,(CC!A:A=H8)*(CC!B:B=J8),0))} -> 902 | J8: PROPIOS | K8: 1000
C9: JARB Y ASOCIADOS | D9: CONTRAPRESTACIÓN | E9: 30 | F9: 0 | G9: ARA6000161 | H9: AIFA | I9: {=INDEX(CC!C:C,MATCH(1,(CC!A:A=H9)*(CC!B:B=J9),0))} -> 902 | J9: PROPIOS | K9: 30
B10: MXN | C10: B. BRAUN MEDICAL DE MEXICO | D10: TRANSPORTE | E10: 4600 | F10: 0 | G10: JMA6000219 | H10: TRANSITO | I10: {=INDEX(CC!C:C,MATCH(1,(CC!A:A=H10)*(CC!B:B=J10),0))} -> 602 | J10: PROPIOS | K10: 4600
B11: MXN | C11: EDITORIAL PANINI MEXICO | D11: CAPTURA DE VUCEM | E11: 324.5 | F11: 0 | G11: JMA6000209 | H11: CDMX | I11: {=INDEX(CC!C:C,MATCH(1,(CC!A:A=H11)*(CC!B:B=J11),0))} -> 1502 | J11: PROPIOS | K11: 324.5
C12: EDITORIAL PANINI MEXICO | D12: SERVICIOS COMPLEMENTARIOS | E12: 3461.42 | F12: 0 | G12: JMA6000209 | H12: CDMX | I12: {=INDEX(CC!C:C,MATCH(1,(CC!A:A=H12)*(CC!B:B=J12),0))} -> 1502 | J12: PROPIOS | K12: 3461.42
C13: EDITORIAL PANINI MEXICO | D13: CONTRAPRESTACIÓN | E13: 32.44 | F13: 0 | G13: JMA6000209 | H13: CDMX | I13: {=INDEX(CC!C:C,MATCH(1,(CC!A:A=H13)*(CC!B:B=J13),0))} -> 1502 | J13: PROPIOS | K13: 32.44
C14: EDITORIAL PANINI MEXICO | D14: ASESORIA ADUANAL | E14: 4597.2 | F14: 0 | G14: JMA6000209 | H14: CDMX | I14: {=INDEX(CC!C:C,MATCH(1,(CC!A:A=H14)*(CC!B:B=J14),0))} -> 1502 | J14: PROPIOS | K14: 4597.2
A15: 17.3288 | B15: USD | C15: IMILE DELIVERY SERVICES MEXICO | D15: SERVICIO DE MANIOBRA | E15: 22880 | F15: 0 | G15: IMILE JULIO 1 | H15: IMILE AIFA | I15: {=INDEX(CC!C:C,MATCH(1,(CC!A:A=H15)*(CC!B:B=J15),0))} -> 1402 | J15: PROPIOS | K15: =(E15-F15)*$A$15 -> 396482.94
C16: IMILE DELIVERY SERVICES MEXICO | D16: RECONOCIMIENTO ADUANERO | E16: 5130 | F16: 0 | G16: IMILE JULIO 1 | H16: IMILE AIFA | I16: {=INDEX(CC!C:C,MATCH(1,(CC!A:A=H16)*(CC!B:B=J16),0))} -> 1402 | J16: PROPIOS | K16: =(E16-F16)*$A$15 -> 88896.744
C17: IMILE DELIVERY SERVICES MEXICO | D17: CANDADOS | E17: 1090 | F17: 0 | G17: IMILE JULIO 1 | H17: IMILE AIFA | I17: {=INDEX(CC!C:C,MATCH(1,(CC!A:A=H17)*(CC!B:B=J17),0))} -> 1402 | J17: PROPIOS | K17: =(E17-F17)*$A$15 -> 18888.392
B18: MXN | C18: CARGOTECNIA EQUIPOS | D18: COORDINACION DE EMBARQUE | E18: 1695.33 | F18: 0 | G18: JMA6000204 | H18: CDMX | I18: {=INDEX(CC!C:C,MATCH(1,(CC!A:A=H18)*(CC!B:B=J18),0))} -> 1502 | J18: PROPIOS | K18: 1695.33
C19: CARGOTECNIA EQUIPOS | D19: SERVICIOS COMPLEMENTARIOS | E19: 2797.05 | F19: 0 | G19: JMA6000204 | H19: CDMX | I19: {=INDEX(CC!C:C,MATCH(1,(CC!A:A=H19)*(CC!B:B=J19),0))} -> 1502 | J19: PROPIOS | K19: 2797.05
C20: CARGOTECNIA EQUIPOS | D20: MANIOBRAS AA | E20: 14348.31 | F20: 0 | G20: JMA6000204 | H20: CDMX | I20: {=INDEX(CC!C:C,MATCH(1,(CC!A:A=H20)*(CC!B:B=J20),0))} -> 1503 | J20: TERCEROS | K20: 14348.31
C21: CARGOTECNIA EQUIPOS | D21: PREVIO AA | E21: 1488 | F21: 0 | G21: JMA6000204 | H21: CDMX | I21: {=INDEX(CC!C:C,MATCH(1,(CC!A:A=H21)*(CC!B:B=J21),0))} -> 1503 | J21: TERCEROS | K21: 1488
C22: CARGOTECNIA EQUIPOS | D22: REVALIDACION AA | E22: 2835 | F22: 0 | G22: JMA6000204 | H22: CDMX | I22: {=INDEX(CC!C:C,MATCH(1,(CC!A:A=H22)*(CC!B:B=J22),0))} -> 1503 | J22: TERCEROS | K22: 2835
C23: CARGOTECNIA EQUIPOS | D23: CONTRAPRESTACIÓN | E23: 35 | F23: 0 | G23: JMA6000204 | H23: CDMX | I23: {=INDEX(CC!C:C,MATCH(1,(CC!A:A=H23)*(CC!B:B=J23),0))} -> 1502 | J23: PROPIOS | K23: 35
C24: CARGOTECNIA EQUIPOS | D24: ASESORIA ADUANAL | E24: 1468.45 | F24: 0 | G24: JMA6000204 | H24: CDMX | I24: {=INDEX(CC!C:C,MATCH(1,(CC!A:A=H24)*(CC!B:B=J24),0))} -> 1502 | J24: PROPIOS | K24: 1468.45
B25: MXN | C25: EQUIPOS ESPECIALES MPOWER | D25: COORDINACION DE EMBARQUE | E25: 1555.35 | F25: 0 | G25: LAI2602712 | H25: LAZARO | I25: {=INDEX(CC!C:C,MATCH(1,(CC!A:A=H25)*(CC!B:B=J25),0))} -> 1102 | J25: PROPIOS | K25: 1555.35
C26: EQUIPOS ESPECIALES MPOWER | D26: CAPTURA DE VUCEM | E26: 339.06 | F26: 0 | G26: LAI2602712 | H26: LAZARO | I26: {=INDEX(CC!C:C,MATCH(1,(CC!A:A=H26)*(CC!B:B=J26),0))} -> 1102 | J26: PROPIOS | K26: 339.06
C27: EQUIPOS ESPECIALES MPOWER | D27: MANIOBRAS AA | E27: 9563.79 | F27: 0 | G27: LAI2602712 | H27: LAZARO | I27: {=INDEX(CC!C:C,MATCH(1,(CC!A:A=H27)*(CC!B:B=J27),0))} -> 1103 | J27: TERCEROS | K27: 9563.79
C28: EQUIPOS ESPECIALES MPOWER | D28: CONTRAPRESTACIÓN | E28: 36.29 | F28: 0 | G28: LAI2602712 | H28: LAZARO | I28: {=INDEX(CC!C:C,MATCH(1,(CC!A:A=H28)*(CC!B:B=J28),0))} -> 1102 | J28: PROPIOS | K28: 36.29
C29: EQUIPOS ESPECIALES MPOWER | D29: ASESORIA ADUANAL | E29: 7123.5 | F29: 0 | G29: LAI2602712 | H29: LAZARO | I29: {=INDEX(CC!C:C,MATCH(1,(CC!A:A=H29)*(CC!B:B=J29),0))} -> 1102 | J29: PROPIOS | K29: 7123.5
C30: EQUIPOS ESPECIALES MPOWER | D30: ENTREGA DE LLENADO Y VACIO AA | E30: 3000 | F30: 0 | G30: LAI2602712 | H30: LAZARO | I30: {=INDEX(CC!C:C,MATCH(1,(CC!A:A=H30)*(CC!B:B=J30),0))} -> 1103 | J30: TERCEROS | K30: 3000
B31: MXN | C31: PROMINENT FLUID CONTROLS DE MEXICO | D31: COORDINACION DE EMBARQUE | E31: 945.65 | F31: 0 | G31: JMA6000225 | H31: CDMX | I31: {=INDEX(CC!C:C,MATCH(1,(CC!A:A=H31)*(CC!B:B=J31),0))} -> 1502 | J31: PROPIOS | K31: 945.65
C32: PROMINENT FLUID CONTROLS DE MEXICO | D32: CAPTURA DE VUCEM | E32: 362.91 | F32: 0 | G32: JMA6000225 | H32: CDMX | I32: {=INDEX(CC!C:C,MATCH(1,(CC!A:A=H32)*(CC!B:B=J32),0))} -> 1502 | J32: PROPIOS | K32: 362.91
C33: PROMINENT FLUID CONTROLS DE MEXICO | D33: SERVICIOS COMPLEMENTARIOS | E33: 1536.68 | F33: 0 | G33: JMA6000225 | H33: CDMX | I33: {=INDEX(CC!C:C,MATCH(1,(CC!A:A=H33)*(CC!B:B=J33),0))} -> 1502 | J33: PROPIOS | K33: 1536.68
C34: PROMINENT FLUID CONTROLS DE MEXICO | D34: MANIFESTACION DE VALOR | E34: 1500 | F34: 0 | G34: JMA6000225 | H34: CDMX | I34: {=INDEX(CC!C:C,MATCH(1,(CC!A:A=H34)*(CC!B:B=J34),0))} -> 1502 | J34: PROPIOS | K34: 1500
C35: PROMINENT FLUID CONTROLS DE MEXICO | D35: MANIOBRAS AA | E35: 5826.96 | F35: 0 | G35: JMA6000225 | H35: CDMX | I35: {=INDEX(CC!C:C,MATCH(1,(CC!A:A=H35)*(CC!B:B=J35),0))} -> 1503 | J35: TERCEROS | K35: 5826.96
C36: PROMINENT FLUID CONTROLS DE MEXICO | D36: CONTRAPRESTACIÓN | E36: 36.29 | F36: 0 | G36: JMA6000225 | H36: CDMX | I36: {=INDEX(CC!C:C,MATCH(1,(CC!A:A=H36)*(CC!B:B=J36),0))} -> 1502 | J36: PROPIOS | K36: 36.29
C37: PROMINENT FLUID CONTROLS DE MEXICO | D37: ASESORIA ADUANAL | E37: 827.44 | F37: 0 | G37: JMA6000225 | H37: CDMX | I37: {=INDEX(CC!C:C,MATCH(1,(CC!A:A=H37)*(CC!B:B=J37),0))} -> 1502 | J37: PROPIOS | K37: 827.44
B38: MXN | C38: CARGA AEREA CONSOLIDADA | D38: TRANSPORTE | E38: 0.01 | F38: 0 | G38: DHL03082026 | H38: DHL | I38: {=INDEX(CC!C:C,MATCH(1,(CC!A:A=H38)*(CC!B:B=J38),0))} -> 502 | J38: PROPIOS | K38: 0.01
B39: MXN | C39: PROMINENT FLUID CONTROLS DE MEXICO | D39: TRANSPORTE | E39: 4150 | F39: 0 | G39: JMA6000225 | H39: TRANSITO | I39: {=INDEX(CC!C:C,MATCH(1,(CC!A:A=H39)*(CC!B:B=J39),0))} -> 602 | J39: PROPIOS | K39: 4150
B40: MXN | C40: CREATIVA TCH | D40: TRANSPORTE | E40: 8050 | F40: 0 | G40: JML6000215 | H40: LAREDO | I40: {=INDEX(CC!C:C,MATCH(1,(CC!A:A=H40)*(CC!B:B=J40),0))} -> 1302 | J40: PROPIOS | K40: 8050
A41: 17.3288 | B41: USD | C41: IMILE DELIVERY SERVICES MEXICO | D41: SERVICIO EXTRAORDINARIO | E41: 1615 | F41: 0 | G41: IMILE JULIO 3 | H41: IMILE AIFA | I41: {=INDEX(CC!C:C,MATCH(1,(CC!A:A=H41)*(CC!B:B=J41),0))} -> 1402 | J41: PROPIOS | K41: =(E41-F41)*$A$41 -> 27986.012
A42: 17.3288 | B42: USD | C42: IMILE DELIVERY SERVICES MEXICO | D42: GUIAS DESPACHADAS | E42: 94068 | F42: 0 | G42: IMILE JULIO 2 | H42: IMILE AIFA | I42: {=INDEX(CC!C:C,MATCH(1,(CC!A:A=H42)*(CC!B:B=J42),0))} -> 1402 | J42: PROPIOS | K42: =(E42-F42)*$A$41 -> 1630085.6
C43: IMILE DELIVERY SERVICES MEXICO | D43: GUIAS DESPACHADAS | E43: 11816.4 | F43: 0 | G43: IMILE JULIO 2 | H43: IMILE AIFA | I43: {=INDEX(CC!C:C,MATCH(1,(CC!A:A=H43)*(CC!B:B=J43),0))} -> 1402 | J43: PROPIOS | K43: 204764.03
C44: IMILE DELIVERY SERVICES MEXICO | D44: GUIAS DESPACHADAS | E44: 2650.2 | F44: 0 | G44: IMILE JULIO 2 | H44: IMILE AIFA | I44: {=INDEX(CC!C:C,MATCH(1,(CC!A:A=H44)*(CC!B:B=J44),0))} -> 1402 | J44: PROPIOS | K44: 45924.79
A45: 17.4418 | B45: USD | C45: TMM ALMACENADORA | D45: VALIDACION | E45: 5220 | F45: 0 | G45: TAP JULIO | H45: TMM | I45: {=INDEX(CC!C:C,MATCH(1,(CC!A:A=H45)*(CC!B:B=J45),0))} -> 2002 | J45: PROPIOS | K45: =(E45-F45)*$A$45 -> 91046.196
C46: TMM ALMACENADORA | D46: GUIAS DESPACHADAS | E46: 71545.4 | F46: 0 | G46: TAP JULIO | H46: TMM | I46: {=INDEX(CC!C:C,MATCH(1,(CC!A:A=H46)*(CC!B:B=J46),0))} -> 2002 | J46: PROPIOS | K46: =(E46-F46)*$A$45 -> 1247880.6
C47: TMM ALMACENADORA | D47: SERVICIO EXTRAORDINARIO | E47: 2329 | F47: 0 | G47: TAP JULIO | H47: TMM | I47: {=INDEX(CC!C:C,MATCH(1,(CC!A:A=H47)*(CC!B:B=J47),0))} -> 2002 | J47: PROPIOS | K47: =(E47-F47)*$A$45 -> 40621.952
C48: TMM ALMACENADORA | D48: RECONOCIMIENTO ADUANERO | E48: 50 | F48: 0 | G48: TAP JULIO | H48: TMM | I48: {=INDEX(CC!C:C,MATCH(1,(CC!A:A=H48)*(CC!B:B=J48),0))} -> 2002 | J48: PROPIOS | K48: =(E48-F48)*$A$45 -> 872.09
C49: TMM ALMACENADORA | D49: RECTIFICACIONES | E49: 5100 | F49: 0 | G49: TAP JULIO | H49: TMM | I49: {=INDEX(CC!C:C,MATCH(1,(CC!A:A=H49)*(CC!B:B=J49),0))} -> 2002 | J49: PROPIOS | K49: =(E49-F49)*$A$45 -> 88953.18
B50: MXN | C50: B. BRAUN MEDICAL DE MEXICO | D50: CAPTURA DE VUCEM | E50: 209.07 | F50: 0 | G50: JET6010314 | H50: TOLUCA | I50: {=INDEX(CC!C:C,MATCH(1,(CC!A:A=H50)*(CC!B:B=J50),0))} -> 1002 | J50: PROPIOS | K50: 209.07
C51: B. BRAUN MEDICAL DE MEXICO | D51: MANIOBRAS AA | E51: 637.64 | F51: 0 | G51: JET6010314 | H51: TOLUCA | I51: {=INDEX(CC!C:C,MATCH(1,(CC!A:A=H51)*(CC!B:B=J51),0))} -> 1002 | J51: PROPIOS | K51: 637.64
C52: B. BRAUN MEDICAL DE MEXICO | D52: CONTRAPRESTACIÓN | E52: 35 | F52: 0 | G52: JET6010314 | H52: TOLUCA | I52: {=INDEX(CC!C:C,MATCH(1,(CC!A:A=H52)*(CC!B:B=J52),0))} -> 1002 | J52: PROPIOS | K52: 35
C53: B. BRAUN MEDICAL DE MEXICO | D53: ASESORIA ADUANAL | E53: 835.72 | F53: 0 | G53: JET6010314 | H53: TOLUCA | I53: {=INDEX(CC!C:C,MATCH(1,(CC!A:A=H53)*(CC!B:B=J53),0))} -> 1002 | J53: PROPIOS | K53: 835.72
B54: MXN | C54: CONSERVADORES Y QUIMICOS DE MEXICO | D54: CONTRAPRESTACIÓN | E54: 35 | F54: 0 | G54: MAI2606841 | H54: MANZANILLO | I54: {=INDEX(CC!C:C,MATCH(1,(CC!A:A=H54)*(CC!B:B=J54),0))} -> 1202 | J54: PROPIOS | K54: 35
C55: CONSERVADORES Y QUIMICOS DE MEXICO | D55: ASESORIA ADUANAL | E55: 4520.88 | F55: 0 | G55: MAI2606841 | H55: MANZANILLO | I55: {=INDEX(CC!C:C,MATCH(1,(CC!A:A=H55)*(CC!B:B=J55),0))} -> 1202 | J55: PROPIOS | K55: 4520.88
B56: MXN | C56: CARGOTECNIA EQUIPOS | D56: TRANSPORTE | E56: 2400 | F56: 0 | G56: CJMA6000211 | H56: TRANSITO | I56: {=INDEX(CC!C:C,MATCH(1,(CC!A:A=H56)*(CC!B:B=J56),0))} -> 602 | J56: PROPIOS | K56: 2400
B57: MXN | C57: CARGOTECNIA EQUIPOS | D57: COORDINACION DE EMBARQUE | E57: 1695.33 | F57: 0 | G57: JMA6000211 | H57: CDMX | I57: {=INDEX(CC!C:C,MATCH(1,(CC!A:A=H57)*(CC!B:B=J57),0))} -> 1502 | J57: PROPIOS | K57: 1695.33
C58: CARGOTECNIA EQUIPOS | D58: CAPTURA DE VUCEM | E58: 326.62 | F58: 0 | G58: JMA6000211 | H58: CDMX | I58: {=INDEX(CC!C:C,MATCH(1,(CC!A:A=H58)*(CC!B:B=J58),0))} -> 1502 | J58: PROPIOS | K58: 326.62
C59: CARGOTECNIA EQUIPOS | D59: SERVICIOS COMPLEMENTARIOS | E59: 4933.97 | F59: 0 | G59: JMA6000211 | H59: CDMX | I59: {=INDEX(CC!C:C,MATCH(1,(CC!A:A=H59)*(CC!B:B=J59),0))} -> 1502 | J59: PROPIOS | K59: 4933.97
C60: CARGOTECNIA EQUIPOS | D60: MANIOBRAS AA | E60: 12894.36 | F60: 0 | G60: JMA6000211 | H60: CDMX | I60: {=INDEX(CC!C:C,MATCH(1,(CC!A:A=H60)*(CC!B:B=J60),0))} -> 1503 | J60: TERCEROS | K60: 12894.36
C61: CARGOTECNIA EQUIPOS | D61: PREVIO AA | E61: 1183 | F61: 0 | G61: JMA6000211 | H61: CDMX | I61: {=INDEX(CC!C:C,MATCH(1,(CC!A:A=H61)*(CC!B:B=J61),0))} -> 1503 | J61: TERCEROS | K61: 1183
C62: CARGOTECNIA EQUIPOS | D62: MONTACARGAS AA | E62: 1167.24 | F62: 0 | G62: JMA6000211 | H62: CDMX | I62: {=INDEX(CC!C:C,MATCH(1,(CC!A:A=H62)*(CC!B:B=J62),0))} -> 1502 | J62: PROPIOS | K62: 1167.24
C63: CARGOTECNIA EQUIPOS | D63: REVALIDACION AA | E63: 2835 | F63: 0 | G63: JMA6000211 | H63: CDMX | I63: {=INDEX(CC!C:C,MATCH(1,(CC!A:A=H63)*(CC!B:B=J63),0))} -> 1503 | J63: TERCEROS | K63: 2835
C64: CARGOTECNIA EQUIPOS | D64: CONTRAPRESTACIÓN | E64: 35 | F64: 0 | G64: JMA6000211 | H64: CDMX | I64: {=INDEX(CC!C:C,MATCH(1,(CC!A:A=H64)*(CC!B:B=J64),0))} -> 1502 | J64: PROPIOS | K64: 35
C65: CARGOTECNIA EQUIPOS | D65: ASESORIA ADUANAL | E65: 2590.33 | F65: 0 | G65: JMA6000211 | H65: CDMX | I65: {=INDEX(CC!C:C,MATCH(1,(CC!A:A=H65)*(CC!B:B=J65),0))} -> 1502 | J65: PROPIOS | K65: 2590.33
B66: MXN | C66: B. BRAUN MEDICAL DE MEXICO | D66: COORDINACION DE EMBARQUE | E66: 1800 | F66: 0 | G66: JMA6000219 | H66: CDMX | I66: {=INDEX(CC!C:C,MATCH(1,(CC!A:A=H66)*(CC!B:B=J66),0))} -> 1502 | J66: PROPIOS | K66: 1800
C67: B. BRAUN MEDICAL DE MEXICO | D67: CAPTURA DE VUCEM | E67: 350 | F67: 0 | G67: JMA6000219 | H67: CDMX | I67: {=INDEX(CC!C:C,MATCH(1,(CC!A:A=H67)*(CC!B:B=J67),0))} -> 1502 | J67: PROPIOS | K67: 350
C68: B. BRAUN MEDICAL DE MEXICO | D68: SERVICIOS COMPLEMENTARIOS | E68: 5099.61 | F68: 0 | G68: JMA6000219 | H68: CDMX | I68: {=INDEX(CC!C:C,MATCH(1,(CC!A:A=H68)*(CC!B:B=J68),0))} -> 1502 | J68: PROPIOS | K68: 5099.61
C69: B. BRAUN MEDICAL DE MEXICO | D69: CONTRAPRESTACIÓN | E69: 35 | F69: 0 | G69: JMA6000219 | H69: CDMX | I69: {=INDEX(CC!C:C,MATCH(1,(CC!A:A=H69)*(CC!B:B=J69),0))} -> 1502 | J69: PROPIOS | K69: 35
C70: B. BRAUN MEDICAL DE MEXICO | D70: ASESORIA ADUANAL | E70: 3300 | F70: 0 | G70: JMA6000219 | H70: CDMX | I70: {=INDEX(CC!C:C,MATCH(1,(CC!A:A=H70)*(CC!B:B=J70),0))} -> 1502 | J70: PROPIOS | K70: 3300
B71: MXN | C71: CREATIVA TCH | D71: CAPTURA DE VUCEM | E71: 261.66 | F71: 0 | G71: JML6000215 | H71: LAREDO | I71: {=INDEX(CC!C:C,MATCH(1,(CC!A:A=H71)*(CC!B:B=J71),0))} -> 1302 | J71: PROPIOS | K71: 261.66
C72: CREATIVA TCH | D72: SERVICIOS COMPLEMENTARIOS | E72: 1977.13 | F72: 0 | G72: JML6000215 | H72: LAREDO | I72: {=INDEX(CC!C:C,MATCH(1,(CC!A:A=H72)*(CC!B:B=J72),0))} -> 1302 | J72: PROPIOS | K72: 1977.13
C73: CREATIVA TCH | D73: MANIFESTACION DE VALOR | E73: 2500 | F73: 0 | G73: JML6000215 | H73: LAREDO | I73: {=INDEX(CC!C:C,MATCH(1,(CC!A:A=H73)*(CC!B:B=J73),0))} -> 1302 | J73: PROPIOS | K73: 2500
C74: CREATIVA TCH | D74: AGENTE ADUANAL AMERICANO AA | E74: 5843.74 | F74: 0 | G74: JML6000215 | H74: LAREDO | I74: {=INDEX(CC!C:C,MATCH(1,(CC!A:A=H74)*(CC!B:B=J74),0))} -> 1302 | J74: PROPIOS | K74: 5843.74
C75: CREATIVA TCH | D75: SHIPPER EXPORT | E75: 523.32 | F75: 0 | G75: JML6000215 | H75: LAREDO | I75: {=INDEX(CC!C:C,MATCH(1,(CC!A:A=H75)*(CC!B:B=J75),0))} -> 1302 | J75: PROPIOS | K75: 523.32
C76: CREATIVA TCH | D76: CRUCE FRONTERIZO AA | E76: 2714.98 | F76: 0 | G76: JML6000215 | H76: LAREDO | I76: {=INDEX(CC!C:C,MATCH(1,(CC!A:A=H76)*(CC!B:B=J76),0))} -> 1302 | J76: PROPIOS | K76: 2714.98
C77: CREATIVA TCH | D77: CONTRAPRESTACIÓN | E77: 35 | F77: 0 | G77: JML6000215 | H77: LAREDO | I77: {=INDEX(CC!C:C,MATCH(1,(CC!A:A=H77)*(CC!B:B=J77),0))} -> 1302 | J77: PROPIOS | K77: 35
C78: CREATIVA TCH | D78: ASESORIA ADUANAL | E78: 2286.21 | F78: 0 | G78: JML6000215 | H78: LAREDO | I78: {=INDEX(CC!C:C,MATCH(1,(CC!A:A=H78)*(CC!B:B=J78),0))} -> 1302 | J78: PROPIOS | K78: 2286.21
B79: MXN | C79: PROMINENT FLUID CONTROLS DE MEXICO | D79: COORDINACION DE EMBARQUE | E79: 945.65 | F79: 0 | G79: JMA6000224 | H79: CDMX | I79: {=INDEX(CC!C:C,MATCH(1,(CC!A:A=H79)*(CC!B:B=J79),0))} -> 1502 | J79: PROPIOS | K79: 945.65
C80: PROMINENT FLUID CONTROLS DE MEXICO | D80: CAPTURA DE VUCEM | E80: 362.91 | F80: 0 | G80: JMA6000224 | H80: CDMX | I80: {=INDEX(CC!C:C,MATCH(1,(CC!A:A=H80)*(CC!B:B=J80),0))} -> 1502 | J80: PROPIOS | K80: 362.91
C81: PROMINENT FLUID CONTROLS DE MEXICO | D81: SERVICIOS COMPLEMENTARIOS | E81: 1536.68 | F81: 0 | G81: JMA6000224 | H81: CDMX | I81: {=INDEX(CC!C:C,MATCH(1,(CC!A:A=H81)*(CC!B:B=J81),0))} -> 1502 | J81: PROPIOS | K81: 1536.68
C82: PROMINENT FLUID CONTROLS DE MEXICO | D82: MANIFESTACION DE VALOR | E82: 1500 | F82: 0 | G82: JMA6000224 | H82: CDMX | I82: {=INDEX(CC!C:C,MATCH(1,(CC!A:A=H82)*(CC!B:B=J82),0))} -> 1502 | J82: PROPIOS | K82: 1500
C83: PROMINENT FLUID CONTROLS DE MEXICO | D83: MANIOBRAS AA | E83: 8146.4 | F83: 0 | G83: JMA6000224 | H83: CDMX | I83: {=INDEX(CC!C:C,MATCH(1,(CC!A:A=H83)*(CC!B:B=J83),0))} -> 1503 | J83: TERCEROS | K83: 8146.4
C84: PROMINENT FLUID CONTROLS DE MEXICO | D84: CONTRAPRESTACIÓN | E84: 36.29 | F84: 0 | G84: JMA6000224 | H84: CDMX | I84: {=INDEX(CC!C:C,MATCH(1,(CC!A:A=H84)*(CC!B:B=J84),0))} -> 1502 | J84: PROPIOS | K84: 36.29
C85: PROMINENT FLUID CONTROLS DE MEXICO | D85: ASESORIA ADUANAL | E85: 1037.5 | F85: 0 | G85: JMA6000224 | H85: CDMX | I85: {=INDEX(CC!C:C,MATCH(1,(CC!A:A=H85)*(CC!B:B=J85),0))} -> 1502 | J85: PROPIOS | K85: 1037.5
B86: MXN | C86: SERVICIOS COMERCIALES AMAZON MEXICO | D86: Servicios postales de paqueteo y courrier | E86: 73027.72 | F86: 0 | G86: AMAZON | H86: AMAZON 1 | I86: {=INDEX(CC!C:C,MATCH(1,(CC!A:A=H86)*(CC!B:B=J86),0))} -> 202 | J86: PROPIOS | K86: 73027.72
C87: SERVICIOS COMERCIALES AMAZON MEXICO | D87: Servicios postales de paqueteo y courrier | G87: AMAZON | H87: AMAZON 1 | I87: {=INDEX(CC!C:C,MATCH(1,(CC!A:A=H87)*(CC!B:B=J87),0))} -> 202 | J87: PROPIOS
B88: MXN | C88: CDD CENTRAL DATA DESIGN | D88: COORDINACION DE EMBARQUE | E88: 1800 | F88: 0 | G88: ARA6000158 | H88: AIFA | I88: {=INDEX(CC!C:C,MATCH(1,(CC!A:A=H88)*(CC!B:B=J88),0))} -> 902 | J88: PROPIOS | K88: 1800
C89: CDD CENTRAL DATA DESIGN | D89: CAPTURA DE VUCEM | E89: 350 | F89: 0 | G89: ARA6000158 | H89: AIFA | I89: {=INDEX(CC!C:C,MATCH(1,(CC!A:A=H89)*(CC!B:B=J89),0))} -> 902 | J89: PROPIOS | K89: 350
C90: CDD CENTRAL DATA DESIGN | D90: SERVICIOS COMPLEMENTARIOS | E90: 1800 | F90: 0 | G90: ARA6000158 | H90: AIFA | I90: {=INDEX(CC!C:C,MATCH(1,(CC!A:A=H90)*(CC!B:B=J90),0))} -> 902 | J90: PROPIOS | K90: 1800
C91: CDD CENTRAL DATA DESIGN | D91: CONTRAPRESTACIÓN | E91: 35 | F91: 0 | G91: ARA6000158 | H91: AIFA | I91: {=INDEX(CC!C:C,MATCH(1,(CC!A:A=H91)*(CC!B:B=J91),0))} -> 902 | J91: PROPIOS | K91: 35
C92: CDD CENTRAL DATA DESIGN | D92: ASESORIA ADUANAL | E92: 3300 | F92: 0 | G92: ARA6000158 | H92: AIFA | I92: {=INDEX(CC!C:C,MATCH(1,(CC!A:A=H92)*(CC!B:B=J92),0))} -> 902 | J92: PROPIOS | K92: 3300
B93: MXN | C93: CARGA AEREA CONSOLIDADA | D93: TRANSPORTE | E93: 0.01 | F93: 0 | G93: DHL04082026 | H93: DHL | I93: {=INDEX(CC!C:C,MATCH(1,(CC!A:A=H93)*(CC!B:B=J93),0))} -> 502 | J93: PROPIOS | K93: 0.01
B94: MXN | C94: TRAVEL ESONIC | D94: DISEÑO DE ETIQUETADO Y CONSTANCIA DE CONFORMIDAD | E94: 3000 | F94: 0 | G94: CCDECERT050826 | H94: CDMX | I94: {=INDEX(CC!C:C,MATCH(1,(CC!A:A=H94)*(CC!B:B=J94),0))} -> 1502 | J94: PROPIOS | K94: 3000
C95: TRAVEL ESONIC | D95: CERTIFICADO NOM-001-SCFI-2018 | E95: 26000 | F95: 0 | G95: CCDECERT050826 | H95: CDMX | I95: {=INDEX(CC!C:C,MATCH(1,(CC!A:A=H95)*(CC!B:B=J95),0))} -> 1502 | J95: PROPIOS | K95: 26000
B96: MXN | C96: CREATIVA TCH | D96: COORDINACION DE EMBARQUE | E96: 1695.33 | F96: 0 | G96: JMA6000220 | H96: CDMX | I96: {=INDEX(CC!C:C,MATCH(1,(CC!A:A=H96)*(CC!B:B=J96),0))} -> 1502 | J96: PROPIOS | K96: 1695.33
C97: CREATIVA TCH | D97: CAPTURA DE VUCEM | E97: 326.62 | F97: 0 | G97: JMA6000220 | H97: CDMX | I97: {=INDEX(CC!C:C,MATCH(1,(CC!A:A=H97)*(CC!B:B=J97),0))} -> 1502 | J97: PROPIOS | K97: 326.62
C98: CREATIVA TCH | D98: SERVICIOS COMPLEMENTARIOS | E98: 5749.57 | F98: 0 | G98: JMA6000220 | H98: CDMX | I98: {=INDEX(CC!C:C,MATCH(1,(CC!A:A=H98)*(CC!B:B=J98),0))} -> 1502 | J98: PROPIOS | K98: 5749.57
C99: CREATIVA TCH | D99: MANIFESTACION DE VALOR | E99: 2500 | F99: 0 | G99: JMA6000220 | H99: CDMX | I99: {=INDEX(CC!C:C,MATCH(1,(CC!A:A=H99)*(CC!B:B=J99),0))} -> 1502 | J99: PROPIOS | K99: 2500
C100: CREATIVA TCH | D100: CONTRAPRESTACIÓN | E100: 35 | F100: 0 | G100: JMA6000220 | H100: CDMX | I100: {=INDEX(CC!C:C,MATCH(1,(CC!A:A=H100)*(CC!B:B=J100),0))} -> 1502 | J100: PROPIOS | K100: 35
...

Sheet reglas
A1: ID | B1: EMISOR | C1: PATRÓN | D1: CONCEPTO | E1: TIPO DE BÚSQUEDA
A2: 1 | B2: CUALQUIERA | C2: TARIFA | D2: TRANSPORTES LOCALES | E2: EXACTA
A3: 2 | B3: CUALQUIERA | C3: TARIFA DE CANCELACION | D3: TRANSPORTES LOCALES | E3: EXACTA
A4: 3 | B4: AAACESA, ALMACENES FISCALIZADOS, S.A. DE C.V. | C4: MANEJO POR VALOR | D4: MANIOBRAS | E4: CONTIENE
A5: 4 | B5: AAACESA, ALMACENES FISCALIZADOS, S.A. DE C.V. | C5: ALMACENAJE | D5: MANIOBRAS | E5: CONTIENE
A6: 5 | B6: AAACESA, ALMACENES FISCALIZADOS, S.A. DE C.V. | C6: MANTRANSFER | D6: MANIOBRAS | E6: CONTIENE
A7: 6 | B7: AAACESA, ALMACENES FISCALIZADOS, S.A. DE C.V. | C7: COSTO DE TRANSFERENCIA | D7: MANIOBRAS | E7: CONTIENE
A8: 7 | B8: AAACESA, ALMACENES FISCALIZADOS, S.A. DE C.V. | C8: MANIOBRAS PARA EL RECONOCIMIENTO PREVIO | D8: MANIOBRAS | E8: CONTIENE
A9: 8 | B9: SUALSA | C9: PALETIZADA TOTAL DE TRAILER | D9: MANIOBRAS | E9: CONTIENE
A10: 9 | B10: DHL GLOBAL FORWARDING (MEXICO) | C10: SEPARACION DE EMBARQUES EN DESTINO | D10: MANIOBRAS | E10: CONTIENE
A11: 10 | B11: DHL GLOBAL FORWARDING (MEXICO) | C11: MANEJO EN TERMINAL FORWARDER EN DESTINO | D11: MANIOBRAS | E11: CONTIENE
A12: 11 | B12: DHL EXPRESS MEXICO | C12: * | D12: GUIAS | E12: SOLO EMISOR
A13: 12 | B13: E-LEVEL CLOUD SERVICES | C13: MICROSOFT 365 BUSINESS PREMIUM | D13: LICENCIAS 365 | E13: CONTIENE
... A235: 234 | B235: MARGARITA TERESA LOERA VAZQUEZ | C235: Etiquetas Adhesivas | D235: ETIQUETADO AA | E235: CONTIENE

Sheet CC
A1: cc | B1: tipo | C1: cc
A2: staff | B2: PROPIOS | C2: 102
A3: Amazon 1 | B3: PROPIOS | C3: 202
A4: Amazon 2 | B4: PROPIOS | C4: 302
A5: estafeta | B5: PROPIOS | C5: 402
A6: estafeta | B6: TERCEROS | C6: 403
A7: dhl | B7: PROPIOS | C7: 502
A8: dhl | B8: TERCEROS | C8: 503
A9: Transito | B9: PROPIOS | C9: 602
A10: Transito | B10: TERCEROS | C10: 603
A11: Tijuana | B11: PROPIOS | C11: 702
A12: Tijuana | B12: TERCEROS | C12: 703
A13: Mexicali | B13: PROPIOS | C13: 802
... A35: TMM | B35: TERCEROS | C35: 2003

Sheet recibidas
A1: TipoCambio | B1: Moneda | C1: EmisorNombre | D1: Descripcion | E1: Importe | F1: DescuentoConcepto | G1: ADUANA | H1: CC | I1: TIPO | J1: monto 1 | K1: CONCEPTO PARA CIERRE
A2: 1 | B2: MXN | C2: CONFEDERACION LATINOAMERICANA DE AGENTES ADUANALES | D2: CUOTA MENSUAL | E2: 13480 | F2: 0 | G2: VERACRUZ | H2: {=INDEX(CC!C:C,MATCH(1,(CC!A:A=G2)*(CC!B:B=I2),0))} -> 1702 | I2: PROPIOS | J2: 13480 | K2: =IFERROR(__xludf.DUMMYFUNCTION("IFERROR( INDEX( FILTER( MAP( reglas!$B$2:$B$240, reglas!$C$2:$C$240, reglas!$D$2:$D$240, reglas!$E$2:$E$240, LAMBDA(rEmisor,rPatron,rConcepto,rTipo, IF( AND( OR( UPPER(TRIM(rEmisor))=UPPER(TRIM(C2)), UPPER(TRIM(rEmisor))=""CUALQUIERA"" ), OR( UPPER(TRIM(r"&"Tipo))=""SOLO EMISOR"", AND( UPPER(TRIM(rTipo))=""EXACTA"", UPPER(TRIM(AG2))=UPPER(TRIM(rPatron)) ), AND( OR( UPPER(TRIM(rTipo))=""CONTIENE"", UPPER(TRIM(rTipo))=""COINCIDENCIA"" ), ISNUMBER(SEARCH(UPPER(TRIM(rPatron)),UPPER(TRIM(D2)))) ) ) ), rConcepto, "&""""" ) ) ), MAP( reglas!$B$2:$B$240, reglas!$C$2:$C$240, reglas!$D$2:$D$240, reglas!$E$2:$E$240, LAMBDA(rEmisor,rPatron,rConcepto,rTipo, IF( AND( OR( UPPER(TRIM(rEmisor))=UPPER(TRIM(C2)), UPPER(TRIM(rEmisor))=""CUALQUIERA"" ), OR( UPPER(TRIM(rTipo))=""SOL"&"O EMISOR"", AND( UPPER(TRIM(rTipo))=""EXACTA"", UPPER(TRIM(D2))=UPPER(TRIM(rPatron)) ), AND( OR( UPPER(TRIM(rTipo))=""CONTIENE"", UPPER(TRIM(rTipo))=""COINCIDENCIA"" ), ISNUMBER(SEARCH(UPPER(TRIM(rPatron)),UPPER(TRIM(D2)))) ) ) ), rConcepto, """" ) ) )<>"&""""" ), 1 ), """" )"),"CUOTAS Y SUSCRIPCIONES") -> CUOTAS Y SUSCRIPCIONES
C3: CONFEDERACION LATINOAMERICANA DE AGENTES ADUANALES | D3: CUOTA POR ADUANA, COBRO ADICIONAL POR ADUANA CON SEDES DE CLAA (VERACRUZ,AIFA,MANZANILLO) | E3: 3423 | F3: 0 | G3: VERACRUZ | H3: {=INDEX(CC!C:C,MATCH(1,(CC!A:A=G3)*(CC!B:B=I3),0))} -> 1702 | I3: PROPIOS | J3: 1141 | K3: =IFERROR(__xludf.DUMMYFUNCTION("IFERROR( INDEX( FILTER( MAP( reglas!$B$2:$B$240, reglas!$C$2:$C$240, reglas!$D$2:$D$240, reglas!$E$2:$E$240, LAMBDA(rEmisor,rPatron,rConcepto,rTipo, IF( AND( OR( UPPER(TRIM(rEmisor))=UPPER(TRIM(C3)), UPPER(TRIM(rEmisor))=""CUALQUIERA"" ), OR( UPPER(TRIM(r"&"Tipo))=""SOLO EMISOR"", AND( UPPER(TRIM(rTipo))=""EXACTA"", UPPER(TRIM(AG3))=UPPER(TRIM(rPatron)) ), AND( OR( UPPER(TRIM(rTipo))=""CONTIENE"", UPPER(TRIM(rTipo))=""COINCIDENCIA"" ), ISNUMBER(SEARCH(UPPER(TRIM(rPatron)),UPPER(TRIM(D3)))) ) ) ), rConcepto, "&""""" ) ) ), MAP( reglas!$B$2:$B$240, reglas!$C$2:$C$240, reglas!$D$2:$D$240, reglas!$E$2:$E$240, LAMBDA(rEmisor,rPatron,rConcepto,rTipo, IF( AND( OR( UPPER(TRIM(rEmisor))=UPPER(TRIM(C3)), UPPER(TRIM(rEmisor))=""CUALQUIERA"" ), OR( UPPER(TRIM(rTipo))=""SOL"&"O EMISOR"", AND( UPPER(TRIM(rTipo))=""EXACTA"", UPPER(TRIM(D3))=UPPER(TRIM(rPatron)) ), AND( OR( UPPER(TRIM(rTipo))=""CONTIENE"", UPPER(TRIM(rTipo))=""COINCIDENCIA"" ), ISNUMBER(SEARCH(UPPER(TRIM(rPatron)),UPPER(TRIM(D3)))) ) ) ), rConcepto, """" ) ) )<>"&""""" ), 1 ), """" )"),"CUOTAS Y SUSCRIPCIONES") -> CUOTAS Y SUSCRIPCIONES
C4: CONFEDERACION LATINOAMERICANA DE AGENTES ADUANALES | D4: CUOTA POR ADUANA, COBRO ADICIONAL POR ADUANA CON SEDES DE CLAA (VERACRUZ,AIFA,MANZANILLO) | G4: AIFA | H4: {=INDEX(CC!C:C,MATCH(1,(CC!A:A=G4)*(CC!B:B=I4),0))} -> 902 | I4: PROPIOS | J4: 1141 | K4: =IFERROR(__xludf.DUMMYFUNCTION("IFERROR( INDEX( FILTER( MAP( reglas!$B$2:$B$240, reglas!$C$2:$C$240, reglas!$D$2:$D$240, reglas!$E$2:$E$240, LAMBDA(rEmisor,rPatron,rConcepto,rTipo, IF( AND( OR( UPPER(TRIM(rEmisor))=UPPER(TRIM(C4)), UPPER(TRIM(rEmisor))=""CUALQUIERA"" ), OR( UPPER(TRIM(r"&"Tipo))=""SOLO EMISOR"", AND( UPPER(TRIM(rTipo))=""EXACTA"", UPPER(TRIM(AG4))=UPPER(TRIM(rPatron)) ), AND( OR( UPPER(TRIM(rTipo))=""CONTIENE"", UPPER(TRIM(rTipo))=""COINCIDENCIA"" ), ISNUMBER(SEARCH(UPPER(TRIM(rPatron)),UPPER(TRIM(D4)))) ) ) ), rConcepto, "&""""" ) ) ), MAP( reglas!$B$2:$B$240, reglas!$C$2:$C$240, reglas!$D$2:$D$240, reglas!$E$2:$E$240, LAMBDA(rEmisor,rPatron,rConcepto,rTipo, IF( AND( OR( UPPER(TRIM(rEmisor))=UPPER(TRIM(C4)), UPPER(TRIM(rEmisor))=""CUALQUIERA"" ), OR( UPPER(TRIM(rTipo))=""SOL"&"O EMISOR"", AND( UPPER(TRIM(rTipo))=""EXACTA"", UPPER(TRIM(D4))=UPPER(TRIM(rPatron)) ), AND( OR( UPPER(TRIM(rTipo))=""CONTIENE"", UPPER(TRIM(rTipo))=""COINCIDENCIA"" ), ISNUMBER(SEARCH(UPPER(TRIM(rPatron)),UPPER(TRIM(D4)))) ) ) ), rConcepto, """" ) ) )<>"&""""" ), 1 ), """" )"),"CUOTAS Y SUSCRIPCIONES") -> CUOTAS Y SUSCRIPCIONES
C5: CONFEDERACION LATINOAMERICANA DE AGENTES ADUANALES | D5: CUOTA POR ADUANA, COBRO ADICIONAL POR ADUANA CON SEDES DE CLAA (VERACRUZ,AIFA,MANZANILLO) | G5: MANZANILLO | H5: {=INDEX(CC!C:C,MATCH(1,(CC!A:A=G5)*(CC!B:B=I5),0))} -> 1202 | I5: PROPIOS | J5: 1141 | K5: =IFERROR(__xludf.DUMMYFUNCTION("IFERROR( INDEX( FILTER( MAP( reglas!$B$2:$B$240, reglas!$C$2:$C$240, reglas!$D$2:$D$240, reglas!$E$2:$E$240, LAMBDA(rEmisor,rPatron,rConcepto,rTipo, IF( AND( OR( UPPER(TRIM(rEmisor))=UPPER(TRIM(C5)), UPPER(TRIM(rEmisor))=""CUALQUIERA"" ), OR( UPPER(TRIM(r"&"Tipo))=""SOLO EMISOR"", AND( UPPER(TRIM(rTipo))=""EXACTA"", UPPER(TRIM(AG5))=UPPER(TRIM(rPatron)) ), AND( OR( UPPER(TRIM(rTipo))=""CONTIENE"", UPPER(TRIM(rTipo))=""COINCIDENCIA"" ), ISNUMBER(SEARCH(UPPER(TRIM(rPatron)),UPPER(TRIM(D5)))) ) ) ), rConcepto, "&""""" ) ) ), MAP( reglas!$B$2:$B$240, reglas!$C$2:$C$240, reglas!$D$2:$D$240, reglas!$E$2:$E$240, LAMBDA(rEmisor,rPatron,rConcepto,rTipo, IF( AND( OR( UPPER(TRIM(rEmisor))=UPPER(TRIM(C5)), UPPER(TRIM(rEmisor))=""CUALQUIERA"" ), OR( UPPER(TRIM(rTipo))=""SOL"&"O EMISOR"", AND( UPPER(TRIM(rTipo))=""EXACTA"", UPPER(TRIM(D5))=UPPER(TRIM(rPatron)) ), AND( OR( UPPER(TRIM(rTipo))=""CONTIENE"", UPPER(TRIM(rTipo))=""COINCIDENCIA"" ), ISNUMBER(SEARCH(UPPER(TRIM(rPatron)),UPPER(TRIM(D5)))) ) ) ), rConcepto, """" ) ) )<>"&""""" ), 1 ), """" )"),"CUOTAS Y SUSCRIPCIONES") -> CUOTAS Y SUSCRIPCIONES
B6: MXN | C6: CRISTOFER PAZ JIMENEZ | D6: FLETE LOCAL ADUANA AIFA A CUAUTITLÁN, EDO. MÉX. 04/08/2026. | E6: 11500 | F6: 0 | G6: IMILE AIFA | H6: {=INDEX(CC!C:C,MATCH(1,(CC!A:A=G6)*(CC!B:B=I6),0))} -> 1402 | I6: PROPIOS | J6: 11500 | K6: =IFERROR(__xludf.DUMMYFUNCTION("IFERROR( INDEX( FILTER( MAP( reglas!$B$2:$B$240, reglas!$C$2:$C$240, reglas!$D$2:$D$240, reglas!$E$2:$E$240, LAMBDA(rEmisor,rPatron,rConcepto,rTipo, IF( AND( OR( UPPER(TRIM(rEmisor))=UPPER(TRIM(C6)), UPPER(TRIM(rEmisor))=""CUALQUIERA"" ), OR( UPPER(TRIM(r"&"Tipo))=""SOLO EMISOR"", AND( UPPER(TRIM(rTipo))=""EXACTA"", UPPER(TRIM(AG6))=UPPER(TRIM(rPatron)) ), AND( OR( UPPER(TRIM(rTipo))=""CONTIENE"", UPPER(TRIM(rTipo))=""COINCIDENCIA"" ), ISNUMBER(SEARCH(UPPER(TRIM(rPatron)),UPPER(TRIM(D6)))) ) ) ), rConcepto, "&""""" ) ) ), MAP( reglas!$B$2:$B$240, reglas!$C$2:$C$240, reglas!$D$2:$D$240, reglas!$E$2:$E$240, LAMBDA(rEmisor,rPatron,rConcepto,rTipo, IF( AND( OR( UPPER(TRIM(rEmisor))=UPPER(TRIM(C6)), UPPER(TRIM(rEmisor))=""CUALQUIERA"" ), OR( UPPER(TRIM(rTipo))=""SOL"&"O EMISOR"", AND( UPPER(TRIM(rTipo))=""EXACTA"", UPPER(TRIM(D6))=UPPER(TRIM(rPatron)) ), AND( OR( UPPER(TRIM(rTipo))=""CONTIENE"", UPPER(TRIM(rTipo))=""COINCIDENCIA"" ), ISNUMBER(SEARCH(UPPER(TRIM(rPatron)),UPPER(TRIM(D6)))) ) ) ), rConcepto, """" ) ) )<>"&""""" ), 1 ), """" )"),"TRANSPORTE") -> TRANSPORTE
B7: MXN | C7: SISTEMA UNIFICADO DE MANIOBRAS AEREAS PARA AGENTES ADUANALES | D7: Carga de camión | E7: 3500 | F7: 0 | G7: IMILE AIFA | H7: {=INDEX(CC!C:C,MATCH(1,(CC!A:A=G7)*(CC!B:B=I7),0))} -> 1402 | I7: PROPIOS | J7: 3500 | K7: =IFERROR(__xludf.DUMMYFUNCTION("IFERROR( INDEX( FILTER( MAP( reglas!$B$2:$B$240, reglas!$C$2:$C$240, reglas!$D$2:$D$240, reglas!$E$2:$E$240, LAMBDA(rEmisor,rPatron,rConcepto,rTipo, IF( AND( OR( UPPER(TRIM(rEmisor))=UPPER(TRIM(C7)), UPPER(TRIM(rEmisor))=""CUALQUIERA"" ), OR( UPPER(TRIM(r"&"Tipo))=""SOLO EMISOR"", AND( UPPER(TRIM(rTipo))=""EXACTA"", UPPER(TRIM(AG7))=UPPER(TRIM(rPatron)) ), AND( OR( UPPER(TRIM(rTipo))=""CONTIENE"", UPPER(TRIM(rTipo))=""COINCIDENCIA"" ), ISNUMBER(SEARCH(UPPER(TRIM(rPatron)),UPPER(TRIM(D7)))) ) ) ), rConcepto, "&""""" ) ) ), MAP( reglas!$B$2:$B$240, reglas!$C$2:$C$240, reglas!$D$2:$D$240, reglas!$E$2:$E$240, LAMBDA(rEmisor,rPatron,rConcepto,rTipo, IF( AND( OR( UPPER(TRIM(rEmisor))=UPPER(TRIM(C7)), UPPER(TRIM(rEmisor))=""CUALQUIERA"" ), OR( UPPER(TRIM(rTipo))=""SOL"&"O EMISOR"", AND( UPPER(TRIM(rTipo))=""EXACTA"", UPPER(TRIM(D7))=UPPER(TRIM(rPatron)) ), AND( OR( UPPER(TRIM(rTipo))=""CONTIENE"", UPPER(TRIM(rTipo))=""COINCIDENCIA"" ), ISNUMBER(SEARCH(UPPER(TRIM(rPatron)),UPPER(TRIM(D7)))) ) ) ), rConcepto, """" ) ) )<>"&""""" ), 1 ), """" )"),"MANIOBRAS") -> MANIOBRAS
B8: MXN | C8: CRISTOFER PAZ JIMENEZ | D8: FLETE LOCAL ADUANA AIFA A CUAUTITLÁN, EDO. MÉX. 03/08/2026. | E8: 11500 | F8: 0 | G8: IMILE AIFA | H8: {=INDEX(CC!C:C,MATCH(1,(CC!A:A=G8)*(CC!B:B=I8),0))} -> 1402 | I8: PROPIOS | J8: 11500 | K8: =IFERROR(__xludf.DUMMYFUNCTION("IFERROR( INDEX( FILTER( MAP( reglas!$B$2:$B$240, reglas!$C$2:$C$240, reglas!$D$2:$D$240, reglas!$E$2:$E$240, LAMBDA(rEmisor,rPatron,rConcepto,rTipo, IF( AND( OR( UPPER(TRIM(rEmisor))=UPPER(TRIM(C8)), UPPER(TRIM(rEmisor))=""CUALQUIERA"" ), OR( UPPER(TRIM(r"&"Tipo))=""SOLO EMISOR"", AND( UPPER(TRIM(rTipo))=""EXACTA"", UPPER(TRIM(AG8))=UPPER(TRIM(rPatron)) ), AND( OR( UPPER(TRIM(rTipo))=""CONTIENE"", UPPER(TRIM(rTipo))=""COINCIDENCIA"" ), ISNUMBER(SEARCH(UPPER(TRIM(rPatron)),UPPER(TRIM(D8)))) ) ) ), rConcepto, "&""""" ) ) ), MAP( reglas!$B$2:$B$240, reglas!$C$2:$C$240, reglas!$D$2:$D$240, reglas!$E$2:$E$240, LAMBDA(rEmisor,rPatron,rConcepto,rTipo, IF( AND( OR( UPPER(TRIM(rEmisor))=UPPER(TRIM(C8)), UPPER(TRIM(rEmisor))=""CUALQUIERA"" ), OR( UPPER(TRIM(rTipo))=""SOL"&"O EMISOR"", AND( UPPER(TRIM(rTipo))=""EXACTA"", UPPER(TRIM(D8))=UPPER(TRIM(rPatron)) ), AND( OR( UPPER(TRIM(rTipo))=""CONTIENE"", UPPER(TRIM(rTipo))=""COINCIDENCIA"" ), ISNUMBER(SEARCH(UPPER(TRIM(rPatron)),UPPER(TRIM(D8)))) ) ) ), rConcepto, """" ) ) )<>"&""""" ), 1 ), """" )"),"TRANSPORTE") -> TRANSPORTE
B9: MXN | C9: CRISTOFER PAZ JIMENEZ | D9: FLETE LOCAL ADUANA AIFA A CUAUTITLÁN, EDO. MÉX. 01/08/2026. | E9: 11500 | F9: 0 | G9: IMILE AIFA | H9: {=INDEX(CC!C:C,MATCH(1,(CC!A:A=G9)*(CC!B:B=I9),0))} -> 1402 | I9: PROPIOS | J9: 11500 | K9: =IFERROR(__xludf.DUMMYFUNCTION("IFERROR( INDEX( FILTER( MAP( reglas!$B$2:$B$240, reglas!$C$2:$C$240, reglas!$D$2:$D$240, reglas!$E$2:$E$240, LAMBDA(rEmisor,rPatron,rConcepto,rTipo, IF( AND( OR( UPPER(TRIM(rEmisor))=UPPER(TRIM(C9)), UPPER(TRIM(rEmisor))=""CUALQUIERA"" ), OR( UPPER(TRIM(r"&"Tipo))=""SOLO EMISOR"", AND( UPPER(TRIM(rTipo))=""EXACTA"", UPPER(TRIM(AG9))=UPPER(TRIM(rPatron)) ), AND( OR( UPPER(TRIM(rTipo))=""CONTIENE"", UPPER(TRIM(rTipo))=""COINCIDENCIA"" ), ISNUMBER(SEARCH(UPPER(TRIM(rPatron)),UPPER(TRIM(D9)))) ) ) ), rConcepto, "&""""" ) ) ), MAP( reglas!$B$2:$B$240, reglas!$C$2:$C$240, reglas!$D$2:$D$240, reglas!$E$2:$E$240, LAMBDA(rEmisor,rPatron,rConcepto,rTipo, IF( AND( OR( UPPER(TRIM(rEmisor))=UPPER(TRIM(C9)), UPPER(TRIM(rEmisor))=""CUALQUIERA"" ), OR( UPPER(TRIM(rTipo))=""SOL"&"O EMISOR"", AND( UPPER(TRIM(rTipo))=""EXACTA"", UPPER(TRIM(D9))=UPPER(TRIM(rPatron)) ), AND( OR( UPPER(TRIM(rTipo))=""CONTIENE"", UPPER(TRIM(rTipo))=""COINCIDENCIA"" ), ISNUMBER(SEARCH(UPPER(TRIM(rPatron)),UPPER(TRIM(D9)))) ) ) ), rConcepto, """" ) ) )<>"&""""" ), 1 ), """" )"),"TRANSPORTE") -> TRANSPORTE
A10: 1 | B10: MXN | C10: GOOGLE CLOUD MEXICO | D10: Servicios de workspace | E10: 140 | F10: 0 | G10: STAFF | H10: {=INDEX(CC!C:C,MATCH(1,(CC!A:A=G10)*(CC!B:B=I10),0))} -> 102 | I10: PROPIOS | J10: 140 | K10: =IFERROR(__xludf.DUMMYFUNCTION("IFERROR( INDEX( FILTER( MAP( reglas!$B$2:$B$240, reglas!$C$2:$C$240, reglas!$D$2:$D$240, reglas!$E$2:$E$240, LAMBDA(rEmisor,rPatron,rConcepto,rTipo, IF( AND( OR( UPPER(TRIM(rEmisor))=UPPER(TRIM(C10)), UPPER(TRIM(rEmisor))=""CUALQUIERA"" ), OR( UPPER(TRIM("&"rTipo))=""SOLO EMISOR"", AND( UPPER(TRIM(rTipo))=""EXACTA"", UPPER(TRIM(AG10))=UPPER(TRIM(rPatron)) ), AND( OR( UPPER(TRIM(rTipo))=""CONTIENE"", UPPER(TRIM(rTipo))=""COINCIDENCIA"" ), ISNUMBER(SEARCH(UPPER(TRIM(rPatron)),UPPER(TRIM(D10)))) ) ) ), rConcept"&"o, """" ) ) ), MAP( reglas!$B$2:$B$240, reglas!$C$2:$C$240, reglas!$D$2:$D$240, reglas!$E$2:$E$240, LAMBDA(rEmisor,rPatron,rConcepto,rTipo, IF( AND( OR( UPPER(TRIM(rEmisor))=UPPER(TRIM(C10)), UPPER(TRIM(rEmisor))=""CUALQUIERA"" ), OR( UPPER(TRIM(rTipo))="&"""SOLO EMISOR"", AND( UPPER(TRIM(rTipo))=""EXACTA"", UPPER(TRIM(D10))=UPPER(TRIM(rPatron)) ), AND( OR( UPPER(TRIM(rTipo))=""CONTIENE"", UPPER(TRIM(rTipo))=""COINCIDENCIA"" ), ISNUMBER(SEARCH(UPPER(TRIM(rPatron)),UPPER(TRIM(D10)))) ) ) ), rConcepto, """" )"&" ) )<>"""" ), 1 ), """" )"),"SERVICIO EN LA NUBE") -> SERVICIO EN LA NUBE
B11: MXN | C11: MEGACABLE COMUNICACIONES DE MEXICO | D11: Internet MetroC Facturación del 01 de Agosto al 31 de Agosto de 2026 1060760956 | E11: 6800 | F11: 0 | G11: TOLUCA | H11: {=INDEX(CC!C:C,MATCH(1,(CC!A:A=G11)*(CC!B:B=I11),0))} -> 1002 | I11: PROPIOS | J11: 6800 | K11: =IFERROR(__xludf.DUMMYFUNCTION("IFERROR( INDEX( FILTER( MAP( reglas!$B$2:$B$240, reglas!$C$2:$C$240, reglas!$D$2:$D$240, reglas!$E$2:$E$240, LAMBDA(rEmisor,rPatron,rConcepto,rTipo, IF( AND( OR( UPPER(TRIM(rEmisor))=UPPER(TRIM(C11)), UPPER(TRIM(rEmisor))=""CUALQUIERA"" ), OR( UPPER(TRIM("&"rTipo))=""SOLO EMISOR"", AND( UPPER(TRIM(rTipo))=""EXACTA"", UPPER(TRIM(AG11))=UPPER(TRIM(rPatron)) ), AND( OR( UPPER(TRIM(rTipo))=""CONTIENE"", UPPER(TRIM(rTipo))=""COINCIDENCIA"" ), ISNUMBER(SEARCH(UPPER(TRIM(rPatron)),UPPER(TRIM(D11)))) ) ) ), rConcept"&"o, """" ) ) ), MAP( reglas!$B$2:$B$240, reglas!$C$2:$C$240, reglas!$D$2:$D$240, reglas!$E$2:$E$240, LAMBDA(rEmisor,rPatron,rConcepto,rTipo, IF( AND( OR( UPPER(TRIM(rEmisor))=UPPER(TRIM(C11)), UPPER(TRIM(rEmisor))=""CUALQUIERA"" ), OR( UPPER(TRIM(rTipo))="&"""SOLO EMISOR"", AND( UPPER(TRIM(rTipo))=""EXACTA"", UPPER(TRIM(D11))=UPPER(TRIM(rPatron)) ), AND( OR( UPPER(TRIM(rTipo))=""CONTIENE"", UPPER(TRIM(rTipo))=""COINCIDENCIA"" ), ISNUMBER(SEARCH(UPPER(TRIM(rPatron)),UPPER(TRIM(D11)))) ) ) ), rConcepto, """" )"&" ) )<>"""" ), 1 ), """" )"),"INTERNET") -> INTERNET
B12: MXN | C12: CRISTOFER PAZ JIMENEZ | D12: FLETE LOCAL ADUANA AIFA A CUAUTITLÁN, EDO. MÉX. 03/08/2026. | E12: 11500 | F12: 0 | G12: IMILE AIFA | H12: {=INDEX(CC!C:C,MATCH(1,(CC!A:A=G12)*(CC!B:B=I12),0))} -> 1402 | I12: PROPIOS | J12: 11500 | K12: =IFERROR(__xludf.DUMMYFUNCTION("IFERROR( INDEX( FILTER( MAP( reglas!$B$2:$B$240, reglas!$C$2:$C$240, reglas!$D$2:$D$240, reglas!$E$2:$E$240, LAMBDA(rEmisor,rPatron,rConcepto,rTipo, IF( AND( OR( UPPER(TRIM(rEmisor))=UPPER(TRIM(C12)), UPPER(TRIM(rEmisor))=""CUALQUIERA"" ), OR( UPPER(TRIM("&"rTipo))=""SOLO EMISOR"", AND( UPPER(TRIM(rTipo))=""EXACTA"", UPPER(TRIM(AG12))=UPPER(TRIM(rPatron)) ), AND( OR( UPPER(TRIM(rTipo))=""CONTIENE"", UPPER(TRIM(rTipo))=""COINCIDENCIA"" ), ISNUMBER(SEARCH(UPPER(TRIM(rPatron)),UPPER(TRIM(D12)))) ) ) ), rConcept"&"o, """" ) ) ), MAP( reglas!$B$2:$B$240, reglas!$C$2:$C$240, reglas!$D$2:$D$240, reglas!$E$2:$E$240, LAMBDA(rEmisor,rPatron,rConcepto,rTipo, IF( AND( OR( UPPER(TRIM(rEmisor))=UPPER(TRIM(C12)), UPPER(TRIM(rEmisor))=""CUALQUIERA"" ), OR( UPPER(TRIM(rTipo))="&"""SOLO EMISOR"", AND( UPPER(TRIM(rTipo))=""EXACTA"", UPPER(TRIM(D12))=UPPER(TRIM(rPatron)) ), AND( OR( UPPER(TRIM(rTipo))=""CONTIENE"", UPPER(TRIM(rTipo))=""COINCIDENCIA"" ), ISNUMBER(SEARCH(UPPER(TRIM(rPatron)),UPPER(TRIM(D12)))) ) ) ), rConcepto, """" )"&" ) )<>"""" ), 1 ), """" )"),"TRANSPORTE") -> TRANSPORTE
B13: MXN | C13: CRISTOFER PAZ JIMENEZ | D13: FLETE LOCAL ADUANA AIFA A CUAUTITLÁN, EDO. MÉX. 01/08/2026. | E13: 11500 | F13: 0 | G13: IMILE AIFA | H13: {=INDEX(CC!C:C,MATCH(1,(CC!A:A=G13)*(CC!B:B=I13),0))} -> 1402 | I13: PROPIOS | J13: 11500 | K13: =IFERROR(__xludf.DUMMYFUNCTION("IFERROR( INDEX( FILTER( MAP( reglas!$B$2:$B$240, reglas!$C$2:$C$240, reglas!$D$2:$D$240, reglas!$E$2:$E$240, LAMBDA(rEmisor,rPatron,rConcepto,rTipo, IF( AND( OR( UPPER(TRIM(rEmisor))=UPPER(TRIM(C13)), UPPER(TRIM(rEmisor))=""CUALQUIERA"" ), OR( UPPER(TRIM("&"rTipo))=""SOLO EMISOR"", AND( UPPER(TRIM(rTipo))=""EXACTA"", UPPER(TRIM(AG13))=UPPER(TRIM(rPatron)) ), AND( OR( UPPER(TRIM(rTipo))=""CONTIENE"", UPPER(TRIM(rTipo))=""COINCIDENCIA"" ), ISNUMBER(SEARCH(UPPER(TRIM(rPatron)),UPPER(TRIM(D13)))) ) ) ), rConcept"&"o, """" ) ) ), MAP( reglas!$B$2:$B$240, reglas!$C$2:$C$240, reglas!$D$2:$D$240, reglas!$E$2:$E$240, LAMBDA(rEmisor,rPatron,rConcepto,rTipo, IF( AND( OR( UPPER(TRIM(rEmisor))=UPPER(TRIM(C13)), UPPER(TRIM(rEmisor))=""CUALQUIERA"" ), OR( UPPER(TRIM(rTipo))="&"""SOLO EMISOR"", AND( UPPER(TRIM(rTipo))=""EXACTA"", UPPER(TRIM(D13))=UPPER(TRIM(rPatron)) ), AND( OR( UPPER(TRIM(rTipo))=""CONTIENE"", UPPER(TRIM(rTipo))=""COINCIDENCIA"" ), ISNUMBER(SEARCH(UPPER(TRIM(rPatron)),UPPER(TRIM(D13)))) ) ) ), rConcepto, """" )"&" ) )<>"""" ), 1 ), """" )"),"TRANSPORTE") -> TRANSPORTE
B14: MXN | C14: SISTEMA UNIFICADO DE MANIOBRAS AEREAS PARA AGENTES ADUANALES | D14: Carga de camión | E14: 3500 | F14: 0 | G14: IMILE AIFA | H14: {=INDEX(CC!C:C,MATCH(1,(CC!A:A=G14)*(CC!B:B=I14),0))} -> 1402 | I14: PROPIOS | J14: 3500 | K14: =IFERROR(__xludf.DUMMYFUNCTION("IFERROR( INDEX( FILTER( MAP( reglas!$B$2:$B$240, reglas!$C$2:$C$240, reglas!$D$2:$D$240, reglas!$E$2:$E$240, LAMBDA(rEmisor,rPatron,rConcepto,rTipo, IF( AND( OR( UPPER(TRIM(rEmisor))=UPPER(TRIM(C14)), UPPER(TRIM(rEmisor))=""CUALQUIERA"" ), OR( UPPER(TRIM("&"rTipo))=""SOLO EMISOR"", AND( UPPER(TRIM(rTipo))=""EXACTA"", UPPER(TRIM(AG14))=UPPER(TRIM(rPatron)) ), AND( OR( UPPER(TRIM(rTipo))=""CONTIENE"", UPPER(TRIM(rTipo))=""COINCIDENCIA"" ), ISNUMBER(SEARCH(UPPER(TRIM(rPatron)),UPPER(TRIM(D14)))) ) ) ), rConcept"&"o, """" ) ) ), MAP( reglas!$B$2:$B$240, reglas!$C$2:$C$240, reglas!$D$2:$D$240, reglas!$E$2:$E$240, LAMBDA(rEmisor,rPatron,rConcepto,rTipo, IF( AND( OR( UPPER(TRIM(rEmisor))=UPPER(TRIM(C14)), UPPER(TRIM(rEmisor))=""CUALQUIERA"" ), OR( UPPER(TRIM(rTipo))="&"""SOLO EMISOR"", AND( UPPER(TRIM(rTipo))=""EXACTA"", UPPER(TRIM(D14))=UPPER(TRIM(rPatron)) ), AND( OR( UPPER(TRIM(rTipo))=""CONTIENE"", UPPER(TRIM(rTipo))=""COINCIDENCIA"" ), ISNUMBER(SEARCH(UPPER(TRIM(rPatron)),UPPER(TRIM(D14)))) ) ) ), rConcepto, """" )"&" ) )<>"""" ), 1 ), """" )"),"MANIOBRAS") -> MANIOBRAS
B15: MXN | C15: JORGE ANGEL GOMEZ TERRAZAS | D15: Consultoria Gestión y Estrategia en Negocios | E15: 212500 | F15: 0 | G15: STAFF | H15: {=INDEX(CC!C:C,MATCH(1,(CC!A:A=G15)*(CC!B:B=I15),0))} -> 102 | I15: PROPIOS | K15: =IFERROR(__xludf.DUMMYFUNCTION("IFERROR( INDEX( FILTER( MAP( reglas!$B$2:$B$240, reglas!$C$2:$C$240, reglas!$D$2:$D$240, reglas!$E$2:$E$240, LAMBDA(rEmisor,rPatron,rConcepto,rTipo, IF( AND( OR( UPPER(TRIM(rEmisor))=UPPER(TRIM(C15)), UPPER(TRIM(rEmisor))=""CUALQUIERA"" ), OR( UPPER(TRIM("&"rTipo))=""SOLO EMISOR"", AND( UPPER(TRIM(rTipo))=""EXACTA"", UPPER(TRIM(AG15))=UPPER(TRIM(rPatron)) ), AND( OR( UPPER(TRIM(rTipo))=""CONTIENE"", UPPER(TRIM(rTipo))=""COINCIDENCIA"" ), ISNUMBER(SEARCH(UPPER(TRIM(rPatron)),UPPER(TRIM(D15)))) ) ) ), rConcept"&"o, """" ) ) ), MAP( reglas!$B$2:$B$240, reglas!$C$2:$C$240, reglas!$D$2:$D$240, reglas!$E$2:$E$240, LAMBDA(rEmisor,rPatron,rConcepto,rTipo, IF( AND( OR( UPPER(TRIM(rEmisor))=UPPER(TRIM(C15)), UPPER(TRIM(rEmisor))=""CUALQUIERA"" ), OR( UPPER(TRIM(rTipo))="&"""SOLO EMISOR"", AND( UPPER(TRIM(rTipo))=""EXACTA"", UPPER(TRIM(D15))=UPPER(TRIM(rPatron)) ), AND( OR( UPPER(TRIM(rTipo))=""CONTIENE"", UPPER(TRIM(rTipo))=""COINCIDENCIA"" ), ISNUMBER(SEARCH(UPPER(TRIM(rPatron)),UPPER(TRIM(D15)))) ) ) ), rConcepto, """" )"&" ) )<>"""" ), 1 ), """" )"),"OTRAS ASESORIAS") -> OTRAS ASESORIAS
B16: MXN | C16: BERTHA CORTES CORTES | D16: Servicio de Tráiler Caja 53 FT Eco 32-B realizado el día 02 de Agosto del 2026. Origen: AIFA Destino: Teoloyucan Referencia: IMILE02082026-ECO 32-B | E16: 11500 | F16: 0 | G16: IMILE AIFA | H16: {=INDEX(CC!C:C,MATCH(1,(CC!A:A=G16)*(CC!B:B=I16),0))} -> 1403 | I16: TERCEROS | J16: 11500 | K16: =IFERROR(__xludf.DUMMYFUNCTION("IFERROR( INDEX( FILTER( MAP( reglas!$B$2:$B$240, reglas!$C$2:$C$240, reglas!$D$2:$D$240, reglas!$E$2:$E$240, LAMBDA(rEmisor,rPatron,rConcepto,rTipo, IF( AND( OR( UPPER(TRIM(rEmisor))=UPPER(TRIM(C16)), UPPER(TRIM(rEmisor))=""CUALQUIERA"" ), OR( UPPER(TRIM("&"rTipo))=""SOLO EMISOR"", AND( UPPER(TRIM(rTipo))=""EXACTA"", UPPER(TRIM(AG16))=UPPER(TRIM(rPatron)) ), AND( OR( UPPER(TRIM(rTipo))=""CONTIENE"", UPPER(TRIM(rTipo))=""COINCIDENCIA"" ), ISNUMBER(SEARCH(UPPER(TRIM(rPatron)),UPPER(TRIM(D16)))) ) ) ), rConcept"&"o, """" ) ) ), MAP( reglas!$B$2:$B$240, reglas!$C$2:$C$240, reglas!$D$2:$D$240, reglas!$E$2:$E$240, LAMBDA(rEmisor,rPatron,rConcepto,rTipo, IF( AND( OR( UPPER(TRIM(rEmisor))=UPPER(TRIM(C16)), UPPER(TRIM(rEmisor))=""CUALQUIERA"" ), OR( UPPER(TRIM(rTipo))="&"""SOLO EMISOR"", AND( UPPER(TRIM(rTipo))=""EXACTA"", UPPER(TRIM(D16))=UPPER(TRIM(rPatron)) ), AND( OR( UPPER(TRIM(rTipo))=""CONTIENE"", UPPER(TRIM(rTipo))=""COINCIDENCIA"" ), ISNUMBER(SEARCH(UPPER(TRIM(rPatron)),UPPER(TRIM(D16)))) ) ) ), rConcepto, """" )"&" ) )<>"""" ), 1 ), """" )"),"TRANSPORTE") -> TRANSPORTE
B17: MXN | C17: JORGE ANGEL GOMEZ TERRAZAS | D17: Consultoria Gestión y Estrategia en Negocios | E17: 207500 | F17: 0 | G17: STAFF | H17: {=INDEX(CC!C:C,MATCH(1,(CC!A:A=G17)*(CC!B:B=I17),0))} -> 102 | I17: PROPIOS | J17: 207500 | K17: =IFERROR(__xludf.DUMMYFUNCTION("IFERROR( INDEX( FILTER( MAP( reglas!$B$2:$B$240, reglas!$C$2:$C$240, reglas!$D$2:$D$240, reglas!$E$2:$E$240, LAMBDA(rEmisor,rPatron,rConcepto,rTipo, IF( AND( OR( UPPER(TRIM(rEmisor))=UPPER(TRIM(C17)), UPPER(TRIM(rEmisor))=""CUALQUIERA"" ), OR( UPPER(TRIM("&"rTipo))=""SOLO EMISOR"", AND( UPPER(TRIM(rTipo))=""EXACTA"", UPPER(TRIM(AG17))=UPPER(TRIM(rPatron)) ), AND( OR( UPPER(TRIM(rTipo))=""CONTIENE"", UPPER(TRIM(rTipo))=""COINCIDENCIA"" ), ISNUMBER(SEARCH(UPPER(TRIM(rPatron)),UPPER(TRIM(D17)))) ) ) ), rConcept"&"o, """" ) ) ), MAP( reglas!$B$2:$B$240, reglas!$C$2:$C$240, reglas!$D$2:$D$240, reglas!$E$2:$E$240, LAMBDA(rEmisor,rPatron,rConcepto,rTipo, IF( AND( OR( UPPER(TRIM(rEmisor))=UPPER(TRIM(C17)), UPPER(TRIM(rEmisor))=""CUALQUIERA"" ), OR( UPPER(TRIM(rTipo))="&"""SOLO EMISOR"", AND( UPPER(TRIM(rTipo))=""EXACTA"", UPPER(TRIM(D17))=UPPER(TRIM(rPatron)) ), AND( OR( UPPER(TRIM(rTipo))=""CONTIENE"", UPPER(TRIM(rTipo))=""COINCIDENCIA"" ), ISNUMBER(SEARCH(UPPER(TRIM(rPatron)),UPPER(TRIM(D17)))) ) ) ), rConcepto, """" )"&" ) )<>"""" ), 1 ), """" )"),"OTRAS ASESORIAS") -> OTRAS ASESORIAS
B18: MXN | C18: CRISTOFER PAZ JIMENEZ | D18: FLETE LOCAL ADUANA AIFA A CUAUTITLÁN, EDO. MÉX. 02/08/2026. | E18: 11500 | F18: 0 | G18: IMILE AIFA | H18: {=INDEX(CC!C:C,MATCH(1,(CC!A:A=G18)*(CC!B:B=I18),0))} -> 1402 | I18: PROPIOS | J18: 11500 | K18: =IFERROR(__xludf.DUMMYFUNCTION("IFERROR( INDEX( FILTER( MAP( reglas!$B$2:$B$240, reglas!$C$2:$C$240, reglas!$D$2:$D$240, reglas!$E$2:$E$240, LAMBDA(rEmisor,rPatron,rConcepto,rTipo, IF( AND( OR( UPPER(TRIM(rEmisor))=UPPER(TRIM(C18)), UPPER(TRIM(rEmisor))=""CUALQUIERA"" ), OR( UPPER(TRIM("&"rTipo))=""SOLO EMISOR"", AND( UPPER(TRIM(rTipo))=""EXACTA"", UPPER(TRIM(AG18))=UPPER(TRIM(rPatron)) ), AND( OR( UPPER(TRIM(rTipo))=""CONTIENE"", UPPER(TRIM(rTipo))=""COINCIDENCIA"" ), ISNUMBER(SEARCH(UPPER(TRIM(rPatron)),UPPER(TRIM(D18)))) ) ) ), rConcept"&"o, """" ) ) ), MAP( reglas!$B$2:$B$240, reglas!$C$2:$C$240, reglas!$D$2:$D$240, reglas!$E$2:$E$240, LAMBDA(rEmisor,rPatron,rConcepto,rTipo, IF( AND( OR( UPPER(TRIM(rEmisor))=UPPER(TRIM(C18)), UPPER(TRIM(rEmisor))=""CUALQUIERA"" ), OR( UPPER(TRIM(rTipo))="&"""SOLO EMISOR"", AND( UPPER(TRIM(rTipo))=""EXACTA"", UPPER(TRIM(D18))=UPPER(TRIM(rPatron)) ), AND( OR( UPPER(TRIM(rTipo))=""CONTIENE"", UPPER(TRIM(rTipo))=""COINCIDENCIA"" ), ISNUMBER(SEARCH(UPPER(TRIM(rPatron)),UPPER(TRIM(D18)))) ) ) ), rConcepto, """" )"&" ) )<>"""" ), 1 ), """" )"),"TRANSPORTE") -> TRANSPORTE
A19: 1 | B19: MXN | C19: FEDERAL EXPRESS HOLDINGS (MEXICO) Y COMPAÑIA | D19: Etiquetado | E19: 600 | F19: 478 | G19: TOLUCA | H19: {=INDEX(CC!C:C,MATCH(1,(CC!A:A=G19)*(CC!B:B=I19),0))} -> 1002 | I19: PROPIOS | J19: 122 | K19: =IFERROR(__xludf.DUMMYFUNCTION("IFERROR( INDEX( FILTER( MAP( reglas!$B$2:$B$240, reglas!$C$2:$C$240, reglas!$D$2:$D$240, reglas!$E$2:$E$240, LAMBDA(rEmisor,rPatron,rConcepto,rTipo, IF( AND( OR( UPPER(TRIM(rEmisor))=UPPER(TRIM(C19)), UPPER(TRIM(rEmisor))=""CUALQUIERA"" ), OR( UPPER(TRIM("&"rTipo))=""SOLO EMISOR"", AND( UPPER(TRIM(rTipo))=""EXACTA"", UPPER(TRIM(AG19))=UPPER(TRIM(rPatron)) ), AND( OR( UPPER(TRIM(rTipo))=""CONTIENE"", UPPER(TRIM(rTipo))=""COINCIDENCIA"" ), ISNUMBER(SEARCH(UPPER(TRIM(rPatron)),UPPER(TRIM(D19)))) ) ) ), rConcept"&"o, """" ) ) ), MAP( reglas!$B$2:$B$240, reglas!$C$2:$C$240, reglas!$D$2:$D$240, reglas!$E$2:$E$240, LAMBDA(rEmisor,rPatron,rConcepto,rTipo, IF( AND( OR( UPPER(TRIM(rEmisor))=UPPER(TRIM(C19)), UPPER(TRIM(rEmisor))=""CUALQUIERA"" ), OR( UPPER(TRIM(rTipo))="&"""SOLO EMISOR"", AND( UPPER(TRIM(rTipo))=""EXACTA"", UPPER(TRIM(D19))=UPPER(TRIM(rPatron)) ), AND( OR( UPPER(TRIM(rTipo))=""CONTIENE"", UPPER(TRIM(rTipo))=""COINCIDENCIA"" ), ISNUMBER(SEARCH(UPPER(TRIM(rPatron)),UPPER(TRIM(D19)))) ) ) ), rConcepto, """" )"&" ) )<>"""" ), 1 ), """" )"),"MANIOBRAS") -> MANIOBRAS
C20: FEDERAL EXPRESS HOLDINGS (MEXICO) Y COMPAÑIA | D20: Cambio de Instruccion | E20: 634.54 | F20: 0 | G20: TOLUCA | H20: {=INDEX(CC!C:C,MATCH(1,(CC!A:A=G20)*(CC!B:B=I20),0))} -> 1002 | I20: PROPIOS | J20: 634.54 | K20: =IFERROR(__xludf.DUMMYFUNCTION("IFERROR( INDEX( FILTER( MAP( reglas!$B$2:$B$240, reglas!$C$2:$C$240, reglas!$D$2:$D$240, reglas!$E$2:$E$240, LAMBDA(rEmisor,rPatron,rConcepto,rTipo, IF( AND( OR( UPPER(TRIM(rEmisor))=UPPER(TRIM(C20)), UPPER(TRIM(rEmisor))=""CUALQUIERA"" ), OR( UPPER(TRIM("&"rTipo))=""SOLO EMISOR"", AND( UPPER(TRIM(rTipo))=""EXACTA"", UPPER(TRIM(AG20))=UPPER(TRIM(rPatron)) ), AND( OR( UPPER(TRIM(rTipo))=""CONTIENE"", UPPER(TRIM(rTipo))=""COINCIDENCIA"" ), ISNUMBER(SEARCH(UPPER(TRIM(rPatron)),UPPER(TRIM(D20)))) ) ) ), rConcept"&"o, """" ) ) ), MAP( reglas!$B$2:$B$240, reglas!$C$2:$C$240, reglas!$D$2:$D$240, reglas!$E$2:$E$240, LAMBDA(rEmisor,rPatron,rConcepto,rTipo, IF( AND( OR( UPPER(TRIM(rEmisor))=UPPER(TRIM(C20)), UPPER(TRIM(rEmisor))=""CUALQUIERA"" ), OR( UPPER(TRIM(rTipo))="&"""SOLO EMISOR"", AND( UPPER(TRIM(rTipo))=""EXACTA"", UPPER(TRIM(D20))=UPPER(TRIM(rPatron)) ), AND( OR( UPPER(TRIM(rTipo))=""CONTIENE"", UPPER(TRIM(rTipo))=""COINCIDENCIA"" ), ISNUMBER(SEARCH(UPPER(TRIM(rPatron)),UPPER(TRIM(D20)))) ) ) ), rConcepto, """" )"&" ) )<>"""" ), 1 ), """" )"),"MANIOBRAS") -> MANIOBRAS
C21: FEDERAL EXPRESS HOLDINGS (MEXICO) Y COMPAÑIA | D21: Almacenaje | E21: 634.89 | F21: 0 | G21: TOLUCA | H21: {=INDEX(CC!C:C,MATCH(1,(CC!A:A=G21)*(CC!B:B=I21),0))} -> 1002 | I21: PROPIOS | J21: 634.89 | K21: =IFERROR(__xludf.DUMMYFUNCTION("IFERROR( INDEX( FILTER( MAP( reglas!$B$2:$B$240, reglas!$C$2:$C$240, reglas!$D$2:$D$240, reglas!$E$2:$E$240, LAMBDA(rEmisor,rPatron,rConcepto,rTipo, IF( AND( OR( UPPER(TRIM(rEmisor))=UPPER(TRIM(C21)), UPPER(TRIM(rEmisor))=""CUALQUIERA"" ), OR( UPPER(TRIM("&"rTipo))=""SOLO EMISOR"", AND( UPPER(TRIM(rTipo))=""EXACTA"", UPPER(TRIM(AG21))=UPPER(TRIM(rPatron)) ), AND( OR( UPPER(TRIM(rTipo))=""CONTIENE"", UPPER(TRIM(rTipo))=""COINCIDENCIA"" ), ISNUMBER(SEARCH(UPPER(TRIM(rPatron)),UPPER(TRIM(D21)))) ) ) ), rConcept"&"o, """" ) ) ), MAP( reglas!$B$2:$B$240, reglas!$C$2:$C$240, reglas!$D$2:$D$240, reglas!$E$2:$E$240, LAMBDA(rEmisor,rPatron,rConcepto,rTipo, IF( AND( OR( UPPER(TRIM(rEmisor))=UPPER(TRIM(C21)), UPPER(TRIM(rEmisor))=""CUALQUIERA"" ), OR( UPPER(TRIM(rTipo))="&"""SOLO EMISOR"", AND( UPPER(TRIM(rTipo))=""EXACTA"", UPPER(TRIM(D21))=UPPER(TRIM(rPatron)) ), AND( OR( UPPER(TRIM(rTipo))=""CONTIENE"", UPPER(TRIM(rTipo))=""COINCIDENCIA"" ), ISNUMBER(SEARCH(UPPER(TRIM(rPatron)),UPPER(TRIM(D21)))) ) ) ), rConcepto, """" )"&" ) )<>"""" ), 1 ), """" )"),"MANIOBRAS") -> MANIOBRAS
C22: FEDERAL EXPRESS HOLDINGS (MEXICO) Y COMPAÑIA | D22: Asignacion de Guia Aerea | E22: 580.56 | F22: 0 | G22: TOLUCA | H22: {=INDEX(CC!C:C,MATCH(1,(CC!A:A=G22)*(CC!B:B=I22),0))} -> 1002 | I22: PROPIOS | J22: 580.56 | K22: =IFERROR(__xludf.DUMMYFUNCTION("IFERROR( INDEX( FILTER( MAP( reglas!$B$2:$B$240, reglas!$C$2:$C$240, reglas!$D$2:$D$240, reglas!$E$2:$E$240, LAMBDA(rEmisor,rPatron,rConcepto,rTipo, IF( AND( OR( UPPER(TRIM(rEmisor))=UPPER(TRIM(C22)), UPPER(TRIM(rEmisor))=""CUALQUIERA"" ), OR( UPPER(TRIM("&"rTipo))=""SOLO EMISOR"", AND( UPPER(TRIM(rTipo))=""EXACTA"", UPPER(TRIM(AG22))=UPPER(TRIM(rPatron)) ), AND( OR( UPPER(TRIM(rTipo))=""CONTIENE"", UPPER(TRIM(rTipo))=""COINCIDENCIA"" ), ISNUMBER(SEARCH(UPPER(TRIM(rPatron)),UPPER(TRIM(D22)))) ) ) ), rConcept"&"o, """" ) ) ), MAP( reglas!$B$2:$B$240, reglas!$C$2:$C$240, reglas!$D$2:$D$240, reglas!$E$2:$E$240, LAMBDA(rEmisor,rPatron,rConcepto,rTipo, IF( AND( OR( UPPER(TRIM(rEmisor))=UPPER(TRIM(C22)), UPPER(TRIM(rEmisor))=""CUALQUIERA"" ), OR( UPPER(TRIM(rTipo))="&"""SOLO EMISOR"", AND( UPPER(TRIM(rTipo))=""EXACTA"", UPPER(TRIM(D22))=UPPER(TRIM(rPatron)) ), AND( OR( UPPER(TRIM(rTipo))=""CONTIENE"", UPPER(TRIM(rTipo))=""COINCIDENCIA"" ), ISNUMBER(SEARCH(UPPER(TRIM(rPatron)),UPPER(TRIM(D22)))) ) ) ), rConcepto, """" )"&" ) )<>"""" ), 1 ), """" )"),"MANIOBRAS") -> MANIOBRAS
C23: FEDERAL EXPRESS HOLDINGS (MEXICO) Y COMPAÑIA | D23: Manejo | E23: 634.89 | F23: 0 | G23: TOLUCA | H23: {=INDEX(CC!C:C,MATCH(1,(CC!A:A=G23)*(CC!B:B=I23),0))} -> 1002 | I23: PROPIOS | J23: 634.89 | K23: =IFERROR(__xludf.DUMMYFUNCTION("IFERROR( INDEX( FILTER( MAP( reglas!$B$2:$B$240, reglas!$C$2:$C$240, reglas!$D$2:$D$240, reglas!$E$2:$E$240, LAMBDA(rEmisor,rPatron,rConcepto,rTipo, IF( AND( OR( UPPER(TRIM(rEmisor))=UPPER(TRIM(C23)), UPPER(TRIM(rEmisor))=""CUALQUIERA"" ), OR( UPPER(TRIM("&"rTipo))=""SOLO EMISOR"", AND( UPPER(TRIM(rTipo))=""EXACTA"", UPPER(TRIM(AG23))=UPPER(TRIM(rPatron)) ), AND( OR( UPPER(TRIM(rTipo))=""CONTIENE"", UPPER(TRIM(rTipo))=""COINCIDENCIA"" ), ISNUMBER(SEARCH(UPPER(TRIM(rPatron)),UPPER(TRIM(D23)))) ) ) ), rConcept"&"o, """" ) ) ), MAP( reglas!$B$2:$B$240, reglas!$C$2:$C$240, reglas!$D$2:$D$240, reglas!$E$2:$E$240, LAMBDA(rEmisor,rPatron,rConcepto,rTipo, IF( AND( OR( UPPER(TRIM(rEmisor))=UPPER(TRIM(C23)), UPPER(TRIM(rEmisor))=""CUALQUIERA"" ), OR( UPPER(TRIM(rTipo))="&"""SOLO EMISOR"", AND( UPPER(TRIM(rTipo))=""EXACTA"", UPPER(TRIM(D23))=UPPER(TRIM(rPatron)) ), AND( OR( UPPER(TRIM(rTipo))=""CONTIENE"", UPPER(TRIM(rTipo))=""COINCIDENCIA"" ), ISNUMBER(SEARCH(UPPER(TRIM(rPatron)),UPPER(TRIM(D23)))) ) ) ), rConcepto, """" )"&" ) )<>"""" ), 1 ), """" )"),"MANIOBRAS") -> MANIOBRAS
C24: FEDERAL EXPRESS HOLDINGS (MEXICO) Y COMPAÑIA | D24: Custodia | E24: 360.49 | F24: 0 | G24: TOLUCA | H24: {=INDEX(CC!C:C,MATCH(1,(CC!A:A=G24)*(CC!B:B=I24),0))} -> 1002 | I24: PROPIOS | J24: 360.49 | K24: =IFERROR(__xludf.DUMMYFUNCTION("IFERROR( INDEX( FILTER( MAP( reglas!$B$2:$B$240, reglas!$C$2:$C$240, reglas!$D$2:$D$240, reglas!$E$2:$E$240, LAMBDA(rEmisor,rPatron,rConcepto,rTipo, IF( AND( OR( UPPER(TRIM(rEmisor))=UPPER(TRIM(C24)), UPPER(TRIM(rEmisor))=""CUALQUIERA"" ), OR( UPPER(TRIM("&"rTipo))=""SOLO EMISOR"", AND( UPPER(TRIM(rTipo))=""EXACTA"", UPPER(TRIM(AG24))=UPPER(TRIM(rPatron)) ), AND( OR( UPPER(TRIM(rTipo))=""CONTIENE"", UPPER(TRIM(rTipo))=""COINCIDENCIA"" ), ISNUMBER(SEARCH(UPPER(TRIM(rPatron)),UPPER(TRIM(D24)))) ) ) ), rConcept"&"o, """" ) ) ), MAP( reglas!$B$2:$B$240, reglas!$C$2:$C$240, reglas!$D$2:$D$240, reglas!$E$2:$E$240, LAMBDA(rEmisor,rPatron,rConcepto,rTipo, IF( AND( OR( UPPER(TRIM(rEmisor))=UPPER(TRIM(C24)), UPPER(TRIM(rEmisor))=""CUALQUIERA"" ), OR( UPPER(TRIM(rTipo))="&"""SOLO EMISOR"", AND( UPPER(TRIM(rTipo))=""EXACTA"", UPPER(TRIM(D24))=UPPER(TRIM(rPatron)) ), AND( OR( UPPER(TRIM(rTipo))=""CONTIENE"", UPPER(TRIM(rTipo))=""COINCIDENCIA"" ), ISNUMBER(SEARCH(UPPER(TRIM(rPatron)),UPPER(TRIM(D24)))) ) ) ), rConcepto, """" )"&" ) )<>"""" ), 1 ), """" )"),"MANIOBRAS") -> MANIOBRAS
C25: FEDERAL EXPRESS HOLDINGS (MEXICO) Y COMPAÑIA | D25: Maniobras para Previo | E25: 666.13 | F25: 0 | G25: TOLUCA | H25: {=INDEX(CC!C:C,MATCH(1,(CC!A:A=G25)*(CC!B:B=I25),0))} -> 1002 | I25: PROPIOS | J25: 666.13 | K25: =IFERROR(__xludf.DUMMYFUNCTION("IFERROR( INDEX( FILTER( MAP( reglas!$B$2:$B$240, reglas!$C$2:$C$240, reglas!$D$2:$D$240, reglas!$E$2:$E$240, LAMBDA(rEmisor,rPatron,rConcepto,rTipo, IF( AND( OR( UPPER(TRIM(rEmisor))=UPPER(TRIM(C25)), UPPER(TRIM(rEmisor))=""CUALQUIERA"" ), OR( UPPER(TRIM("&"rTipo))=""SOLO EMISOR"", AND( UPPER(TRIM(rTipo))=""EXACTA"", UPPER(TRIM(AG25))=UPPER(TRIM(rPatron)) ), AND( OR( UPPER(TRIM(rTipo))=""CONTIENE"", UPPER(TRIM(rTipo))=""COINCIDENCIA"" ), ISNUMBER(SEARCH(UPPER(TRIM(rPatron)),UPPER(TRIM(D25)))) ) ) ), rConcept"&"o, """" ) ) ), MAP( reglas!$B$2:$B$240, reglas!$C$2:$C$240, reglas!$D$2:$D$240, reglas!$E$2:$E$240, LAMBDA(rEmisor,rPatron,rConcepto,rTipo, IF( AND( OR( UPPER(TRIM(rEmisor))=UPPER(TRIM(C25)), UPPER(TRIM(rEmisor))=""CUALQUIERA"" ), OR( UPPER(TRIM(rTipo))="&"""SOLO EMISOR"", AND( UPPER(TRIM(rTipo))=""EXACTA"", UPPER(TRIM(D25))=UPPER(TRIM(rPatron)) ), AND( OR( UPPER(TRIM(rTipo))=""CONTIENE"", UPPER(TRIM(rTipo))=""COINCIDENCIA"" ), ISNUMBER(SEARCH(UPPER(TRIM(rPatron)),UPPER(TRIM(D25)))) ) ) ), rConcepto, """" )"&" ) )<>"""" ), 1 ), """" )"),"MANIOBRAS") -> MANIOBRAS
B26: MXN | C26: SISTEMA UNIFICADO DE MANIOBRAS AEREAS PARA AGENTES ADUANALES | D26: Carga de camión | E26: 3500 | F26: 0 | G26: IMILE AIFA | H26: {=INDEX(CC!C:C,MATCH(1,(CC!A:A=G26)*(CC!B:B=I26),0))} -> 1402 | I26: PROPIOS | J26: 3500 | K26: =IFERROR(__xludf.DUMMYFUNCTION("IFERROR( INDEX( FILTER( MAP( reglas!$B$2:$B$240, reglas!$C$2:$C$240, reglas!$D$2:$D$240, reglas!$E$2:$E$240, LAMBDA(rEmisor,rPatron,rConcepto,rTipo, IF( AND( OR( UPPER(TRIM(rEmisor))=UPPER(TRIM(C26)), UPPER(TRIM(rEmisor))=""CUALQUIERA"" ), OR( UPPER(TRIM("&"rTipo))=""SOLO EMISOR"", AND( UPPER(TRIM(rTipo))=""EXACTA"", UPPER(TRIM(AG26))=UPPER(TRIM(rPatron)) ), AND( OR( UPPER(TRIM(rTipo))=""CONTIENE"", UPPER(TRIM(rTipo))=""COINCIDENCIA"" ), ISNUMBER(SEARCH(UPPER(TRIM(rPatron)),UPPER(TRIM(D26)))) ) ) ), rConcept"&"o, """" ) ) ), MAP( reglas!$B$2:$B$240, reglas!$C$2:$C$240, reglas!$D$2:$D$240, reglas!$E$2:$E$240, LAMBDA(rEmisor,rPatron,rConcepto,rTipo, IF( AND( OR( UPPER(TRIM(rEmisor))=UPPER(TRIM(C26)), UPPER(TRIM(rEmisor))=""CUALQUIERA"" ), OR( UPPER(TRIM(rTipo))="&"""SOLO EMISOR"", AND( UPPER(TRIM(rTipo))=""EXACTA"", UPPER(TRIM(D26))=UPPER(TRIM(rPatron)) ), AND( OR( UPPER(TRIM(rTipo))=""CONTIENE"", UPPER(TRIM(rTipo))=""COINCIDENCIA"" ), ISNUMBER(SEARCH(UPPER(TRIM(rPatron)),UPPER(TRIM(D26)))) ) ) ), rConcepto, """" )"&" ) )<>"""" ), 1 ), """" )"),"MANIOBRAS") -> MANIOBRAS
B27: MXN | C27: KYA TI | D27: Servicios de comercio internacional | E27: 20000 | F27: 0 | G27: LAREDO | H27: {=INDEX(CC!C:C,MATCH(1,(CC!A:A=G27)*(CC!B:B=I27),0))} -> 1302 | I27: PROPIOS | K27: =IFERROR(__xludf.DUMMYFUNCTION("IFERROR( INDEX( FILTER( MAP( reglas!$B$2:$B$240, reglas!$C$2:$C$240, reglas!$D$2:$D$240, reglas!$E$2:$E$240, LAMBDA(rEmisor,rPatron,rConcepto,rTipo, IF( AND( OR( UPPER(TRIM(rEmisor))=UPPER(TRIM(C27)), UPPER(TRIM(rEmisor))=""CUALQUIERA"" ), OR( UPPER(TRIM("&"rTipo))=""SOLO EMISOR"", AND( UPPER(TRIM(rTipo))=""EXACTA"", UPPER(TRIM(AG27))=UPPER(TRIM(rPatron)) ), AND( OR( UPPER(TRIM(rTipo))=""CONTIENE"", UPPER(TRIM(rTipo))=""COINCIDENCIA"" ), ISNUMBER(SEARCH(UPPER(TRIM(rPatron)),UPPER(TRIM(D27)))) ) ) ), rConcept"&"o, """" ) ) ), MAP( reglas!$B$2:$B$240, reglas!$C$2:$C$240, reglas!$D$2:$D$240, reglas!$E$2:$E$240, LAMBDA(rEmisor,rPatron,rConcepto,rTipo, IF( AND( OR( UPPER(TRIM(rEmisor))=UPPER(TRIM(C27)), UPPER(TRIM(rEmisor))=""CUALQUIERA"" ), OR( UPPER(TRIM(rTipo))="&"""SOLO EMISOR"", AND( UPPER(TRIM(rTipo))=""EXACTA"", UPPER(TRIM(D27))=UPPER(TRIM(rPatron)) ), AND( OR( UPPER(TRIM(rTipo))=""CONTIENE"", UPPER(TRIM(rTipo))=""COINCIDENCIA"" ), ISNUMBER(SEARCH(UPPER(TRIM(rPatron)),UPPER(TRIM(D27)))) ) ) ), rConcepto, """" )"&" ) )<>"""" ), 1 ), """" )"),"VALIDACION") -> VALIDACION
C28: KYA TI | D28: Servicios de comercio internacional | G28: ESTAFETA | H28: {=INDEX(CC!C:C,MATCH(1,(CC!A:A=G28)*(CC!B:B=I28),0))} -> 402 | I28: PROPIOS | K28: =IFERROR(__xludf.DUMMYFUNCTION("IFERROR( INDEX( FILTER( MAP( reglas!$B$2:$B$240, reglas!$C$2:$C$240, reglas!$D$2:$D$240, reglas!$E$2:$E$240, LAMBDA(rEmisor,rPatron,rConcepto,rTipo, IF( AND( OR( UPPER(TRIM(rEmisor))=UPPER(TRIM(C28)), UPPER(TRIM(rEmisor))=""CUALQUIERA"" ), OR( UPPER(TRIM("&"rTipo))=""SOLO EMISOR"", AND( UPPER(TRIM(rTipo))=""EXACTA"", UPPER(TRIM(AG28))=UPPER(TRIM(rPatron)) ), AND( OR( UPPER(TRIM(rTipo))=""CONTIENE"", UPPER(TRIM(rTipo))=""COINCIDENCIA"" ), ISNUMBER(SEARCH(UPPER(TRIM(rPatron)),UPPER(TRIM(D28)))) ) ) ), rConcept"&"o, """" ) ) ), MAP( reglas!$B$2:$B$240, reglas!$C$2:$C$240, reglas!$D$2:$D$240, reglas!$E$2:$E$240, LAMBDA(rEmisor,rPatron,rConcepto,rTipo, IF( AND( OR( UPPER(TRIM(rEmisor))=UPPER(TRIM(C28)), UPPER(TRIM(rEmisor))=""CUALQUIERA"" ), OR( UPPER(TRIM(rTipo))="&"""SOLO EMISOR"", AND( UPPER(TRIM(rTipo))=""EXACTA"", UPPER(TRIM(D28))=UPPER(TRIM(rPatron)) ), AND( OR( UPPER(TRIM(rTipo))=""CONTIENE"", UPPER(TRIM(rTipo))=""COINCIDENCIA"" ), ISNUMBER(SEARCH(UPPER(TRIM(rPatron)),UPPER(TRIM(D28)))) ) ) ), rConcepto, """" )"&" ) )<>"""" ), 1 ), """" )"),"VALIDACION") -> VALIDACION
C29: KYA TI | D29: Servicios de comercio internacional | G29: MANZANILLO | H29: {=INDEX(CC!C:C,MATCH(1,(CC!A:A=G29)*(CC!B:B=I29),0))} -> 1202 | I29: PROPIOS | K29: =IFERROR(__xludf.DUMMYFUNCTION("IFERROR( INDEX( FILTER( MAP( reglas!$B$2:$B$240, reglas!$C$2:$C$240, reglas!$D$2:$D$240, reglas!$E$2:$E$240, LAMBDA(rEmisor,rPatron,rConcepto,rTipo, IF( AND( OR( UPPER(TRIM(rEmisor))=UPPER(TRIM(C29)), UPPER(TRIM(rEmisor))=""CUALQUIERA"" ), OR( UPPER(TRIM("&"rTipo))=""SOLO EMISOR"", AND( UPPER(TRIM(rTipo))=""EXACTA"", UPPER(TRIM(AG29))=UPPER(TRIM(rPatron)) ), AND( OR( UPPER(TRIM(rTipo))=""CONTIENE"", UPPER(TRIM(rTipo))=""COINCIDENCIA"" ), ISNUMBER(SEARCH(UPPER(TRIM(rPatron)),UPPER(TRIM(D29)))) ) ) ), rConcept"&"o, """" ) ) ), MAP( reglas!$B$2:$B$240, reglas!$C$2:$C$240, reglas!$D$2:$D$240, reglas!$E$2:$E$240, LAMBDA(rEmisor,rPatron,rConcepto,rTipo, IF( AND( OR( UPPER(TRIM(rEmisor))=UPPER(TRIM(C29)), UPPER(TRIM(rEmisor))=""CUALQUIERA"" ), OR( UPPER(TRIM(rTipo))="&"""SOLO EMISOR"", AND( UPPER(TRIM(rTipo))=""EXACTA"", UPPER(TRIM(D29))=UPPER(TRIM(rPatron)) ), AND( OR( UPPER(TRIM(rTipo))=""CONTIENE"", UPPER(TRIM(rTipo))=""COINCIDENCIA"" ), ISNUMBER(SEARCH(UPPER(TRIM(rPatron)),UPPER(TRIM(D29)))) ) ) ), rConcepto, """" )"&" ) )<>"""" ), 1 ), """" )"),"VALIDACION") -> VALIDACION
B30: MXN | C30: CRISTOFER PAZ JIMENEZ | D30: FLETE LOCAL ADUANA AIFA A CUAUTITLÁN, EDO. MÉX. 03/08/2026. | E30: 11500 | F30: 0 | G30: IMILE AIFA | H30: {=INDEX(CC!C:C,MATCH(1,(CC!A:A=G30)*(CC!B:B=I30),0))} -> 1402 | I30: PROPIOS | J30: 11500 | K30: =IFERROR(__xludf.DUMMYFUNCTION("IFERROR( INDEX( FILTER( MAP( reglas!$B$2:$B$240, reglas!$C$2:$C$240, reglas!$D$2:$D$240, reglas!$E$2:$E$240, LAMBDA(rEmisor,rPatron,rConcepto,rTipo, IF( AND( OR( UPPER(TRIM(rEmisor))=UPPER(TRIM(C30)), UPPER(TRIM(rEmisor))=""CUALQUIERA"" ), OR( UPPER(TRIM("&"rTipo))=""SOLO EMISOR"", AND( UPPER(TRIM(rTipo))=""EXACTA"", UPPER(TRIM(AG30))=UPPER(TRIM(rPatron)) ), AND( OR( UPPER(TRIM(rTipo))=""CONTIENE"", UPPER(TRIM(rTipo))=""COINCIDENCIA"" ), ISNUMBER(SEARCH(UPPER(TRIM(rPatron)),UPPER(TRIM(D30)))) ) ) ), rConcept"&"o, """" ) ) ), MAP( reglas!$B$2:$B$240, reglas!$C$2:$C$240, reglas!$D$2:$D$240, reglas!$E$2:$E$240, LAMBDA(rEmisor,rPatron,rConcepto,rTipo, IF( AND( OR( UPPER(TRIM(rEmisor))=UPPER(TRIM(C30)), UPPER(TRIM(rEmisor))=""CUALQUIERA"" ), OR( UPPER(TRIM(rTipo))="&"""SOLO EMISOR"", AND( UPPER(TRIM(rTipo))=""EXACTA"", UPPER(TRIM(D30))=UPPER(TRIM(rPatron)) ), AND( OR( UPPER(TRIM(rTipo))=""CONTIENE"", UPPER(TRIM(rTipo))=""COINCIDENCIA"" ), ISNUMBER(SEARCH(UPPER(TRIM(rPatron)),UPPER(TRIM(D30)))) ) ) ), rConcepto, """" )"&" ) )<>"""" ), 1 ), """" )"),"TRANSPORTE") -> TRANSPORTE
B31: MXN | C31: SUPER SERVICIO RUDEM | D31: 32011 MAGNA | E31: 605.87 | F31: 0 | G31: AMAZON 1 | H31: {=INDEX(CC!C:C,MATCH(1,(CC!A:A=G31)*(CC!B:B=I31),0))} -> 202 | I31: PROPIOS | K31: =IFERROR(__xludf.DUMMYFUNCTION("IFERROR( INDEX( FILTER( MAP( reglas!$B$2:$B$240, reglas!$C$2:$C$240, reglas!$D$2:$D$240, reglas!$E$2:$E$240, LAMBDA(rEmisor,rPatron,rConcepto,rTipo, IF( AND( OR( UPPER(TRIM(rEmisor))=UPPER(TRIM(C31)), UPPER(TRIM(rEmisor))=""CUALQUIERA"" ), OR( UPPER(TRIM("&"rTipo))=""SOLO EMISOR"", AND( UPPER(TRIM(rTipo))=""EXACTA"", UPPER(TRIM(AG31))=UPPER(TRIM(rPatron)) ), AND( OR( UPPER(TRIM(rTipo))=""CONTIENE"", UPPER(TRIM(rTipo))=""COINCIDENCIA"" ), ISNUMBER(SEARCH(UPPER(TRIM(rPatron)),UPPER(TRIM(D31)))) ) ) ), rConcept"&"o, """" ) ) ), MAP( reglas!$B$2:$B$240, reglas!$C$2:$C$240, reglas!$D$2:$D$240, reglas!$E$2:$E$240, LAMBDA(rEmisor,rPatron,rConcepto,rTipo, IF( AND( OR( UPPER(TRIM(rEmisor))=UPPER(TRIM(C31)), UPPER(TRIM(rEmisor))=""CUALQUIERA"" ), OR( UPPER(TRIM(rTipo))="&"""SOLO EMISOR"", AND( UPPER(TRIM(rTipo))=""EXACTA"", UPPER(TRIM(D31))=UPPER(TRIM(rPatron)) ), AND( OR( UPPER(TRIM(rTipo))=""CONTIENE"", UPPER(TRIM(rTipo))=""COINCIDENCIA"" ), ISNUMBER(SEARCH(UPPER(TRIM(rPatron)),UPPER(TRIM(D31)))) ) ) ), rConcepto, """" )"&" ) )<>"""" ), 1 ), """" )"),"COMBUSTIBLES Y LUBRICANTES") -> COMBUSTIBLES Y LUBRICANTES
C32: SUPER SERVICIO RUDEM | D32: 32011 MAGNA | E32: 432.78 | F32: 0 | G32: AMAZON 1 | H32: {=INDEX(CC!C:C,MATCH(1,(CC!A:A=G32)*(CC!B:B=I32),0))} -> 202 | I32: PROPIOS | K32: =IFERROR(__xludf.DUMMYFUNCTION("IFERROR( INDEX( FILTER( MAP( reglas!$B$2:$B$240, reglas!$C$2:$C$240, reglas!$D$2:$D$240, reglas!$E$2:$E$240, LAMBDA(rEmisor,rPatron,rConcepto,rTipo, IF( AND( OR( UPPER(TRIM(rEmisor))=UPPER(TRIM(C32)), UPPER(TRIM(rEmisor))=""CUALQUIERA"" ), OR( UPPER(TRIM("&"rTipo))=""SOLO EMISOR"", AND( UPPER(TRIM(rTipo))=""EXACTA"", UPPER(TRIM(AG32))=UPPER(TRIM(rPatron)) ), AND( OR( UPPER(TRIM(rTipo))=""CONTIENE"", UPPER(TRIM(rTipo))=""COINCIDENCIA"" ), ISNUMBER(SEARCH(UPPER(TRIM(rPatron)),UPPER(TRIM(D32)))) ) ) ), rConcept"&"o, """" ) ) ), MAP( reglas!$B$2:$B$240, reglas!$C$2:$C$240, reglas!$D$2:$D$240, reglas!$E$2:$E$240, LAMBDA(rEmisor,rPatron,rConcepto,rTipo, IF( AND( OR( UPPER(TRIM(rEmisor))=UPPER(TRIM(C32)), UPPER(TRIM(rEmisor))=""CUALQUIERA"" ), OR( UPPER(TRIM(rTipo))="&"""SOLO EMISOR"", AND( UPPER(TRIM(rTipo))=""EXACTA"", UPPER(TRIM(D32))=UPPER(TRIM(rPatron)) ), AND( OR( UPPER(TRIM(rTipo))=""CONTIENE"", UPPER(TRIM(rTipo))=""COINCIDENCIA"" ), ISNUMBER(SEARCH(UPPER(TRIM(rPatron)),UPPER(TRIM(D32)))) ) ) ), rConcepto, """" )"&" ) )<>"""" ), 1 ), """" )"),"COMBUSTIBLES Y LUBRICANTES") -> COMBUSTIBLES Y LUBRICANTES
C33: SUPER SERVICIO RUDEM | D33: 32011 MAGNA | E33: 432.78 | F33: 0 | G33: AMAZON 1 | H33: {=INDEX(CC!C:C,MATCH(1,(CC!A:A=G33)*(CC!B:B=I33),0))} -> 202 | I33: PROPIOS | K33: =IFERROR(__xludf.DUMMYFUNCTION("IFERROR( INDEX( FILTER( MAP( reglas!$B$2:$B$240, reglas!$C$2:$C$240, reglas!$D$2:$D$240, reglas!$E$2:$E$240, LAMBDA(rEmisor,rPatron,rConcepto,rTipo, IF( AND( OR( UPPER(TRIM(rEmisor))=UPPER(TRIM(C33)), UPPER(TRIM(rEmisor))=""CUALQUIERA"" ), OR( UPPER(TRIM("&"rTipo))=""SOLO EMISOR"", AND( UPPER(TRIM(rTipo))=""EXACTA"", UPPER(TRIM(AG33))=UPPER(TRIM(rPatron)) ), AND( OR( UPPER(TRIM(rTipo))=""CONTIENE"", UPPER(TRIM(rTipo))=""COINCIDENCIA"" ), ISNUMBER(SEARCH(UPPER(TRIM(rPatron)),UPPER(TRIM(D33)))) ) ) ), rConcept"&"o, """" ) ) ), MAP( reglas!$B$2:$B$240, reglas!$C$2:$C$240, reglas!$D$2:$D$240, reglas!$E$2:$E$240, LAMBDA(rEmisor,rPatron,rConcepto,rTipo, IF( AND( OR( UPPER(TRIM(rEmisor))=UPPER(TRIM(C33)), UPPER(TRIM(rEmisor))=""CUALQUIERA"" ), OR( UPPER(TRIM(rTipo))="&"""SOLO EMISOR"", AND( UPPER(TRIM(rTipo))=""EXACTA"", UPPER(TRIM(D33))=UPPER(TRIM(rPatron)) ), AND( OR( UPPER(TRIM(rTipo))=""CONTIENE"", UPPER(TRIM(rTipo))=""COINCIDENCIA"" ), ISNUMBER(SEARCH(UPPER(TRIM(rPatron)),UPPER(TRIM(D33)))) ) ) ), rConcepto, """" )"&" ) )<>"""" ), 1 ), """" )"),"COMBUSTIBLES Y LUBRICANTES") -> COMBUSTIBLES Y LUBRICANTES
C34: SUPER SERVICIO RUDEM | D34: 34006 DIESEL | E34: 605.21 | F34: 0 | G34: AMAZON 1 | H34: {=INDEX(CC!C:C,MATCH(1,(CC!A:A=G34)*(CC!B:B=I34),0))} -> 202 | I34: PROPIOS | K34: =IFERROR(__xludf.DUMMYFUNCTION("IFERROR( INDEX( FILTER( MAP( reglas!$B$2:$B$240, reglas!$C$2:$C$240, reglas!$D$2:$D$240, reglas!$E$2:$E$240, LAMBDA(rEmisor,rPatron,rConcepto,rTipo, IF( AND( OR( UPPER(TRIM(rEmisor))=UPPER(TRIM(C34)), UPPER(TRIM(rEmisor))=""CUALQUIERA"" ), OR( UPPER(TRIM("&"rTipo))=""SOLO EMISOR"", AND( UPPER(TRIM(rTipo))=""EXACTA"", UPPER(TRIM(AG34))=UPPER(TRIM(rPatron)) ), AND( OR( UPPER(TRIM(rTipo))=""CONTIENE"", UPPER(TRIM(rTipo))=""COINCIDENCIA"" ), ISNUMBER(SEARCH(UPPER(TRIM(rPatron)),UPPER(TRIM(D34)))) ) ) ), rConcept"&"o, """" ) ) ), MAP( reglas!$B$2:$B$240, reglas!$C$2:$C$240, reglas!$D$2:$D$240, reglas!$E$2:$E$240, LAMBDA(rEmisor,rPatron,rConcepto,rTipo, IF( AND( OR( UPPER(TRIM(rEmisor))=UPPER(TRIM(C34)), UPPER(TRIM(rEmisor))=""CUALQUIERA"" ), OR( UPPER(TRIM(rTipo))="&"""SOLO EMISOR"", AND( UPPER(TRIM(rTipo))=""EXACTA"", UPPER(TRIM(D34))=UPPER(TRIM(rPatron)) ), AND( OR( UPPER(TRIM(rTipo))=""CONTIENE"", UPPER(TRIM(rTipo))=""COINCIDENCIA"" ), ISNUMBER(SEARCH(UPPER(TRIM(rPatron)),UPPER(TRIM(D34)))) ) ) ), rConcepto, """" )"&" ) )<>"""" ), 1 ), """" )"),"COMBUSTIBLES Y LUBRICANTES") -> COMBUSTIBLES Y LUBRICANTES
C35: SUPER SERVICIO RUDEM | D35: 32011 MAGNA | E35: 432.78 | F35: 0 | G35: AMAZON 1 | H35: {=INDEX(CC!C:C,MATCH(1,(CC!A:A=G35)*(CC!B:B=I35),0))} -> 202 | I35: PROPIOS | K35: =IFERROR(__xludf.DUMMYFUNCTION("IFERROR( INDEX( FILTER( MAP( reglas!$B$2:$B$240, reglas!$C$2:$C$240, reglas!$D$2:$D$240, reglas!$E$2:$E$240, LAMBDA(rEmisor,rPatron,rConcepto,rTipo, IF( AND( OR( UPPER(TRIM(rEmisor))=UPPER(TRIM(C35)), UPPER(TRIM(rEmisor))=""CUALQUIERA"" ), OR( UPPER(TRIM("&"rTipo))=""SOLO EMISOR"", AND( UPPER(TRIM(rTipo))=""EXACTA"", UPPER(TRIM(AG35))=UPPER(TRIM(rPatron)) ), AND( OR( UPPER(TRIM(rTipo))=""CONTIENE"", UPPER(TRIM(rTipo))=""COINCIDENCIA"" ), ISNUMBER(SEARCH(UPPER(TRIM(rPatron)),UPPER(TRIM(D35)))) ) ) ), rConcept"&"o, """" ) ) ), MAP( reglas!$B$2:$B$240, reglas!$C$2:$C$240, reglas!$D$2:$D$240, reglas!$E$2:$E$240, LAMBDA(rEmisor,rPatron,rConcepto,rTipo, IF( AND( OR( UPPER(TRIM(rEmisor))=UPPER(TRIM(C35)), UPPER(TRIM(rEmisor))=""CUALQUIERA"" ), OR( UPPER(TRIM(rTipo))="&"""SOLO EMISOR"", AND( UPPER(TRIM(rTipo))=""EXACTA"", UPPER(TRIM(D35))=UPPER(TRIM(rPatron)) ), AND( OR( UPPER(TRIM(rTipo))=""CONTIENE"", UPPER(TRIM(rTipo))=""COINCIDENCIA"" ), ISNUMBER(SEARCH(UPPER(TRIM(rPatron)),UPPER(TRIM(D35)))) ) ) ), rConcepto, """" )"&" ) )<>"""" ), 1 ), """" )"),"COMBUSTIBLES Y LUBRICANTES") -> COMBUSTIBLES Y LUBRICANTES
C36: SUPER SERVICIO RUDEM | D36: 32011 MAGNA | E36: 432.78 | F36: 0 | G36: AMAZON 1 | H36: {=INDEX(CC!C:C,MATCH(1,(CC!A:A=G36)*(CC!B:B=I36),0))} -> 202 | I36: PROPIOS | K36: =IFERROR(__xludf.DUMMYFUNCTION("IFERROR( INDEX( FILTER( MAP( reglas!$B$2:$B$240, reglas!$C$2:$C$240, reglas!$D$2:$D$240, reglas!$E$2:$E$240, LAMBDA(rEmisor,rPatron,rConcepto,rTipo, IF( AND( OR( UPPER(TRIM(rEmisor))=UPPER(TRIM(C36)), UPPER(TRIM(rEmisor))=""CUALQUIERA"" ), OR( UPPER(TRIM("&"rTipo))=""SOLO EMISOR"", AND( UPPER(TRIM(rTipo))=""EXACTA"", UPPER(TRIM(AG36))=UPPER(TRIM(rPatron)) ), AND( OR( UPPER(TRIM(rTipo))=""CONTIENE"", UPPER(TRIM(rTipo))=""COINCIDENCIA"" ), ISNUMBER(SEARCH(UPPER(TRIM(rPatron)),UPPER(TRIM(D36)))) ) ) ), rConcept"&"o, """" ) ) ), MAP( reglas!$B$2:$B$240, reglas!$C$2:$C$240, reglas!$D$2:$D$240, reglas!$E$2:$E$240, LAMBDA(rEmisor,rPatron,rConcepto,rTipo, IF( AND( OR( UPPER(TRIM(rEmisor))=UPPER(TRIM(C36)), UPPER(TRIM(rEmisor))=""CUALQUIERA"" ), OR( UPPER(TRIM(rTipo))="&"""SOLO EMISOR"", AND( UPPER(TRIM(rTipo))=""EXACTA"", UPPER(TRIM(D36))=UPPER(TRIM(rPatron)) ), AND( OR( UPPER(TRIM(rTipo))=""CONTIENE"", UPPER(TRIM(rTipo))=""COINCIDENCIA"" ), ISNUMBER(SEARCH(UPPER(TRIM(rPatron)),UPPER(TRIM(D36)))) ) ) ), rConcepto, """" )"&" ) )<>"""" ), 1 ), """" )"),"COMBUSTIBLES Y LUBRICANTES") -> COMBUSTIBLES Y LUBRICANTES
C37: SUPER SERVICIO RUDEM | D37: 32011 MAGNA | E37: 612.34 | F37: 0 | G37: AMAZON 1 | H37: {=INDEX(CC!C:C,MATCH(1,(CC!A:A=G37)*(CC!B:B=I37),0))} -> 202 | I37: PROPIOS | K37: =IFERROR(__xludf.DUMMYFUNCTION("IFERROR( INDEX( FILTER( MAP( reglas!$B$2:$B$240, reglas!$C$2:$C$240, reglas!$D$2:$D$240, reglas!$E$2:$E$240, LAMBDA(rEmisor,rPatron,rConcepto,rTipo, IF( AND( OR( UPPER(TRIM(rEmisor))=UPPER(TRIM(C37)), UPPER(TRIM(rEmisor))=""CUALQUIERA"" ), OR( UPPER(TRIM("&"rTipo))=""SOLO EMISOR"", AND( UPPER(TRIM(rTipo))=""EXACTA"", UPPER(TRIM(AG37))=UPPER(TRIM(rPatron)) ), AND( OR( UPPER(TRIM(rTipo))=""CONTIENE"", UPPER(TRIM(rTipo))=""COINCIDENCIA"" ), ISNUMBER(SEARCH(UPPER(TRIM(rPatron)),UPPER(TRIM(D37)))) ) ) ), rConcept"&"o, """" ) ) ), MAP( reglas!$B$2:$B$240, reglas!$C$2:$C$240, reglas!$D$2:$D$240, reglas!$E$2:$E$240, LAMBDA(rEmisor,rPatron,rConcepto,rTipo, IF( AND( OR( UPPER(TRIM(rEmisor))=UPPER(TRIM(C37)), UPPER(TRIM(rEmisor))=""CUALQUIERA"" ), OR( UPPER(TRIM(rTipo))="&"""SOLO EMISOR"", AND( UPPER(TRIM(rTipo))=""EXACTA"", UPPER(TRIM(D37))=UPPER(TRIM(rPatron)) ), AND( OR( UPPER(TRIM(rTipo))=""CONTIENE"", UPPER(TRIM(rTipo))=""COINCIDENCIA"" ), ISNUMBER(SEARCH(UPPER(TRIM(rPatron)),UPPER(TRIM(D37)))) ) ) ), rConcepto, """" )"&" ) )<>"""" ), 1 ), """" )"),"COMBUSTIBLES Y LUBRICANTES") -> COMBUSTIBLES Y LUBRICANTES
C38: SUPER SERVICIO RUDEM | D38: BARDAHL HIDRAULICA | E38: 165.52 | F38: 0 | G38: AMAZON 1 | H38: {=INDEX(CC!C:C,MATCH(1,(CC!A:A=G38)*(CC!B:B=I38),0))} -> 202 | I38: PROPIOS | K38: =IFERROR(__xludf.DUMMYFUNCTION("IFERROR( INDEX( FILTER( MAP( reglas!$B$2:$B$240, reglas!$C$2:$C$240, reglas!$D$2:$D$240, reglas!$E$2:$E$240, LAMBDA(rEmisor,rPatron,rConcepto,rTipo, IF( AND( OR( UPPER(TRIM(rEmisor))=UPPER(TRIM(C38)), UPPER(TRIM(rEmisor))=""CUALQUIERA"" ), OR( UPPER(TRIM("&"rTipo))=""SOLO EMISOR"", AND( UPPER(TRIM(rTipo))=""EXACTA"", UPPER(TRIM(AG38))=UPPER(TRIM(rPatron)) ), AND( OR( UPPER(TRIM(rTipo))=""CONTIENE"", UPPER(TRIM(rTipo))=""COINCIDENCIA"" ), ISNUMBER(SEARCH(UPPER(TRIM(rPatron)),UPPER(TRIM(D38)))) ) ) ), rConcept"&"o, """" ) ) ), MAP( reglas!$B$2:$B$240, reglas!$C$2:$C$240, reglas!$D$2:$D$240, reglas!$E$2:$E$240, LAMBDA(rEmisor,rPatron,rConcepto,rTipo, IF( AND( OR( UPPER(TRIM(rEmisor))=UPPER(TRIM(C38)), UPPER(TRIM(rEmisor))=""CUALQUIERA"" ), OR( UPPER(TRIM(rTipo))="&"""SOLO EMISOR"", AND( UPPER(TRIM(rTipo))=""EXACTA"", UPPER(TRIM(D38))=UPPER(TRIM(rPatron)) ), AND( OR( UPPER(TRIM(rTipo))=""CONTIENE"", UPPER(TRIM(rTipo))=""COINCIDENCIA"" ), ISNUMBER(SEARCH(UPPER(TRIM(rPatron)),UPPER(TRIM(D38)))) ) ) ), rConcepto, """" )"&" ) )<>"""" ), 1 ), """" )"),"COMBUSTIBLES Y LUBRICANTES") -> COMBUSTIBLES Y LUBRICANTES
C39: SUPER SERVICIO RUDEM | D39: 32011 MAGNA | E39: 432.78 | F39: 0 | G39: AMAZON 1 | H39: {=INDEX(CC!C:C,MATCH(1,(CC!A:A=G39)*(CC!B:B=I39),0))} -> 202 | I39: PROPIOS | K39: =IFERROR(__xludf.DUMMYFUNCTION("IFERROR( INDEX( FILTER( MAP( reglas!$B$2:$B$240, reglas!$C$2:$C$240, reglas!$D$2:$D$240, reglas!$E$2:$E$240, LAMBDA(rEmisor,rPatron,rConcepto,rTipo, IF( AND( OR( UPPER(TRIM(rEmisor))=UPPER(TRIM(C39)), UPPER(TRIM(rEmisor))=""CUALQUIERA"" ), OR( UPPER(TRIM("&"rTipo))=""SOLO EMISOR"", AND( UPPER(TRIM(rTipo))=""EXACTA"", UPPER(TRIM(AG39))=UPPER(TRIM(rPatron)) ), AND( OR( UPPER(TRIM(rTipo))=""CONTIENE"", UPPER(TRIM(rTipo))=""COINCIDENCIA"" ), ISNUMBER(SEARCH(UPPER(TRIM(rPatron)),UPPER(TRIM(D39)))) ) ) ), rConcept"&"o, """" ) ) ), MAP( reglas!$B$2:$B$240, reglas!$C$2:$C$240, reglas!$D$2:$D$240, reglas!$E$2:$E$240, LAMBDA(rEmisor,rPatron,rConcepto,rTipo, IF( AND( OR( UPPER(TRIM(rEmisor))=UPPER(TRIM(C39)), UPPER(TRIM(rEmisor))=""CUALQUIERA"" ), OR( UPPER(TRIM(rTipo))="&"""SOLO EMISOR"", AND( UPPER(TRIM(rTipo))=""EXACTA"", UPPER(TRIM(D39))=UPPER(TRIM(rPatron)) ), AND( OR( UPPER(TRIM(rTipo))=""CONTIENE"", UPPER(TRIM(rTipo))=""COINCIDENCIA"" ), ISNUMBER(SEARCH(UPPER(TRIM(rPatron)),UPPER(TRIM(D39)))) ) ) ), rConcepto, """" )"&" ) )<>"""" ), 1 ), """" )"),"COMBUSTIBLES Y LUBRICANTES") -> COMBUSTIBLES Y LUBRICANTES
C40: SUPER SERVICIO RUDEM | D40: 34006 DIESEL | E40: 691.68 | F40: 0 | G40: AMAZON 1 | H40: {=INDEX(CC!C:C,MATCH(1,(CC!A:A=G40)*(CC!B:B=I40),0))} -> 202 | I40: PROPIOS | K40: =IFERROR(__xludf.DUMMYFUNCTION("IFERROR( INDEX( FILTER( MAP( reglas!$B$2:$B$240, reglas!$C$2:$C$240, reglas!$D$2:$D$240, reglas!$E$2:$E$240, LAMBDA(rEmisor,rPatron,rConcepto,rTipo, IF( AND( OR( UPPER(TRIM(rEmisor))=UPPER(TRIM(C40)), UPPER(TRIM(rEmisor))=""CUALQUIERA"" ), OR( UPPER(TRIM("&"rTipo))=""SOLO EMISOR"", AND( UPPER(TRIM(rTipo))=""EXACTA"", UPPER(TRIM(AG40))=UPPER(TRIM(rPatron)) ), AND( OR( UPPER(TRIM(rTipo))=""CONTIENE"", UPPER(TRIM(rTipo))=""COINCIDENCIA"" ), ISNUMBER(SEARCH(UPPER(TRIM(rPatron)),UPPER(TRIM(D40)))) ) ) ), rConcept"&"o, """" ) ) ), MAP( reglas!$B$2:$B$240, reglas!$C$2:$C$240, reglas!$D$2:$D$240, reglas!$E$2:$E$240, LAMBDA(rEmisor,rPatron,rConcepto,rTipo, IF( AND( OR( UPPER(TRIM(rEmisor))=UPPER(TRIM(C40)), UPPER(TRIM(rEmisor))=""CUALQUIERA"" ), OR( UPPER(TRIM(rTipo))="&"""SOLO EMISOR"", AND( UPPER(TRIM(rTipo))=""EXACTA"", UPPER(TRIM(D40))=UPPER(TRIM(rPatron)) ), AND( OR( UPPER(TRIM(rTipo))=""CONTIENE"", UPPER(TRIM(rTipo))=""COINCIDENCIA"" ), ISNUMBER(SEARCH(UPPER(TRIM(rPatron)),UPPER(TRIM(D40)))) ) ) ), rConcepto, """" )"&" ) )<>"""" ), 1 ), """" )"),"COMBUSTIBLES Y LUBRICANTES") -> COMBUSTIBLES Y LUBRICANTES
C41: SUPER SERVICIO RUDEM | D41: 32011 MAGNA | E41: 432.78 | F41: 0 | G41: AMAZON 1 | H41: {=INDEX(CC!C:C,MATCH(1,(CC!A:A=G41)*(CC!B:B=I41),0))} -> 202 | I41: PROPIOS | K41: =IFERROR(__xludf.DUMMYFUNCTION("IFERROR( INDEX( FILTER( MAP( reglas!$B$2:$B$240, reglas!$C$2:$C$240, reglas!$D$2:$D$240, reglas!$E$2:$E$240, LAMBDA(rEmisor,rPatron,rConcepto,rTipo, IF( AND( OR( UPPER(TRIM(rEmisor))=UPPER(TRIM(C41)), UPPER(TRIM(rEmisor))=""CUALQUIERA"" ), OR( UPPER(TRIM("&"rTipo))=""SOLO EMISOR"", AND( UPPER(TRIM(rTipo))=""EXACTA"", UPPER(TRIM(AG41))=UPPER(TRIM(rPatron)) ), AND( OR( UPPER(TRIM(rTipo))=""CONTIENE"", UPPER(TRIM(rTipo))=""COINCIDENCIA"" ), ISNUMBER(SEARCH(UPPER(TRIM(rPatron)),UPPER(TRIM(D41)))) ) ) ), rConcept"&"o, """" ) ) ), MAP( reglas!$B$2:$B$240, reglas!$C$2:$C$240, reglas!$D$2:$D$240, reglas!$E$2:$E$240, LAMBDA(rEmisor,rPatron,rConcepto,rTipo, IF( AND( OR( UPPER(TRIM(rEmisor))=UPPER(TRIM(C41)), UPPER(TRIM(rEmisor))=""CUALQUIERA"" ), OR( UPPER(TRIM(rTipo))="&"""SOLO EMISOR"", AND( UPPER(TRIM(rTipo))=""EXACTA"", UPPER(TRIM(D41))=UPPER(TRIM(rPatron)) ), AND( OR( UPPER(TRIM(rTipo))=""CONTIENE"", UPPER(TRIM(rTipo))=""COINCIDENCIA"" ), ISNUMBER(SEARCH(UPPER(TRIM(rPatron)),UPPER(TRIM(D41)))) ) ) ), rConcepto, """" )"&" ) )<>"""" ), 1 ), """" )"),"COMBUSTIBLES Y LUBRICANTES") -> COMBUSTIBLES Y LUBRICANTES
C42: SUPER SERVICIO RUDEM | D42: 32011 MAGNA | E42: 432.78 | F42: 0 | G42: AMAZON 1 | H42: {=INDEX(CC!C:C,MATCH(1,(CC!A:A=G42)*(CC!B:B=I42),0))} -> 202 | I42: PROPIOS | K42: =IFERROR(__xludf.DUMMYFUNCTION("IFERROR( INDEX( FILTER( MAP( reglas!$B$2:$B$240, reglas!$C$2:$C$240, reglas!$D$2:$D$240, reglas!$E$2:$E$240, LAMBDA(rEmisor,rPatron,rConcepto,rTipo, IF( AND( OR( UPPER(TRIM(rEmisor))=UPPER(TRIM(C42)), UPPER(TRIM(rEmisor))=""CUALQUIERA"" ), OR( UPPER(TRIM("&"rTipo))=""SOLO EMISOR"", AND( UPPER(TRIM(rTipo))=""EXACTA"", UPPER(TRIM(AG42))=UPPER(TRIM(rPatron)) ), AND( OR( UPPER(TRIM(rTipo))=""CONTIENE"", UPPER(TRIM(rTipo))=""COINCIDENCIA"" ), ISNUMBER(SEARCH(UPPER(TRIM(rPatron)),UPPER(TRIM(D42)))) ) ) ), rConcept"&"o, """" ) ) ), MAP( reglas!$B$2:$B$240, reglas!$C$2:$C$240, reglas!$D$2:$D$240, reglas!$E$2:$E$240, LAMBDA(rEmisor,rPatron,rConcepto,rTipo, IF( AND( OR( UPPER(TRIM(rEmisor))=UPPER(TRIM(C42)), UPPER(TRIM(rEmisor))=""CUALQUIERA"" ), OR( UPPER(TRIM(rTipo))="&"""SOLO EMISOR"", AND( UPPER(TRIM(rTipo))=""EXACTA"", UPPER(TRIM(D42))=UPPER(TRIM(rPatron)) ), AND( OR( UPPER(TRIM(rTipo))=""CONTIENE"", UPPER(TRIM(rTipo))=""COINCIDENCIA"" ), ISNUMBER(SEARCH(UPPER(TRIM(rPatron)),UPPER(TRIM(D42)))) ) ) ), rConcepto, """" )"&" ) )<>"""" ), 1 ), """" )"),"COMBUSTIBLES Y LUBRICANTES") -> COMBUSTIBLES Y LUBRICANTES
C43: SUPER SERVICIO RUDEM | D43: 32011 MAGNA | E43: 432.78 | F43: 0 | G43: AMAZON 1 | H43: {=INDEX(CC!C:C,MATCH(1,(CC!A:A=G43)*(CC!B:B=I43),0))} -> 202 | I43: PROPIOS | K43: =IFERROR(__xludf.DUMMYFUNCTION("IFERROR( INDEX( FILTER( MAP( reglas!$B$2:$B$240, reglas!$C$2:$C$240, reglas!$D$2:$D$240, reglas!$E$2:$E$240, LAMBDA(rEmisor,rPatron,rConcepto,rTipo, IF( AND( OR( UPPER(TRIM(rEmisor))=UPPER(TRIM(C43)), UPPER(TRIM(rEmisor))=""CUALQUIERA"" ), OR( UPPER(TRIM("&"rTipo))=""SOLO EMISOR"", AND( UPPER(TRIM(rTipo))=""EXACTA"", UPPER(TRIM(AG43))=UPPER(TRIM(rPatron)) ), AND( OR( UPPER(TRIM(rTipo))=""CONTIENE"", UPPER(TRIM(rTipo))=""COINCIDENCIA"" ), ISNUMBER(SEARCH(UPPER(TRIM(rPatron)),UPPER(TRIM(D43)))) ) ) ), rConcept"&"o, """" ) ) ), MAP( reglas!$B$2:$B$240, reglas!$C$2:$C$240, reglas!$D$2:$D$240, reglas!$E$2:$E$240, LAMBDA(rEmisor,rPatron,rConcepto,rTipo, IF( AND( OR( UPPER(TRIM(rEmisor))=UPPER(TRIM(C43)), UPPER(TRIM(rEmisor))=""CUALQUIERA"" ), OR( UPPER(TRIM(rTipo))="&"""SOLO EMISOR"", AND( UPPER(TRIM(rTipo))=""EXACTA"", UPPER(TRIM(D43))=UPPER(TRIM(rPatron)) ), AND( OR( UPPER(TRIM(rTipo))=""CONTIENE"", UPPER(TRIM(rTipo))=""COINCIDENCIA"" ), ISNUMBER(SEARCH(UPPER(TRIM(rPatron)),UPPER(TRIM(D43)))) ) ) ), rConcepto, """" )"&" ) )<>"""" ), 1 ), """" )"),"COMBUSTIBLES Y LUBRICANTES") -> COMBUSTIBLES Y LUBRICANTES
C44: SUPER SERVICIO RUDEM | D44: 34006 DIESEL | E44: 605.21 | F44: 0 | G44: AMAZON 1 | H44: {=INDEX(CC!C:C,MATCH(1,(CC!A:A=G44)*(CC!B:B=I44),0))} -> 202 | I44: PROPIOS | K44: =IFERROR(__xludf.DUMMYFUNCTION("IFERROR( INDEX( FILTER( MAP( reglas!$B$2:$B$240, reglas!$C$2:$C$240, reglas!$D$2:$D$240, reglas!$E$2:$E$240, LAMBDA(rEmisor,rPatron,rConcepto,rTipo, IF( AND( OR( UPPER(TRIM(rEmisor))=UPPER(TRIM(C44)), UPPER(TRIM(rEmisor))=""CUALQUIERA"" ), OR( UPPER(TRIM("&"rTipo))=""SOLO EMISOR"", AND( UPPER(TRIM(rTipo))=""EXACTA"", UPPER(TRIM(AG44))=UPPER(TRIM(rPatron)) ), AND( OR( UPPER(TRIM(rTipo))=""CONTIENE"", UPPER(TRIM(rTipo))=""COINCIDENCIA"" ), ISNUMBER(SEARCH(UPPER(TRIM(rPatron)),UPPER(TRIM(D44)))) ) ) ), rConcept"&"o, """" ) ) ), MAP( reglas!$B$2:$B$240, reglas!$C$2:$C$240, reglas!$D$2:$D$240, reglas!$E$2:$E$240, LAMBDA(rEmisor,rPatron,rConcepto,rTipo, IF( AND( OR( UPPER(TRIM(rEmisor))=UPPER(TRIM(C44)), UPPER(TRIM(rEmisor))=""CUALQUIERA"" ), OR( UPPER(TRIM(rTipo))="&"""SOLO EMISOR"", AND( UPPER(TRIM(rTipo))=""EXACTA"", UPPER(TRIM(D44))=UPPER(TRIM(rPatron)) ), AND( OR( UPPER(TRIM(rTipo))=""CONTIENE"", UPPER(TRIM(rTipo))=""COINCIDENCIA"" ), ISNUMBER(SEARCH(UPPER(TRIM(rPatron)),UPPER(TRIM(D44)))) ) ) ), rConcepto, """" )"&" ) )<>"""" ), 1 ), """" )"),"COMBUSTIBLES Y LUBRICANTES") -> COMBUSTIBLES Y LUBRICANTES
C45: SUPER SERVICIO RUDEM | D45: 32011 MAGNA | E45: 432.78 | F45: 0 | G45: AMAZON 1 | H45: {=INDEX(CC!C:C,MATCH(1,(CC!A:A=G45)*(CC!B:B=I45),0))} -> 202 | I45: PROPIOS | K45: =IFERROR(__xludf.DUMMYFUNCTION("IFERROR( INDEX( FILTER( MAP( reglas!$B$2:$B$240, reglas!$C$2:$C$240, reglas!$D$2:$D$240, reglas!$E$2:$E$240, LAMBDA(rEmisor,rPatron,rConcepto,rTipo, IF( AND( OR( UPPER(TRIM(rEmisor))=UPPER(TRIM(C45)), UPPER(TRIM(rEmisor))=""CUALQUIERA"" ), OR( UPPER(TRIM("&"rTipo))=""SOLO EMISOR"", AND( UPPER(TRIM(rTipo))=""EXACTA"", UPPER(TRIM(AG45))=UPPER(TRIM(rPatron)) ), AND( OR( UPPER(TRIM(rTipo))=""CONTIENE"", UPPER(TRIM(rTipo))=""COINCIDENCIA"" ), ISNUMBER(SEARCH(UPPER(TRIM(rPatron)),UPPER(TRIM(D45)))) ) ) ), rConcept"&"o, """" ) ) ), MAP( reglas!$B$2:$B$240, reglas!$C$2:$C$240, reglas!$D$2:$D$240, reglas!$E$2:$E$240, LAMBDA(rEmisor,rPatron,rConcepto,rTipo, IF( AND( OR( UPPER(TRIM(rEmisor))=UPPER(TRIM(C45)), UPPER(TRIM(rEmisor))=""CUALQUIERA"" ), OR( UPPER(TRIM(rTipo))="&"""SOLO EMISOR"", AND( UPPER(TRIM(rTipo))=""EXACTA"", UPPER(TRIM(D45))=UPPER(TRIM(rPatron)) ), AND( OR( UPPER(TRIM(rTipo))=""CONTIENE"", UPPER(TRIM(rTipo))=""COINCIDENCIA"" ), ISNUMBER(SEARCH(UPPER(TRIM(rPatron)),UPPER(TRIM(D45)))) ) ) ), rConcepto, """" )"&" ) )<>"""" ), 1 ), """" )"),"COMBUSTIBLES Y LUBRICANTES") -> COMBUSTIBLES Y LUBRICANTES
C46: SUPER SERVICIO RUDEM | D46: 32011 MAGNA | E46: 432.78 | F46: 0 | G46: AMAZON 1 | H46: {=INDEX(CC!C:C,MATCH(1,(CC!A:A=G46)*(CC!B:B=I46),0))} -> 202 | I46: PROPIOS | K46: =IFERROR(__xludf.DUMMYFUNCTION("IFERROR( INDEX( FILTER( MAP( reglas!$B$2:$B$240, reglas!$C$2:$C$240, reglas!$D$2:$D$240, reglas!$E$2:$E$240, LAMBDA(rEmisor,rPatron,rConcepto,rTipo, IF( AND( OR( UPPER(TRIM(rEmisor))=UPPER(TRIM(C46)), UPPER(TRIM(rEmisor))=""CUALQUIERA"" ), OR( UPPER(TRIM("&"rTipo))=""SOLO EMISOR"", AND( UPPER(TRIM(rTipo))=""EXACTA"", UPPER(TRIM(AG46))=UPPER(TRIM(rPatron)) ), AND( OR( UPPER(TRIM(rTipo))=""CONTIENE"", UPPER(TRIM(rTipo))=""COINCIDENCIA"" ), ISNUMBER(SEARCH(UPPER(TRIM(rPatron)),UPPER(TRIM(D46)))) ) ) ), rConcept"&"o, """" ) ) ), MAP( reglas!$B$2:$B$240, reglas!$C$2:$C$240, reglas!$D$2:$D$240, reglas!$E$2:$E$240, LAMBDA(rEmisor,rPatron,rConcepto,rTipo, IF( AND( OR( UPPER(TRIM(rEmisor))=UPPER(TRIM(C46)), UPPER(TRIM(rEmisor))=""CUALQUIERA"" ), OR( UPPER(TRIM(rTipo))="&"""SOLO EMISOR"", AND( UPPER(TRIM(rTipo))=""EXACTA"", UPPER(TRIM(D46))=UPPER(TRIM(rPatron)) ), AND( OR( UPPER(TRIM(rTipo))=""CONTIENE"", UPPER(TRIM(rTipo))=""COINCIDENCIA"" ), ISNUMBER(SEARCH(UPPER(TRIM(rPatron)),UPPER(TRIM(D46)))) ) ) ), rConcepto, """" )"&" ) )<>"""" ), 1 ), """" )"),"COMBUSTIBLES Y LUBRICANTES") -> COMBUSTIBLES Y LUBRICANTES
C47: SUPER SERVICIO RUDEM | D47: BARDAHL HIDRAULICA | E47: 165.52 | F47: 0 | G47: AMAZON 1 | H47: {=INDEX(CC!C:C,MATCH(1,(CC!A:A=G47)*(CC!B:B=I47),0))} -> 202 | I47: PROPIOS | K47: =IFERROR(__xludf.DUMMYFUNCTION("IFERROR( INDEX( FILTER( MAP( reglas!$B$2:$B$240, reglas!$C$2:$C$240, reglas!$D$2:$D$240, reglas!$E$2:$E$240, LAMBDA(rEmisor,rPatron,rConcepto,rTipo, IF( AND( OR( UPPER(TRIM(rEmisor))=UPPER(TRIM(C47)), UPPER(TRIM(rEmisor))=""CUALQUIERA"" ), OR( UPPER(TRIM("&"rTipo))=""SOLO EMISOR"", AND( UPPER(TRIM(rTipo))=""EXACTA"", UPPER(TRIM(AG47))=UPPER(TRIM(rPatron)) ), AND( OR( UPPER(TRIM(rTipo))=""CONTIENE"", UPPER(TRIM(rTipo))=""COINCIDENCIA"" ), ISNUMBER(SEARCH(UPPER(TRIM(rPatron)),UPPER(TRIM(D47)))) ) ) ), rConcept"&"o, """" ) ) ), MAP( reglas!$B$2:$B$240, reglas!$C$2:$C$240, reglas!$D$2:$D$240, reglas!$E$2:$E$240, LAMBDA(rEmisor,rPatron,rConcepto,rTipo, IF( AND( OR( UPPER(TRIM(rEmisor))=UPPER(TRIM(C47)), UPPER(TRIM(rEmisor))=""CUALQUIERA"" ), OR( UPPER(TRIM(rTipo))="&"""SOLO EMISOR"", AND( UPPER(TRIM(rTipo))=""EXACTA"", UPPER(TRIM(D47))=UPPER(TRIM(rPatron)) ), AND( OR( UPPER(TRIM(rTipo))=""CONTIENE"", UPPER(TRIM(rTipo))=""COINCIDENCIA"" ), ISNUMBER(SEARCH(UPPER(TRIM(rPatron)),UPPER(TRIM(D47)))) ) ) ), rConcepto, """" )"&" ) )<>"""" ), 1 ), """" )"),"COMBUSTIBLES Y LUBRICANTES") -> COMBUSTIBLES Y LUBRICANTES
C48: SUPER SERVICIO RUDEM | D48: QUAKER STATE 20W50 ROJO | E48: 212.07 | F48: 0 | G48: AMAZON 1 | H48: {=INDEX(CC!C:C,MATCH(1,(CC!A:A=G48)*(CC!B:B=I48),0))} -> 202 | I48: PROPIOS | K48: =IFERROR(__xludf.DUMMYFUNCTION("IFERROR( INDEX( FILTER( MAP( reglas!$B$2:$B$240, reglas!$C$2:$C$240, reglas!$D$2:$D$240, reglas!$E$2:$E$240, LAMBDA(rEmisor,rPatron,rConcepto,rTipo, IF( AND( OR( UPPER(TRIM(rEmisor))=UPPER(TRIM(C48)), UPPER(TRIM(rEmisor))=""CUALQUIERA"" ), OR( UPPER(TRIM("&"rTipo))=""SOLO EMISOR"", AND( UPPER(TRIM(rTipo))=""EXACTA"", UPPER(TRIM(AG48))=UPPER(TRIM(rPatron)) ), AND( OR( UPPER(TRIM(rTipo))=""CONTIENE"", UPPER(TRIM(rTipo))=""COINCIDENCIA"" ), ISNUMBER(SEARCH(UPPER(TRIM(rPatron)),UPPER(TRIM(D48)))) ) ) ), rConcept"&"o, """" ) ) ), MAP( reglas!$B$2:$B$240, reglas!$C$2:$C$240, reglas!$D$2:$D$240, reglas!$E$2:$E$240, LAMBDA(rEmisor,rPatron,rConcepto,rTipo, IF( AND( OR( UPPER(TRIM(rEmisor))=UPPER(TRIM(C48)), UPPER(TRIM(rEmisor))=""CUALQUIERA"" ), OR( UPPER(TRIM(rTipo))="&"""SOLO EMISOR"", AND( UPPER(TRIM(rTipo))=""EXACTA"", UPPER(TRIM(D48))=UPPER(TRIM(rPatron)) ), AND( OR( UPPER(TRIM(rTipo))=""CONTIENE"", UPPER(TRIM(rTipo))=""COINCIDENCIA"" ), ISNUMBER(SEARCH(UPPER(TRIM(rPatron)),UPPER(TRIM(D48)))) ) ) ), rConcepto, """" )"&" ) )<>"""" ), 1 ), """" )"),"COMBUSTIBLES Y LUBRICANTES") -> COMBUSTIBLES Y LUBRICANTES
C49: SUPER SERVICIO RUDEM | D49: BARDAHL HIDRAULICA | E49: 124.14 | F49: 0 | G49: AMAZON 1 | H49: {=INDEX(CC!C:C,MATCH(1,(CC!A:A=G49)*(CC!B:B=I49),0))} -> 202 | I49: PROPIOS | K49: =IFERROR(__xludf.DUMMYFUNCTION("IFERROR( INDEX( FILTER( MAP( reglas!$B$2:$B$240, reglas!$C$2:$C$240, reglas!$D$2:$D$240, reglas!$E$2:$E$240, LAMBDA(rEmisor,rPatron,rConcepto,rTipo, IF( AND( OR( UPPER(TRIM(rEmisor))=UPPER(TRIM(C49)), UPPER(TRIM(rEmisor))=""CUALQUIERA"" ), OR( UPPER(TRIM("&"rTipo))=""SOLO EMISOR"", AND( UPPER(TRIM(rTipo))=""EXACTA"", UPPER(TRIM(AG49))=UPPER(TRIM(rPatron)) ), AND( OR( UPPER(TRIM(rTipo))=""CONTIENE"", UPPER(TRIM(rTipo))=""COINCIDENCIA"" ), ISNUMBER(SEARCH(UPPER(TRIM(rPatron)),UPPER(TRIM(D49)))) ) ) ), rConcept"&"o, """" ) ) ), MAP( reglas!$B$2:$B$240, reglas!$C$2:$C$240, reglas!$D$2:$D$240, reglas!$E$2:$E$240, LAMBDA(rEmisor,rPatron,rConcepto,rTipo, IF( AND( OR( UPPER(TRIM(rEmisor))=UPPER(TRIM(C49)), UPPER(TRIM(rEmisor))=""CUALQUIERA"" ), OR( UPPER(TRIM(rTipo))="&"""SOLO EMISOR"", AND( UPPER(TRIM(rTipo))=""EXACTA"", UPPER(TRIM(D49))=UPPER(TRIM(rPatron)) ), AND( OR( UPPER(TRIM(rTipo))=""CONTIENE"", UPPER(TRIM(rTipo))=""COINCIDENCIA"" ), ISNUMBER(SEARCH(UPPER(TRIM(rPatron)),UPPER(TRIM(D49)))) ) ) ), rConcepto, """" )"&" ) )<>"""" ), 1 ), """" )"),"COMBUSTIBLES Y LUBRICANTES") -> COMBUSTIBLES Y LUBRICANTES
C50: SUPER SERVICIO RUDEM | D50: 32011 MAGNA | E50: 700.68 | F50: 0 | G50: AMAZON 1 | H50: {=INDEX(CC!C:C,MATCH(1,(CC!A:A=G50)*(CC!B:B=I50),0))} -> 202 | I50: PROPIOS | K50: =IFERROR(__xludf.DUMMYFUNCTION("IFERROR( INDEX( FILTER( MAP( reglas!$B$2:$B$240, reglas!$C$2:$C$240, reglas!$D$2:$D$240, reglas!$E$2:$E$240, LAMBDA(rEmisor,rPatron,rConcepto,rTipo, IF( AND( OR( UPPER(TRIM(rEmisor))=UPPER(TRIM(C50)), UPPER(TRIM(rEmisor))=""CUALQUIERA"" ), OR( UPPER(TRIM("&"rTipo))=""SOLO EMISOR"", AND( UPPER(TRIM(rTipo))=""EXACTA"", UPPER(TRIM(AG50))=UPPER(TRIM(rPatron)) ), AND( OR( UPPER(TRIM(rTipo))=""CONTIENE"", UPPER(TRIM(rTipo))=""COINCIDENCIA"" ), ISNUMBER(SEARCH(UPPER(TRIM(rPatron)),UPPER(TRIM(D50)))) ) ) ), rConcept"&"o, """" ) ) ), MAP( reglas!$B$2:$B$240, reglas!$C$2:$C$240, reglas!$D$2:$D$240, reglas!$E$2:$E$240, LAMBDA(rEmisor,rPatron,rConcepto,rTipo, IF( AND( OR( UPPER(TRIM(rEmisor))=UPPER(TRIM(C50)), UPPER(TRIM(rEmisor))=""CUALQUIERA"" ), OR( UPPER(TRIM(rTipo))="&"""SOLO EMISOR"", AND( UPPER(TRIM(rTipo))=""EXACTA"", UPPER(TRIM(D50))=UPPER(TRIM(rPatron)) ), AND( OR( UPPER(TRIM(rTipo))=""CONTIENE"", UPPER(TRIM(rTipo))=""COINCIDENCIA"" ), ISNUMBER(SEARCH(UPPER(TRIM(rPatron)),UPPER(TRIM(D50)))) ) ) ), rConcepto, """" )"&" ) )<>"""" ), 1 ), """" )"),"COMBUSTIBLES Y LUBRICANTES") -> COMBUSTIBLES Y LUBRICANTES
C51: SUPER SERVICIO RUDEM | D51: 32011 MAGNA | E51: 197.5 | F51: 0 | G51: AMAZON 1 | H51: {=INDEX(CC!C:C,MATCH(1,(CC!A:A=G51)*(CC!B:B=I51),0))} -> 202 | I51: PROPIOS | K51: =IFERROR(__xludf.DUMMYFUNCTION("IFERROR( INDEX( FILTER( MAP( reglas!$B$2:$B$240, reglas!$C$2:$C$240, reglas!$D$2:$D$240, reglas!$E$2:$E$240, LAMBDA(rEmisor,rPatron,rConcepto,rTipo, IF( AND( OR( UPPER(TRIM(rEmisor))=UPPER(TRIM(C51)), UPPER(TRIM(rEmisor))=""CUALQUIERA"" ), OR( UPPER(TRIM("&"rTipo))=""SOLO EMISOR"", AND( UPPER(TRIM(rTipo))=""EXACTA"", UPPER(TRIM(AG51))=UPPER(TRIM(rPatron)) ), AND( OR( UPPER(TRIM(rTipo))=""CONTIENE"", UPPER(TRIM(rTipo))=""COINCIDENCIA"" ), ISNUMBER(SEARCH(UPPER(TRIM(rPatron)),UPPER(TRIM(D51)))) ) ) ), rConcept"&"o, """" ) ) ), MAP( reglas!$B$2:$B$240, reglas!$C$2:$C$240, reglas!$D$2:$D$240, reglas!$E$2:$E$240, LAMBDA(rEmisor,rPatron,rConcepto,rTipo, IF( AND( OR( UPPER(TRIM(rEmisor))=UPPER(TRIM(C51)), UPPER(TRIM(rEmisor))=""CUALQUIERA"" ), OR( UPPER(TRIM(rTipo))="&"""SOLO EMISOR"", AND( UPPER(TRIM(rTipo))=""EXACTA"", UPPER(TRIM(D51))=UPPER(TRIM(rPatron)) ), AND( OR( UPPER(TRIM(rTipo))=""CONTIENE"", UPPER(TRIM(rTipo))=""COINCIDENCIA"" ), ISNUMBER(SEARCH(UPPER(TRIM(rPatron)),UPPER(TRIM(D51)))) ) ) ), rConcepto, """" )"&" ) )<>"""" ), 1 ), """" )"),"COMBUSTIBLES Y LUBRICANTES") -> COMBUSTIBLES Y LUBRICANTES
C52: SUPER SERVICIO RUDEM | D52: 32011 MAGNA | E52: 160.73 | F52: 0 | G52: AMAZON 1 | H52: {=INDEX(CC!C:C,MATCH(1,(CC!A:A=G52)*(CC!B:B=I52),0))} -> 202 | I52: PROPIOS | K52: =IFERROR(__xludf.DUMMYFUNCTION("IFERROR( INDEX( FILTER( MAP( reglas!$B$2:$B$240, reglas!$C$2:$C$240, reglas!$D$2:$D$240, reglas!$E$2:$E$240, LAMBDA(rEmisor,rPatron,rConcepto,rTipo, IF( AND( OR( UPPER(TRIM(rEmisor))=UPPER(TRIM(C52)), UPPER(TRIM(rEmisor))=""CUALQUIERA"" ), OR( UPPER(TRIM("&"rTipo))=""SOLO EMISOR"", AND( UPPER(TRIM(rTipo))=""EXACTA"", UPPER(TRIM(AG52))=UPPER(TRIM(rPatron)) ), AND( OR( UPPER(TRIM(rTipo))=""CONTIENE"", UPPER(TRIM(rTipo))=""COINCIDENCIA"" ), ISNUMBER(SEARCH(UPPER(TRIM(rPatron)),UPPER(TRIM(D52)))) ) ) ), rConcept"&"o, """" ) ) ), MAP( reglas!$B$2:$B$240, reglas!$C$2:$C$240, reglas!$D$2:$D$240, reglas!$E$2:$E$240, LAMBDA(rEmisor,rPatron,rConcepto,rTipo, IF( AND( OR( UPPER(TRIM(rEmisor))=UPPER(TRIM(C52)), UPPER(TRIM(rEmisor))=""CUALQUIERA"" ), OR( UPPER(TRIM(rTipo))="&"""SOLO EMISOR"", AND( UPPER(TRIM(rTipo))=""EXACTA"", UPPER(TRIM(D52))=UPPER(TRIM(rPatron)) ), AND( OR( UPPER(TRIM(rTipo))=""CONTIENE"", UPPER(TRIM(rTipo))=""COINCIDENCIA"" ), ISNUMBER(SEARCH(UPPER(TRIM(rPatron)),UPPER(TRIM(D52)))) ) ) ), rConcepto, """" )"&" ) )<>"""" ), 1 ), """" )"),"COMBUSTIBLES Y LUBRICANTES") -> COMBUSTIBLES Y LUBRICANTES
C53: SUPER SERVICIO RUDEM | D53: 32011 MAGNA | E53: 445 | F53: 0 | G53: AMAZON 1 | H53: {=INDEX(CC!C:C,MATCH(1,(CC!A:A=G53)*(CC!B:B=I53),0))} -> 202 | I53: PROPIOS | K53: =IFERROR(__xludf.DUMMYFUNCTION("IFERROR( INDEX( FILTER( MAP( reglas!$B$2:$B$240, reglas!$C$2:$C$240, reglas!$D$2:$D$240, reglas!$E$2:$E$240, LAMBDA(rEmisor,rPatron,rConcepto,rTipo, IF( AND( OR( UPPER(TRIM(rEmisor))=UPPER(TRIM(C53)), UPPER(TRIM(rEmisor))=""CUALQUIERA"" ), OR( UPPER(TRIM("&"rTipo))=""SOLO EMISOR"", AND( UPPER(TRIM(rTipo))=""EXACTA"", UPPER(TRIM(AG53))=UPPER(TRIM(rPatron)) ), AND( OR( UPPER(TRIM(rTipo))=""CONTIENE"", UPPER(TRIM(rTipo))=""COINCIDENCIA"" ), ISNUMBER(SEARCH(UPPER(TRIM(rPatron)),UPPER(TRIM(D53)))) ) ) ), rConcept"&"o, """" ) ) ), MAP( reglas!$B$2:$B$240, reglas!$C$2:$C$240, reglas!$D$2:$D$240, reglas!$E$2:$E$240, LAMBDA(rEmisor,rPatron,rConcepto,rTipo, IF( AND( OR( UPPER(TRIM(rEmisor))=UPPER(TRIM(C53)), UPPER(TRIM(rEmisor))=""CUALQUIERA"" ), OR( UPPER(TRIM(rTipo))="&"""SOLO EMISOR"", AND( UPPER(TRIM(rTipo))=""EXACTA"", UPPER(TRIM(D53))=UPPER(TRIM(rPatron)) ), AND( OR( UPPER(TRIM(rTipo))=""CONTIENE"", UPPER(TRIM(rTipo))=""COINCIDENCIA"" ), ISNUMBER(SEARCH(UPPER(TRIM(rPatron)),UPPER(TRIM(D53)))) ) ) ), rConcepto, """" )"&" ) )<>"""" ), 1 ), """" )"),"COMBUSTIBLES Y LUBRICANTES") -> COMBUSTIBLES Y LUBRICANTES
C54: SUPER SERVICIO RUDEM | D54: 32011 MAGNA | E54: 597.05 | F54: 0 | G54: AMAZON 1 | H54: {=INDEX(CC!C:C,MATCH(1,(CC!A:A=G54)*(CC!B:B=I54),0))} -> 202 | I54: PROPIOS | K54: =IFERROR(__xludf.DUMMYFUNCTION("IFERROR( INDEX( FILTER( MAP( reglas!$B$2:$B$240, reglas!$C$2:$C$240, reglas!$D$2:$D$240, reglas!$E$2:$E$240, LAMBDA(rEmisor,rPatron,rConcepto,rTipo, IF( AND( OR( UPPER(TRIM(rEmisor))=UPPER(TRIM(C54)), UPPER(TRIM(rEmisor))=""CUALQUIERA"" ), OR( UPPER(TRIM("&"rTipo))=""SOLO EMISOR"", AND( UPPER(TRIM(rTipo))=""EXACTA"", UPPER(TRIM(AG54))=UPPER(TRIM(rPatron)) ), AND( OR( UPPER(TRIM(rTipo))=""CONTIENE"", UPPER(TRIM(rTipo))=""COINCIDENCIA"" ), ISNUMBER(SEARCH(UPPER(TRIM(rPatron)),UPPER(TRIM(D54)))) ) ) ), rConcept"&"o, """" ) ) ), MAP( reglas!$B$2:$B$240, reglas!$C$2:$C$240, reglas!$D$2:$D$240, reglas!$E$2:$E$240, LAMBDA(rEmisor,rPatron,rConcepto,rTipo, IF( AND( OR( UPPER(TRIM(rEmisor))=UPPER(TRIM(C54)), UPPER(TRIM(rEmisor))=""CUALQUIERA"" ), OR( UPPER(TRIM(rTipo))="&"""SOLO EMISOR"", AND( UPPER(TRIM(rTipo))=""EXACTA"", UPPER(TRIM(D54))=UPPER(TRIM(rPatron)) ), AND( OR( UPPER(TRIM(rTipo))=""CONTIENE"", UPPER(TRIM(rTipo))=""COINCIDENCIA"" ), ISNUMBER(SEARCH(UPPER(TRIM(rPatron)),UPPER(TRIM(D54)))) ) ) ), rConcepto, """" )"&" ) )<>"""" ), 1 ), """" )"),"COMBUSTIBLES Y LUBRICANTES") -> COMBUSTIBLES Y LUBRICANTES
C55: SUPER SERVICIO RUDEM | D55: BARDAHL HIDRAULICA | E55: 165.52 | F55: 0 | G55: AMAZON 1 | H55: {=INDEX(CC!C:C,MATCH(1,(CC!A:A=G55)*(CC!B:B=I55),0))} -> 202 | I55: PROPIOS | K55: =IFERROR(__xludf.DUMMYFUNCTION("IFERROR( INDEX( FILTER( MAP( reglas!$B$2:$B$240, reglas!$C$2:$C$240, reglas!$D$2:$D$240, reglas!$E$2:$E$240, LAMBDA(rEmisor,rPatron,rConcepto,rTipo, IF( AND( OR( UPPER(TRIM(rEmisor))=UPPER(TRIM(C55)), UPPER(TRIM(rEmisor))=""CUALQUIERA"" ), OR( UPPER(TRIM("&"rTipo))=""SOLO EMISOR"", AND( UPPER(TRIM(rTipo))=""EXACTA"", UPPER(TRIM(AG55))=UPPER(TRIM(rPatron)) ), AND( OR( UPPER(TRIM(rTipo))=""CONTIENE"", UPPER(TRIM(rTipo))=""COINCIDENCIA"" ), ISNUMBER(SEARCH(UPPER(TRIM(rPatron)),UPPER(TRIM(D55)))) ) ) ), rConcept"&"o, """" ) ) ), MAP( reglas!$B$2:$B$240, reglas!$C$2:$C$240, reglas!$D$2:$D$240, reglas!$E$2:$E$240, LAMBDA(rEmisor,rPatron,rConcepto,rTipo, IF( AND( OR( UPPER(TRIM(rEmisor))=UPPER(TRIM(C55)), UPPER(TRIM(rEmisor))=""CUALQUIERA"" ), OR( UPPER(TRIM(rTipo))="&"""SOLO EMISOR"", AND( UPPER(TRIM(rTipo))=""EXACTA"", UPPER(TRIM(D55))=UPPER(TRIM(rPatron)) ), AND( OR( UPPER(TRIM(rTipo))=""CONTIENE"", UPPER(TRIM(rTipo))=""COINCIDENCIA"" ), ISNUMBER(SEARCH(UPPER(TRIM(rPatron)),UPPER(TRIM(D55)))) ) ) ), rConcepto, """" )"&" ) )<>"""" ), 1 ), """" )"),"COMBUSTIBLES Y LUBRICANTES") -> COMBUSTIBLES Y LUBRICANTES
A56: 1 | B56: MXN | C56: DHL EXPRESS MEXICO | D56: EXPRESS DOMESTIC | E56: 1760.52 | F56: 0 | G56: CDMX | H56: {=INDEX(CC!C:C,MATCH(1,(CC!A:A=G56)*(CC!B:B=I56),0))} -> 1503 | I56: TERCEROS | J56: 1760.52 | K56: =IFERROR(__xludf.DUMMYFUNCTION("IFERROR( INDEX( FILTER( MAP( reglas!$B$2:$B$240, reglas!$C$2:$C$240, reglas!$D$2:$D$240, reglas!$E$2:$E$240, LAMBDA(rEmisor,rPatron,rConcepto,rTipo, IF( AND( OR( UPPER(TRIM(rEmisor))=UPPER(TRIM(C56)), UPPER(TRIM(rEmisor))=""CUALQUIERA"" ), OR( UPPER(TRIM("&"rTipo))=""SOLO EMISOR"", AND( UPPER(TRIM(rTipo))=""EXACTA"", UPPER(TRIM(AG56))=UPPER(TRIM(rPatron)) ), AND( OR( UPPER(TRIM(rTipo))=""CONTIENE"", UPPER(TRIM(rTipo))=""COINCIDENCIA"" ), ISNUMBER(SEARCH(UPPER(TRIM(rPatron)),UPPER(TRIM(D56)))) ) ) ), rConcept"&"o, """" ) ) ), MAP( reglas!$B$2:$B$240, reglas!$C$2:$C$240, reglas!$D$2:$D$240, reglas!$E$2:$E$240, LAMBDA(rEmisor,rPatron,rConcepto,rTipo, IF( AND( OR( UPPER(TRIM(rEmisor))=UPPER(TRIM(C56)), UPPER(TRIM(rEmisor))=""CUALQUIERA"" ), OR( UPPER(TRIM(rTipo))="&"""SOLO EMISOR"", AND( UPPER(TRIM(rTipo))=""EXACTA"", UPPER(TRIM(D56))=UPPER(TRIM(rPatron)) ), AND( OR( UPPER(TRIM(rTipo))=""CONTIENE"", UPPER(TRIM(rTipo))=""COINCIDENCIA"" ), ISNUMBER(SEARCH(UPPER(TRIM(rPatron)),UPPER(TRIM(D56)))) ) ) ), rConcepto, """" )"&" ) )<>"""" ), 1 ), """" )"),"GUIAS") -> GUIAS
A57: 1 | B57: MXN | C57: DHL EXPRESS MEXICO | D57: EXPRESS DOMESTIC | E57: 379 | F57: 0 | G57: CDMX | H57: {=INDEX(CC!C:C,MATCH(1,(CC!A:A=G57)*(CC!B:B=I57),0))} -> 1503 | I57: TERCEROS | J57: 379 | K57: =IFERROR(__xludf.DUMMYFUNCTION("IFERROR( INDEX( FILTER( MAP( reglas!$B$2:$B$240, reglas!$C$2:$C$240, reglas!$D$2:$D$240, reglas!$E$2:$E$240, LAMBDA(rEmisor,rPatron,rConcepto,rTipo, IF( AND( OR( UPPER(TRIM(rEmisor))=UPPER(TRIM(C57)), UPPER(TRIM(rEmisor))=""CUALQUIERA"" ), OR( UPPER(TRIM("&"rTipo))=""SOLO EMISOR"", AND( UPPER(TRIM(rTipo))=""EXACTA"", UPPER(TRIM(AG57))=UPPER(TRIM(rPatron)) ), AND( OR( UPPER(TRIM(rTipo))=""CONTIENE"", UPPER(TRIM(rTipo))=""COINCIDENCIA"" ), ISNUMBER(SEARCH(UPPER(TRIM(rPatron)),UPPER(TRIM(D57)))) ) ) ), rConcept"&"o, """" ) ) ), MAP( reglas!$B$2:$B$240, reglas!$C$2:$C$240, reglas!$D$2:$D$240, reglas!$E$2:$E$240, LAMBDA(rEmisor,rPatron,rConcepto,rTipo, IF( AND( OR( UPPER(TRIM(rEmisor))=UPPER(TRIM(C57)), UPPER(TRIM(rEmisor))=""CUALQUIERA"" ), OR( UPPER(TRIM(rTipo))="&"""SOLO EMISOR"", AND( UPPER(TRIM(rTipo))=""EXACTA"", UPPER(TRIM(D57))=UPPER(TRIM(rPatron)) ), AND( OR( UPPER(TRIM(rTipo))=""CONTIENE"", UPPER(TRIM(rTipo))=""COINCIDENCIA"" ), ISNUMBER(SEARCH(UPPER(TRIM(rPatron)),UPPER(TRIM(D57)))) ) ) ), rConcepto, """" )"&" ) )<>"""" ), 1 ), """" )"),"GUIAS") -> GUIAS
B58: MXN | C58: SISTEMA UNIFICADO DE MANIOBRAS AEREAS PARA AGENTES ADUANALES | D58: DESCARGA Y CARGA | E58: 1000 | F58: 0 | G58: IMILE AIFA | H58: {=INDEX(CC!C:C,MATCH(1,(CC!A:A=G58)*(CC!B:B=I58),0))} -> 1402 | I58: PROPIOS | J58: 1000 | K58: =IFERROR(__xludf.DUMMYFUNCTION("IFERROR( INDEX( FILTER( MAP( reglas!$B$2:$B$240, reglas!$C$2:$C$240, reglas!$D$2:$D$240, reglas!$E$2:$E$240, LAMBDA(rEmisor,rPatron,rConcepto,rTipo, IF( AND( OR( UPPER(TRIM(rEmisor))=UPPER(TRIM(C58)), UPPER(TRIM(rEmisor))=""CUALQUIERA"" ), OR( UPPER(TRIM("&"rTipo))=""SOLO EMISOR"", AND( UPPER(TRIM(rTipo))=""EXACTA"", UPPER(TRIM(AG58))=UPPER(TRIM(rPatron)) ), AND( OR( UPPER(TRIM(rTipo))=""CONTIENE"", UPPER(TRIM(rTipo))=""COINCIDENCIA"" ), ISNUMBER(SEARCH(UPPER(TRIM(rPatron)),UPPER(TRIM(D58)))) ) ) ), rConcept"&"o, """" ) ) ), MAP( reglas!$B$2:$B$240, reglas!$C$2:$C$240, reglas!$D$2:$D$240, reglas!$E$2:$E$240, LAMBDA(rEmisor,rPatron,rConcepto,rTipo, IF( AND( OR( UPPER(TRIM(rEmisor))=UPPER(TRIM(C58)), UPPER(TRIM(rEmisor))=""CUALQUIERA"" ), OR( UPPER(TRIM(rTipo))="&"""SOLO EMISOR"", AND( UPPER(TRIM(rTipo))=""EXACTA"", UPPER(TRIM(D58))=UPPER(TRIM(rPatron)) ), AND( OR( UPPER(TRIM(rTipo))=""CONTIENE"", UPPER(TRIM(rTipo))=""COINCIDENCIA"" ), ISNUMBER(SEARCH(UPPER(TRIM(rPatron)),UPPER(TRIM(D58)))) ) ) ), rConcepto, """" )"&" ) )<>"""" ), 1 ), """" )"),"MANIOBRAS") -> MANIOBRAS
B59: MXN | C59: SISTEMA UNIFICADO DE MANIOBRAS AEREAS PARA AGENTES ADUANALES | D59: Carga de camión | E59: 3500 | F59: 0 | G59: IMILE AIFA | H59: {=INDEX(CC!C:C,MATCH(1,(CC!A:A=G59)*(CC!B:B=I59),0))} -> 1402 | I59: PROPIOS | J59: 3500 | K59: =IFERROR(__xludf.DUMMYFUNCTION("IFERROR( INDEX( FILTER( MAP( reglas!$B$2:$B$240, reglas!$C$2:$C$240, reglas!$D$2:$D$240, reglas!$E$2:$E$240, LAMBDA(rEmisor,rPatron,rConcepto,rTipo, IF( AND( OR( UPPER(TRIM(rEmisor))=UPPER(TRIM(C59)), UPPER(TRIM(rEmisor))=""CUALQUIERA"" ), OR( UPPER(TRIM("&"rTipo))=""SOLO EMISOR"", AND( UPPER(TRIM(rTipo))=""EXACTA"", UPPER(TRIM(AG59))=UPPER(TRIM(rPatron)) ), AND( OR( UPPER(TRIM(rTipo))=""CONTIENE"", UPPER(TRIM(rTipo))=""COINCIDENCIA"" ), ISNUMBER(SEARCH(UPPER(TRIM(rPatron)),UPPER(TRIM(D59)))) ) ) ), rConcept"&"o, """" ) ) ), MAP( reglas!$B$2:$B$240, reglas!$C$2:$C$240, reglas!$D$2:$D$240, reglas!$E$2:$E$240, LAMBDA(rEmisor,rPatron,rConcepto,rTipo, IF( AND( OR( UPPER(TRIM(rEmisor))=UPPER(TRIM(C59)), UPPER(TRIM(rEmisor))=""CUALQUIERA"" ), OR( UPPER(TRIM(rTipo))="&"""SOLO EMISOR"", AND( UPPER(TRIM(rTipo))=""EXACTA"", UPPER(TRIM(D59))=UPPER(TRIM(rPatron)) ), AND( OR( UPPER(TRIM(rTipo))=""CONTIENE"", UPPER(TRIM(rTipo))=""COINCIDENCIA"" ), ISNUMBER(SEARCH(UPPER(TRIM(rPatron)),UPPER(TRIM(D59)))) ) ) ), rConcepto, """" )"&" ) )<>"""" ), 1 ), """" )"),"MANIOBRAS") -> MANIOBRAS
A60: 1 | B60: MXN | C60: FEDERAL EXPRESS HOLDINGS (MEXICO) Y COMPAÑIA | D60: Cambio de Instruccion | E60: 634.54 | F60: 0 | G60: TOLUCA | H60: {=INDEX(CC!C:C,MATCH(1,(CC!A:A=G60)*(CC!B:B=I60),0))} -> 1002 | I60: PROPIOS | J60: 634.54 | K60: =IFERROR(__xludf.DUMMYFUNCTION("IFERROR( INDEX( FILTER( MAP( reglas!$B$2:$B$240, reglas!$C$2:$C$240, reglas!$D$2:$D$240, reglas!$E$2:$E$240, LAMBDA(rEmisor,rPatron,rConcepto,rTipo, IF( AND( OR( UPPER(TRIM(rEmisor))=UPPER(TRIM(C60)), UPPER(TRIM(rEmisor))=""CUALQUIERA"" ), OR( UPPER(TRIM("&"rTipo))=""SOLO EMISOR"", AND( UPPER(TRIM(rTipo))=""EXACTA"", UPPER(TRIM(AG60))=UPPER(TRIM(rPatron)) ), AND( OR( UPPER(TRIM(rTipo))=""CONTIENE"", UPPER(TRIM(rTipo))=""COINCIDENCIA"" ), ISNUMBER(SEARCH(UPPER(TRIM(rPatron)),UPPER(TRIM(D60)))) ) ) ), rConcept"&"o, """" ) ) ), MAP( reglas!$B$2:$B$240, reglas!$C$2:$C$240, reglas!$D$2:$D$240, reglas!$E$2:$E$240, LAMBDA(rEmisor,rPatron,rConcepto,rTipo, IF( AND( OR( UPPER(TRIM(rEmisor))=UPPER(TRIM(C60)), UPPER(TRIM(rEmisor))=""CUALQUIERA"" ), OR( UPPER(TRIM(rTipo))="&"""SOLO EMISOR"", AND( UPPER(TRIM(rTipo))=""EXACTA"", UPPER(TRIM(D60))=UPPER(TRIM(rPatron)) ), AND( OR( UPPER(TRIM(rTipo))=""CONTIENE"", UPPER(TRIM(rTipo))=""COINCIDENCIA"" ), ISNUMBER(SEARCH(UPPER(TRIM(rPatron)),UPPER(TRIM(D60)))) ) ) ), rConcepto, """" )"&" ) )<>"""" ), 1 ), """" )"),"MANIOBRAS") -> MANIOBRAS
C61: FEDERAL EXPRESS HOLDINGS (MEXICO) Y COMPAÑIA | D61: Asignacion de Guia Aerea | E61: 580.56 | F61: 0 | G61: TOLUCA | H61: {=INDEX(CC!C:C,MATCH(1,(CC!A:A=G61)*(CC!B:B=I61),0))} -> 1002 | I61: PROPIOS | J61: 580.56 | K61: =IFERROR(__xludf.DUMMYFUNCTION("IFERROR( INDEX( FILTER( MAP( reglas!$B$2:$B$240, reglas!$C$2:$C$240, reglas!$D$2:$D$240, reglas!$E$2:$E$240, LAMBDA(rEmisor,rPatron,rConcepto,rTipo, IF( AND( OR( UPPER(TRIM(rEmisor))=UPPER(TRIM(C61)), UPPER(TRIM(rEmisor))=""CUALQUIERA"" ), OR( UPPER(TRIM("&"rTipo))=""SOLO EMISOR"", AND( UPPER(TRIM(rTipo))=""EXACTA"", UPPER(TRIM(AG61))=UPPER(TRIM(rPatron)) ), AND( OR( UPPER(TRIM(rTipo))=""CONTIENE"", UPPER(TRIM(rTipo))=""COINCIDENCIA"" ), ISNUMBER(SEARCH(UPPER(TRIM(rPatron)),UPPER(TRIM(D61)))) ) ) ), rConcept"&"o, """" ) ) ), MAP( reglas!$B$2:$B$240, reglas!$C$2:$C$240, reglas!$D$2:$D$240, reglas!$E$2:$E$240, LAMBDA(rEmisor,rPatron,rConcepto,rTipo, IF( AND( OR( UPPER(TRIM(rEmisor))=UPPER(TRIM(C61)), UPPER(TRIM(rEmisor))=""CUALQUIERA"" ), OR( UPPER(TRIM(rTipo))="&"""SOLO EMISOR"", AND( UPPER(TRIM(rTipo))=""EXACTA"", UPPER(TRIM(D61))=UPPER(TRIM(rPatron)) ), AND( OR( UPPER(TRIM(rTipo))=""CONTIENE"", UPPER(TRIM(rTipo))=""COINCIDENCIA"" ), ISNUMBER(SEARCH(UPPER(TRIM(rPatron)),UPPER(TRIM(D61)))) ) ) ), rConcepto, """" )"&" ) )<>"""" ), 1 ), """" )"),"MANIOBRAS") -> MANIOBRAS
C62: FEDERAL EXPRESS HOLDINGS (MEXICO) Y COMPAÑIA | D62: Manejo | E62: 634.89 | F62: 0 | G62: TOLUCA | H62: {=INDEX(CC!C:C,MATCH(1,(CC!A:A=G62)*(CC!B:B=I62),0))} -> 1002 | I62: PROPIOS | J62: 634.89 | K62: =IFERROR(__xludf.DUMMYFUNCTION("IFERROR( INDEX( FILTER( MAP( reglas!$B$2:$B$240, reglas!$C$2:$C$240, reglas!$D$2:$D$240, reglas!$E$2:$E$240, LAMBDA(rEmisor,rPatron,rConcepto,rTipo, IF( AND( OR( UPPER(TRIM(rEmisor))=UPPER(TRIM(C62)), UPPER(TRIM(rEmisor))=""CUALQUIERA"" ), OR( UPPER(TRIM("&"rTipo))=""SOLO EMISOR"", AND( UPPER(TRIM(rTipo))=""EXACTA"", UPPER(TRIM(AG62))=UPPER(TRIM(rPatron)) ), AND( OR( UPPER(TRIM(rTipo))=""CONTIENE"", UPPER(TRIM(rTipo))=""COINCIDENCIA"" ), ISNUMBER(SEARCH(UPPER(TRIM(rPatron)),UPPER(TRIM(D62)))) ) ) ), rConcept"&"o, """" ) ) ), MAP( reglas!$B$2:$B$240, reglas!$C$2:$C$240, reglas!$D$2:$D$240, reglas!$E$2:$E$240, LAMBDA(rEmisor,rPatron,rConcepto,rTipo, IF( AND( OR( UPPER(TRIM(rEmisor))=UPPER(TRIM(C62)), UPPER(TRIM(rEmisor))=""CUALQUIERA"" ), OR( UPPER(TRIM(rTipo))="&"""SOLO EMISOR"", AND( UPPER(TRIM(rTipo))=""EXACTA"", UPPER(TRIM(D62))=UPPER(TRIM(rPatron)) ), AND( OR( UPPER(TRIM(rTipo))=""CONTIENE"", UPPER(TRIM(rTipo))=""COINCIDENCIA"" ), ISNUMBER(SEARCH(UPPER(TRIM(rPatron)),UPPER(TRIM(D62)))) ) ) ), rConcepto, """" )"&" ) )<>"""" ), 1 ), """" )"),"MANIOBRAS") -> MANIOBRAS
C63: FEDERAL EXPRESS HOLDINGS (MEXICO) Y COMPAÑIA | D63: Maniobras para Previo | E63: 666.13 | F63: 0 | G63: TOLUCA | H63: {=INDEX(CC!C:C,MATCH(1,(CC!A:A=G63)*(CC!B:B=I63),0))} -> 1002 | I63: PROPIOS | J63: 666.13 | K63: =IFERROR(__xludf.DUMMYFUNCTION("IFERROR( INDEX( FILTER( MAP( reglas!$B$2:$B$240, reglas!$C$2:$C$240, reglas!$D$2:$D$240, reglas!$E$2:$E$240, LAMBDA(rEmisor,rPatron,rConcepto,rTipo, IF( AND( OR( UPPER(TRIM(rEmisor))=UPPER(TRIM(C63)), UPPER(TRIM(rEmisor))=""CUALQUIERA"" ), OR( UPPER(TRIM("&"rTipo))=""SOLO EMISOR"", AND( UPPER(TRIM(rTipo))=""EXACTA"", UPPER(TRIM(AG63))=UPPER(TRIM(rPatron)) ), AND( OR( UPPER(TRIM(rTipo))=""CONTIENE"", UPPER(TRIM(rTipo))=""COINCIDENCIA"" ), ISNUMBER(SEARCH(UPPER(TRIM(rPatron)),UPPER(TRIM(D63)))) ) ) ), rConcept"&"o, """" ) ) ), MAP( reglas!$B$2:$B$240, reglas!$C$2:$C$240, reglas!$D$2:$D$240, reglas!$E$2:$E$240, LAMBDA(rEmisor,rPatron,rConcepto,rTipo, IF( AND( OR( UPPER(TRIM(rEmisor))=UPPER(TRIM(C63)), UPPER(TRIM(rEmisor))=""CUALQUIERA"" ), OR( UPPER(TRIM(rTipo))="&"""SOLO EMISOR"", AND( UPPER(TRIM(rTipo))=""EXACTA"", UPPER(TRIM(D63))=UPPER(TRIM(rPatron)) ), AND( OR( UPPER(TRIM(rTipo))=""CONTIENE"", UPPER(TRIM(rTipo))=""COINCIDENCIA"" ), ISNUMBER(SEARCH(UPPER(TRIM(rPatron)),UPPER(TRIM(D63)))) ) ) ), rConcepto, """" )"&" ) )<>"""" ), 1 ), """" )"),"MANIOBRAS") -> MANIOBRAS
A64: 1 | B64: MXN | C64: SUALSA | D64: PALETIZADA TOTAL DE TRAILER | E64: 1283.04 | F64: 0 | G64: ESTAFETA | H64: {=INDEX(CC!C:C,MATCH(1,(CC!A:A=G64)*(CC!B:B=I64),0))} -> 403 | I64: TERCEROS | J64: 1283.04 | K64: =IFERROR(__xludf.DUMMYFUNCTION("IFERROR( INDEX( FILTER( MAP( reglas!$B$2:$B$240, reglas!$C$2:$C$240, reglas!$D$2:$D$240, reglas!$E$2:$E$240, LAMBDA(rEmisor,rPatron,rConcepto,rTipo, IF( AND( OR( UPPER(TRIM(rEmisor))=UPPER(TRIM(C64)), UPPER(TRIM(rEmisor))=""CUALQUIERA"" ), OR( UPPER(TRIM("&"rTipo))=""SOLO EMISOR"", AND( UPPER(TRIM(rTipo))=""EXACTA"", UPPER(TRIM(AG64))=UPPER(TRIM(rPatron)) ), AND( OR( UPPER(TRIM(rTipo))=""CONTIENE"", UPPER(TRIM(rTipo))=""COINCIDENCIA"" ), ISNUMBER(SEARCH(UPPER(TRIM(rPatron)),UPPER(TRIM(D64)))) ) ) ), rConcept"&"o, """" ) ) ), MAP( reglas!$B$2:$B$240, reglas!$C$2:$C$240, reglas!$D$2:$D$240, reglas!$E$2:$E$240, LAMBDA(rEmisor,rPatron,rConcepto,rTipo, IF( AND( OR( UPPER(TRIM(rEmisor))=UPPER(TRIM(C64)), UPPER(TRIM(rEmisor))=""CUALQUIERA"" ), OR( UPPER(TRIM(rTipo))="&"""SOLO EMISOR"", AND( UPPER(TRIM(rTipo))=""EXACTA"", UPPER(TRIM(D64))=UPPER(TRIM(rPatron)) ), AND( OR( UPPER(TRIM(rTipo))=""CONTIENE"", UPPER(TRIM(rTipo))=""COINCIDENCIA"" ), ISNUMBER(SEARCH(UPPER(TRIM(rPatron)),UPPER(TRIM(D64)))) ) ) ), rConcepto, """" )"&" ) )<>"""" ), 1 ), """" )"),"MANIOBRAS") -> MANIOBRAS
B65: MXN | C65: CRISTOFER PAZ JIMENEZ | D65: FLETE LOCAL ADUANA AIFA A CUAUTITLÁN, EDO. MÉX. 29/07/2026. | E65: 11500 | F65: 0 | G65: IMILE AIFA | H65: {=INDEX(CC!C:C,MATCH(1,(CC!A:A=G65)*(CC!B:B=I65),0))} -> 1402 | I65: PROPIOS | J65: 11500 | K65: =IFERROR(__xludf.DUMMYFUNCTION("IFERROR( INDEX( FILTER( MAP( reglas!$B$2:$B$240, reglas!$C$2:$C$240, reglas!$D$2:$D$240, reglas!$E$2:$E$240, LAMBDA(rEmisor,rPatron,rConcepto,rTipo, IF( AND( OR( UPPER(TRIM(rEmisor))=UPPER(TRIM(C65)), UPPER(TRIM(rEmisor))=""CUALQUIERA"" ), OR( UPPER(TRIM("&"rTipo))=""SOLO EMISOR"", AND( UPPER(TRIM(rTipo))=""EXACTA"", UPPER(TRIM(AG65))=UPPER(TRIM(rPatron)) ), AND( OR( UPPER(TRIM(rTipo))=""CONTIENE"", UPPER(TRIM(rTipo))=""COINCIDENCIA"" ), ISNUMBER(SEARCH(UPPER(TRIM(rPatron)),UPPER(TRIM(D65)))) ) ) ), rConcept"&"o, """" ) ) ), MAP( reglas!$B$2:$B$240, reglas!$C$2:$C$240, reglas!$D$2:$D$240, reglas!$E$2:$E$240, LAMBDA(rEmisor,rPatron,rConcepto,rTipo, IF( AND( OR( UPPER(TRIM(rEmisor))=UPPER(TRIM(C65)), UPPER(TRIM(rEmisor))=""CUALQUIERA"" ), OR( UPPER(TRIM(rTipo))="&"""SOLO EMISOR"", AND( UPPER(TRIM(rTipo))=""EXACTA"", UPPER(TRIM(D65))=UPPER(TRIM(rPatron)) ), AND( OR( UPPER(TRIM(rTipo))=""CONTIENE"", UPPER(TRIM(rTipo))=""COINCIDENCIA"" ), ISNUMBER(SEARCH(UPPER(TRIM(rPatron)),UPPER(TRIM(D65)))) ) ) ), rConcepto, """" )"&" ) )<>"""" ), 1 ), """" )"),"TRANSPORTE") -> TRANSPORTE
A66: 1 | B66: MXN | C66: FEDERAL EXPRESS HOLDINGS (MEXICO) Y COMPAÑIA | D66: Cambio de Instruccion | E66: 634.54 | F66: 0 | G66: TOLUCA | H66: {=INDEX(CC!C:C,MATCH(1,(CC!A:A=G66)*(CC!B:B=I66),0))} -> 1002 | I66: PROPIOS | J66: 634.54 | K66: =IFERROR(__xludf.DUMMYFUNCTION("IFERROR( INDEX( FILTER( MAP( reglas!$B$2:$B$240, reglas!$C$2:$C$240, reglas!$D$2:$D$240, reglas!$E$2:$E$240, LAMBDA(rEmisor,rPatron,rConcepto,rTipo, IF( AND( OR( UPPER(TRIM(rEmisor))=UPPER(TRIM(C66)), UPPER(TRIM(rEmisor))=""CUALQUIERA"" ), OR( UPPER(TRIM("&"rTipo))=""SOLO EMISOR"", AND( UPPER(TRIM(rTipo))=""EXACTA"", UPPER(TRIM(AG66))=UPPER(TRIM(rPatron)) ), AND( OR( UPPER(TRIM(rTipo))=""CONTIENE"", UPPER(TRIM(rTipo))=""COINCIDENCIA"" ), ISNUMBER(SEARCH(UPPER(TRIM(rPatron)),UPPER(TRIM(D66)))) ) ) ), rConcept"&"o, """" ) ) ), MAP( reglas!$B$2:$B$240, reglas!$C$2:$C$240, reglas!$D$2:$D$240, reglas!$E$2:$E$240, LAMBDA(rEmisor,rPatron,rConcepto,rTipo, IF( AND( OR( UPPER(TRIM(rEmisor))=UPPER(TRIM(C66)), UPPER(TRIM(rEmisor))=""CUALQUIERA"" ), OR( UPPER(TRIM(rTipo))="&"""SOLO EMISOR"", AND( UPPER(TRIM(rTipo))=""EXACTA"", UPPER(TRIM(D66))=UPPER(TRIM(rPatron)) ), AND( OR( UPPER(TRIM(rTipo))=""CONTIENE"", UPPER(TRIM(rTipo))=""COINCIDENCIA"" ), ISNUMBER(SEARCH(UPPER(TRIM(rPatron)),UPPER(TRIM(D66)))) ) ) ), rConcepto, """" )"&" ) )<>"""" ), 1 ), """" )"),"MANIOBRAS") -> MANIOBRAS
C67: FEDERAL EXPRESS HOLDINGS (MEXICO) Y COMPAÑIA | D67: Asignacion de Guia Aerea | E67: 580.56 | F67: 0 | G67: TOLUCA | H67: {=INDEX(CC!C:C,MATCH(1,(CC!A:A=G67)*(CC!B:B=I67),0))} -> 1002 | I67: PROPIOS | J67: 580.56 | K67: =IFERROR(__xludf.DUMMYFUNCTION("IFERROR( INDEX( FILTER( MAP( reglas!$B$2:$B$240, reglas!$C$2:$C$240, reglas!$D$2:$D$240, reglas!$E$2:$E$240, LAMBDA(rEmisor,rPatron,rConcepto,rTipo, IF( AND( OR( UPPER(TRIM(rEmisor))=UPPER(TRIM(C67)), UPPER(TRIM(rEmisor))=""CUALQUIERA"" ), OR( UPPER(TRIM("&"rTipo))=""SOLO EMISOR"", AND( UPPER(TRIM(rTipo))=""EXACTA"", UPPER(TRIM(AG67))=UPPER(TRIM(rPatron)) ), AND( OR( UPPER(TRIM(rTipo))=""CONTIENE"", UPPER(TRIM(rTipo))=""COINCIDENCIA"" ), ISNUMBER(SEARCH(UPPER(TRIM(rPatron)),UPPER(TRIM(D67)))) ) ) ), rConcept"&"o, """" ) ) ), MAP( reglas!$B$2:$B$240, reglas!$C$2:$C$240, reglas!$D$2:$D$240, reglas!$E$2:$E$240, LAMBDA(rEmisor,rPatron,rConcepto,rTipo, IF( AND( OR( UPPER(TRIM(rEmisor))=UPPER(TRIM(C67)), UPPER(TRIM(rEmisor))=""CUALQUIERA"" ), OR( UPPER(TRIM(rTipo))="&"""SOLO EMISOR"", AND( UPPER(TRIM(rTipo))=""EXACTA"", UPPER(TRIM(D67))=UPPER(TRIM(rPatron)) ), AND( OR( UPPER(TRIM(rTipo))=""CONTIENE"", UPPER(TRIM(rTipo))=""COINCIDENCIA"" ), ISNUMBER(SEARCH(UPPER(TRIM(rPatron)),UPPER(TRIM(D67)))) ) ) ), rConcepto, """" )"&" ) )<>"""" ), 1 ), """" )"),"MANIOBRAS") -> MANIOBRAS
C68: FEDERAL EXPRESS HOLDINGS (MEXICO) Y COMPAÑIA | D68: Manejo | E68: 634.89 | F68: 0 | G68: TOLUCA | H68: {=INDEX(CC!C:C,MATCH(1,(CC!A:A=G68)*(CC!B:B=I68),0))} -> 1002 | I68: PROPIOS | J68: 634.89 | K68: =IFERROR(__xludf.DUMMYFUNCTION("IFERROR( INDEX( FILTER( MAP( reglas!$B$2:$B$240, reglas!$C$2:$C$240, reglas!$D$2:$D$240, reglas!$E$2:$E$240, LAMBDA(rEmisor,rPatron,rConcepto,rTipo, IF( AND( OR( UPPER(TRIM(rEmisor))=UPPER(TRIM(C68)), UPPER(TRIM(rEmisor))=""CUALQUIERA"" ), OR( UPPER(TRIM("&"rTipo))=""SOLO EMISOR"", AND( UPPER(TRIM(rTipo))=""EXACTA"", UPPER(TRIM(AG68))=UPPER(TRIM(rPatron)) ), AND( OR( UPPER(TRIM(rTipo))=""CONTIENE"", UPPER(TRIM(rTipo))=""COINCIDENCIA"" ), ISNUMBER(SEARCH(UPPER(TRIM(rPatron)),UPPER(TRIM(D68)))) ) ) ), rConcept"&"o, """" ) ) ), MAP( reglas!$B$2:$B$240, reglas!$C$2:$C$240, reglas!$D$2:$D$240, reglas!$E$2:$E$240, LAMBDA(rEmisor,rPatron,rConcepto,rTipo, IF( AND( OR( UPPER(TRIM(rEmisor))=UPPER(TRIM(C68)), UPPER(TRIM(rEmisor))=""CUALQUIERA"" ), OR( UPPER(TRIM(rTipo))="&"""SOLO EMISOR"", AND( UPPER(TRIM(rTipo))=""EXACTA"", UPPER(TRIM(D68))=UPPER(TRIM(rPatron)) ), AND( OR( UPPER(TRIM(rTipo))=""CONTIENE"", UPPER(TRIM(rTipo))=""COINCIDENCIA"" ), ISNUMBER(SEARCH(UPPER(TRIM(rPatron)),UPPER(TRIM(D68)))) ) ) ), rConcepto, """" )"&" ) )<>"""" ), 1 ), """" )"),"MANIOBRAS") -> MANIOBRAS
C69: FEDERAL EXPRESS HOLDINGS (MEXICO) Y COMPAÑIA | D69: Maniobras para Previo | E69: 666.13 | F69: 0 | G69: TOLUCA | H69: {=INDEX(CC!C:C,MATCH(1,(CC!A:A=G69)*(CC!B:B=I69),0))} -> 1002 | I69: PROPIOS | J69: 666.13 | K69: =IFERROR(__xludf.DUMMYFUNCTION("IFERROR( INDEX( FILTER( MAP( reglas!$B$2:$B$240, reglas!$C$2:$C$240, reglas!$D$2:$D$240, reglas!$E$2:$E$240, LAMBDA(rEmisor,rPatron,rConcepto,rTipo, IF( AND( OR( UPPER(TRIM(rEmisor))=UPPER(TRIM(C69)), UPPER(TRIM(rEmisor))=""CUALQUIERA"" ), OR( UPPER(TRIM("&"rTipo))=""SOLO EMISOR"", AND( UPPER(TRIM(rTipo))=""EXACTA"", UPPER(TRIM(AG69))=UPPER(TRIM(rPatron)) ), AND( OR( UPPER(TRIM(rTipo))=""CONTIENE"", UPPER(TRIM(rTipo))=""COINCIDENCIA"" ), ISNUMBER(SEARCH(UPPER(TRIM(rPatron)),UPPER(TRIM(D69)))) ) ) ), rConcept"&"o, """" ) ) ), MAP( reglas!$B$2:$B$240, reglas!$C$2:$C$240, reglas!$D$2:$D$240, reglas!$E$2:$E$240, LAMBDA(rEmisor,rPatron,rConcepto,rTipo, IF( AND( OR( UPPER(TRIM(rEmisor))=UPPER(TRIM(C69)), UPPER(TRIM(rEmisor))=""CUALQUIERA"" ), OR( UPPER(TRIM(rTipo))="&"""SOLO EMISOR"", AND( UPPER(TRIM(rTipo))=""EXACTA"", UPPER(TRIM(D69))=UPPER(TRIM(rPatron)) ), AND( OR( UPPER(TRIM(rTipo))=""CONTIENE"", UPPER(TRIM(rTipo))=""COINCIDENCIA"" ), ISNUMBER(SEARCH(UPPER(TRIM(rPatron)),UPPER(TRIM(D69)))) ) ) ), rConcepto, """" )"&" ) )<>"""" ), 1 ), """" )"),"MANIOBRAS") -> MANIOBRAS
A70: 1 | B70: MXN | C70: AEROENLACES NACIONALES | D70: TARIFA AEREA PNR: QHYKPQ | E70: 4110.99 | F70: 0 | G70: STAFF | H70: {=INDEX(CC!C:C,MATCH(1,(CC!A:A=G70)*(CC!B:B=I70),0))} -> 102 | I70: PROPIOS | J70: 4110.99 | K70: =IFERROR(__xludf.DUMMYFUNCTION("IFERROR( INDEX( FILTER( MAP( reglas!$B$2:$B$240, reglas!$C$2:$C$240, reglas!$D$2:$D$240, reglas!$E$2:$E$240, LAMBDA(rEmisor,rPatron,rConcepto,rTipo, IF( AND( OR( UPPER(TRIM(rEmisor))=UPPER(TRIM(C70)), UPPER(TRIM(rEmisor))=""CUALQUIERA"" ), OR( UPPER(TRIM("&"rTipo))=""SOLO EMISOR"", AND( UPPER(TRIM(rTipo))=""EXACTA"", UPPER(TRIM(AG70))=UPPER(TRIM(rPatron)) ), AND( OR( UPPER(TRIM(rTipo))=""CONTIENE"", UPPER(TRIM(rTipo))=""COINCIDENCIA"" ), ISNUMBER(SEARCH(UPPER(TRIM(rPatron)),UPPER(TRIM(D70)))) ) ) ), rConcept"&"o, """" ) ) ), MAP( reglas!$B$2:$B$240, reglas!$C$2:$C$240, reglas!$D$2:$D$240, reglas!$E$2:$E$240, LAMBDA(rEmisor,rPatron,rConcepto,rTipo, IF( AND( OR( UPPER(TRIM(rEmisor))=UPPER(TRIM(C70)), UPPER(TRIM(rEmisor))=""CUALQUIERA"" ), OR( UPPER(TRIM(rTipo))="&"""SOLO EMISOR"", AND( UPPER(TRIM(rTipo))=""EXACTA"", UPPER(TRIM(D70))=UPPER(TRIM(rPatron)) ), AND( OR( UPPER(TRIM(rTipo))=""CONTIENE"", UPPER(TRIM(rTipo))=""COINCIDENCIA"" ), ISNUMBER(SEARCH(UPPER(TRIM(rPatron)),UPPER(TRIM(D70)))) ) ) ), rConcepto, """" )"&" ) )<>"""" ), 1 ), """" )"),"GASTOS DE VIAJE") -> GASTOS DE VIAJE
C71: AEROENLACES NACIONALES | D71: SERVICIOS ADICIONALES PNR: QHYKPQ | E71: 662.92 | F71: 0 | G71: STAFF | H71: {=INDEX(CC!C:C,MATCH(1,(CC!A:A=G71)*(CC!B:B=I71),0))} -> 102 | I71: PROPIOS | J71: 662.92 | K71: =IFERROR(__xludf.DUMMYFUNCTION("IFERROR( INDEX( FILTER( MAP( reglas!$B$2:$B$240, reglas!$C$2:$C$240, reglas!$D$2:$D$240, reglas!$E$2:$E$240, LAMBDA(rEmisor,rPatron,rConcepto,rTipo, IF( AND( OR( UPPER(TRIM(rEmisor))=UPPER(TRIM(C71)), UPPER(TRIM(rEmisor))=""CUALQUIERA"" ), OR( UPPER(TRIM("&"rTipo))=""SOLO EMISOR"", AND( UPPER(TRIM(rTipo))=""EXACTA"", UPPER(TRIM(AG71))=UPPER(TRIM(rPatron)) ), AND( OR( UPPER(TRIM(rTipo))=""CONTIENE"", UPPER(TRIM(rTipo))=""COINCIDENCIA"" ), ISNUMBER(SEARCH(UPPER(TRIM(rPatron)),UPPER(TRIM(D71)))) ) ) ), rConcept"&"o, """" ) ) ), MAP( reglas!$B$2:$B$240, reglas!$C$2:$C$240, reglas!$D$2:$D$240, reglas!$E$2:$E$240, LAMBDA(rEmisor,rPatron,rConcepto,rTipo, IF( AND( OR( UPPER(TRIM(rEmisor))=UPPER(TRIM(C71)), UPPER(TRIM(rEmisor))=""CUALQUIERA"" ), OR( UPPER(TRIM(rTipo))="&"""SOLO EMISOR"", AND( UPPER(TRIM(rTipo))=""EXACTA"", UPPER(TRIM(D71))=UPPER(TRIM(rPatron)) ), AND( OR( UPPER(TRIM(rTipo))=""CONTIENE"", UPPER(TRIM(rTipo))=""COINCIDENCIA"" ), ISNUMBER(SEARCH(UPPER(TRIM(rPatron)),UPPER(TRIM(D71)))) ) ) ), rConcepto, """" )"&" ) )<>"""" ), 1 ), """" )"),"GASTOS DE VIAJE") -> GASTOS DE VIAJE
C72: AEROENLACES NACIONALES | D72: CARGOS AEROPORTUARIOS | E72: 851.66 | F72: 0 | G72: STAFF | H72: {=INDEX(CC!C:C,MATCH(1,(CC!A:A=G72)*(CC!B:B=I72),0))} -> 102 | I72: PROPIOS | J72: 851.66 | K72: =IFERROR(__xludf.DUMMYFUNCTION("IFERROR( INDEX( FILTER( MAP( reglas!$B$2:$B$240, reglas!$C$2:$C$240, reglas!$D$2:$D$240, reglas!$E$2:$E$240, LAMBDA(rEmisor,rPatron,rConcepto,rTipo, IF( AND( OR( UPPER(TRIM(rEmisor))=UPPER(TRIM(C72)), UPPER(TRIM(rEmisor))=""CUALQUIERA"" ), OR( UPPER(TRIM("&"rTipo))=""SOLO EMISOR"", AND( UPPER(TRIM(rTipo))=""EXACTA"", UPPER(TRIM(AG72))=UPPER(TRIM(rPatron)) ), AND( OR( UPPER(TRIM(rTipo))=""CONTIENE"", UPPER(TRIM(rTipo))=""COINCIDENCIA"" ), ISNUMBER(SEARCH(UPPER(TRIM(rPatron)),UPPER(TRIM(D72)))) ) ) ), rConcept"&"o, """" ) ) ), MAP( reglas!$B$2:$B$240, reglas!$C$2:$C$240, reglas!$D$2:$D$240, reglas!$E$2:$E$240, LAMBDA(rEmisor,rPatron,rConcepto,rTipo, IF( AND( OR( UPPER(TRIM(rEmisor))=UPPER(TRIM(C72)), UPPER(TRIM(rEmisor))=""CUALQUIERA"" ), OR( UPPER(TRIM(rTipo))="&"""SOLO EMISOR"", AND( UPPER(TRIM(rTipo))=""EXACTA"", UPPER(TRIM(D72))=UPPER(TRIM(rPatron)) ), AND( OR( UPPER(TRIM(rTipo))=""CONTIENE"", UPPER(TRIM(rTipo))=""COINCIDENCIA"" ), ISNUMBER(SEARCH(UPPER(TRIM(rPatron)),UPPER(TRIM(D72)))) ) ) ), rConcepto, """" )"&" ) )<>"""" ), 1 ), """" )"),"GASTOS DE VIAJE") -> GASTOS DE VIAJE
B73: MXN | C73: SISTEMA UNIFICADO DE MANIOBRAS AEREAS PARA AGENTES ADUANALES | D73: Carga de camión | E73: 3500 | F73: 0 | G73: IMILE AIFA | H73: {=INDEX(CC!C:C,MATCH(1,(CC!A:A=G73)*(CC!B:B=I73),0))} -> 1402 | I73: PROPIOS | J73: 3500 | K73: =IFERROR(__xludf.DUMMYFUNCTION("IFERROR( INDEX( FILTER( MAP( reglas!$B$2:$B$240, reglas!$C$2:$C$240, reglas!$D$2:$D$240, reglas!$E$2:$E$240, LAMBDA(rEmisor,rPatron,rConcepto,rTipo, IF( AND( OR( UPPER(TRIM(rEmisor))=UPPER(TRIM(C73)), UPPER(TRIM(rEmisor))=""CUALQUIERA"" ), OR( UPPER(TRIM("&"rTipo))=""SOLO EMISOR"", AND( UPPER(TRIM(rTipo))=""EXACTA"", UPPER(TRIM(AG73))=UPPER(TRIM(rPatron)) ), AND( OR( UPPER(TRIM(rTipo))=""CONTIENE"", UPPER(TRIM(rTipo))=""COINCIDENCIA"" ), ISNUMBER(SEARCH(UPPER(TRIM(rPatron)),UPPER(TRIM(D73)))) ) ) ), rConcept"&"o, """" ) ) ), MAP( reglas!$B$2:$B$240, reglas!$C$2:$C$240, reglas!$D$2:$D$240, reglas!$E$2:$E$240, LAMBDA(rEmisor,rPatron,rConcepto,rTipo, IF( AND( OR( UPPER(TRIM(rEmisor))=UPPER(TRIM(C73)), UPPER(TRIM(rEmisor))=""CUALQUIERA"" ), OR( UPPER(TRIM(rTipo))="&"""SOLO EMISOR"", AND( UPPER(TRIM(rTipo))=""EXACTA"", UPPER(TRIM(D73))=UPPER(TRIM(rPatron)) ), AND( OR( UPPER(TRIM(rTipo))=""CONTIENE"", UPPER(TRIM(rTipo))=""COINCIDENCIA"" ), ISNUMBER(SEARCH(UPPER(TRIM(rPatron)),UPPER(TRIM(D73)))) ) ) ), rConcepto, """" )"&" ) )<>"""" ), 1 ), """" )"),"MANIOBRAS") -> MANIOBRAS
B74: MXN | C74: TOTAL BOX | D74: Infraestructura | E74: 187.46 | F74: 0 | G74: STAFF | H74: {=INDEX(CC!C:C,MATCH(1,(CC!A:A=G74)*(CC!B:B=I74),0))} -> 102 | I74: PROPIOS | J74: 187.46 | K74: =IFERROR(__xludf.DUMMYFUNCTION("IFERROR( INDEX( FILTER( MAP( reglas!$B$2:$B$240, reglas!$C$2:$C$240, reglas!$D$2:$D$240, reglas!$E$2:$E$240, LAMBDA(rEmisor,rPatron,rConcepto,rTipo, IF( AND( OR( UPPER(TRIM(rEmisor))=UPPER(TRIM(C74)), UPPER(TRIM(rEmisor))=""CUALQUIERA"" ), OR( UPPER(TRIM("&"rTipo))=""SOLO EMISOR"", AND( UPPER(TRIM(rTipo))=""EXACTA"", UPPER(TRIM(AG74))=UPPER(TRIM(rPatron)) ), AND( OR( UPPER(TRIM(rTipo))=""CONTIENE"", UPPER(TRIM(rTipo))=""COINCIDENCIA"" ), ISNUMBER(SEARCH(UPPER(TRIM(rPatron)),UPPER(TRIM(D74)))) ) ) ), rConcept"&"o, """" ) ) ), MAP( reglas!$B$2:$B$240, reglas!$C$2:$C$240, reglas!$D$2:$D$240, reglas!$E$2:$E$240, LAMBDA(rEmisor,rPatron,rConcepto,rTipo, IF( AND( OR( UPPER(TRIM(rEmisor))=UPPER(TRIM(C74)), UPPER(TRIM(rEmisor))=""CUALQUIERA"" ), OR( UPPER(TRIM(rTipo))="&"""SOLO EMISOR"", AND( UPPER(TRIM(rTipo))=""EXACTA"", UPPER(TRIM(D74))=UPPER(TRIM(rPatron)) ), AND( OR( UPPER(TRIM(rTipo))=""CONTIENE"", UPPER(TRIM(rTipo))=""COINCIDENCIA"" ), ISNUMBER(SEARCH(UPPER(TRIM(rPatron)),UPPER(TRIM(D74)))) ) ) ), rConcepto, """" )"&" ) )<>"""" ), 1 ), """" )"),"INTERNET") -> INTERNET
A75: 1 | B75: MXN | C75: MENSAJERIA METROPOLITANA | D75: GASTOS EN EL EXTRANJERO | E75: 17818.69 | F75: 0 | G75: VERACRUZ | H75: {=INDEX(CC!C:C,MATCH(1,(CC!A:A=G75)*(CC!B:B=I75),0))} -> 1703 | I75: TERCEROS | J75: 17818.69 | K75: =IFERROR(__xludf.DUMMYFUNCTION("IFERROR( INDEX( FILTER( MAP( reglas!$B$2:$B$240, reglas!$C$2:$C$240, reglas!$D$2:$D$240, reglas!$E$2:$E$240, LAMBDA(rEmisor,rPatron,rConcepto,rTipo, IF( AND( OR( UPPER(TRIM(rEmisor))=UPPER(TRIM(C75)), UPPER(TRIM(rEmisor))=""CUALQUIERA"" ), OR( UPPER(TRIM("&"rTipo))=""SOLO EMISOR"", AND( UPPER(TRIM(rTipo))=""EXACTA"", UPPER(TRIM(AG75))=UPPER(TRIM(rPatron)) ), AND( OR( UPPER(TRIM(rTipo))=""CONTIENE"", UPPER(TRIM(rTipo))=""COINCIDENCIA"" ), ISNUMBER(SEARCH(UPPER(TRIM(rPatron)),UPPER(TRIM(D75)))) ) ) ), rConcept"&"o, """" ) ) ), MAP( reglas!$B$2:$B$240, reglas!$C$2:$C$240, reglas!$D$2:$D$240, reglas!$E$2:$E$240, LAMBDA(rEmisor,rPatron,rConcepto,rTipo, IF( AND( OR( UPPER(TRIM(rEmisor))=UPPER(TRIM(C75)), UPPER(TRIM(rEmisor))=""CUALQUIERA"" ), OR( UPPER(TRIM(rTipo))="&"""SOLO EMISOR"", AND( UPPER(TRIM(rTipo))=""EXACTA"", UPPER(TRIM(D75))=UPPER(TRIM(rPatron)) ), AND( OR( UPPER(TRIM(rTipo))=""CONTIENE"", UPPER(TRIM(rTipo))=""COINCIDENCIA"" ), ISNUMBER(SEARCH(UPPER(TRIM(rPatron)),UPPER(TRIM(D75)))) ) ) ), rConcepto, """" )"&" ) )<>"""" ), 1 ), """" )"),"FLETE MARITIMO") -> FLETE MARITIMO
C76: MENSAJERIA METROPOLITANA | D76: COORDINACION FLETE MARITIMO | E76: 92587.29 | F76: 0 | G76: VERACRUZ | H76: {=INDEX(CC!C:C,MATCH(1,(CC!A:A=G76)*(CC!B:B=I76),0))} -> 1703 | I76: TERCEROS | J76: 92587.29 | K76: =IFERROR(__xludf.DUMMYFUNCTION("IFERROR( INDEX( FILTER( MAP( reglas!$B$2:$B$240, reglas!$C$2:$C$240, reglas!$D$2:$D$240, reglas!$E$2:$E$240, LAMBDA(rEmisor,rPatron,rConcepto,rTipo, IF( AND( OR( UPPER(TRIM(rEmisor))=UPPER(TRIM(C76)), UPPER(TRIM(rEmisor))=""CUALQUIERA"" ), OR( UPPER(TRIM("&"rTipo))=""SOLO EMISOR"", AND( UPPER(TRIM(rTipo))=""EXACTA"", UPPER(TRIM(AG76))=UPPER(TRIM(rPatron)) ), AND( OR( UPPER(TRIM(rTipo))=""CONTIENE"", UPPER(TRIM(rTipo))=""COINCIDENCIA"" ), ISNUMBER(SEARCH(UPPER(TRIM(rPatron)),UPPER(TRIM(D76)))) ) ) ), rConcept"&"o, """" ) ) ), MAP( reglas!$B$2:$B$240, reglas!$C$2:$C$240, reglas!$D$2:$D$240, reglas!$E$2:$E$240, LAMBDA(rEmisor,rPatron,rConcepto,rTipo, IF( AND( OR( UPPER(TRIM(rEmisor))=UPPER(TRIM(C76)), UPPER(TRIM(rEmisor))=""CUALQUIERA"" ), OR( UPPER(TRIM(rTipo))="&"""SOLO EMISOR"", AND( UPPER(TRIM(rTipo))=""EXACTA"", UPPER(TRIM(D76))=UPPER(TRIM(rPatron)) ), AND( OR( UPPER(TRIM(rTipo))=""CONTIENE"", UPPER(TRIM(rTipo))=""COINCIDENCIA"" ), ISNUMBER(SEARCH(UPPER(TRIM(rPatron)),UPPER(TRIM(D76)))) ) ) ), rConcepto, """" )"&" ) )<>"""" ), 1 ), """" )"),"FLETE MARITIMO") -> FLETE MARITIMO
C77: MENSAJERIA METROPOLITANA | D77: GASTOS EN MEXICO | E77: 4716.71 | F77: 0 | G77: VERACRUZ | H77: {=INDEX(CC!C:C,MATCH(1,(CC!A:A=G77)*(CC!B:B=I77),0))} -> 1703 | I77: TERCEROS | J77: 4716.71 | K77: =IFERROR(__xludf.DUMMYFUNCTION("IFERROR( INDEX( FILTER( MAP( reglas!$B$2:$B$240, reglas!$C$2:$C$240, reglas!$D$2:$D$240, reglas!$E$2:$E$240, LAMBDA(rEmisor,rPatron,rConcepto,rTipo, IF( AND( OR( UPPER(TRIM(rEmisor))=UPPER(TRIM(C77)), UPPER(TRIM(rEmisor))=""CUALQUIERA"" ), OR( UPPER(TRIM("&"rTipo))=""SOLO EMISOR"", AND( UPPER(TRIM(rTipo))=""EXACTA"", UPPER(TRIM(AG77))=UPPER(TRIM(rPatron)) ), AND( OR( UPPER(TRIM(rTipo))=""CONTIENE"", UPPER(TRIM(rTipo))=""COINCIDENCIA"" ), ISNUMBER(SEARCH(UPPER(TRIM(rPatron)),UPPER(TRIM(D77)))) ) ) ), rConcept"&"o, """" ) ) ), MAP( reglas!$B$2:$B$240, reglas!$C$2:$C$240, reglas!$D$2:$D$240, reglas!$E$2:$E$240, LAMBDA(rEmisor,rPatron,rConcepto,rTipo, IF( AND( OR( UPPER(TRIM(rEmisor))=UPPER(TRIM(C77)), UPPER(TRIM(rEmisor))=""CUALQUIERA"" ), OR( UPPER(TRIM(rTipo))="&"""SOLO EMISOR"", AND( UPPER(TRIM(rTipo))=""EXACTA"", UPPER(TRIM(D77))=UPPER(TRIM(rPatron)) ), AND( OR( UPPER(TRIM(rTipo))=""CONTIENE"", UPPER(TRIM(rTipo))=""COINCIDENCIA"" ), ISNUMBER(SEARCH(UPPER(TRIM(rPatron)),UPPER(TRIM(D77)))) ) ) ), rConcepto, """" )"&" ) )<>"""" ), 1 ), """" )"),"FLETE MARITIMO") -> FLETE MARITIMO
C78: MENSAJERIA METROPOLITANA | D78: GASTOS EN EL EXTRANJERO | E78: 2707.74 | F78: 0 | G78: VERACRUZ | H78: {=INDEX(CC!C:C,MATCH(1,(CC!A:A=G78)*(CC!B:B=I78),0))} -> 1703 | I78: TERCEROS | J78: 2707.74 | K78: =IFERROR(__xludf.DUMMYFUNCTION("IFERROR( INDEX( FILTER( MAP( reglas!$B$2:$B$240, reglas!$C$2:$C$240, reglas!$D$2:$D$240, reglas!$E$2:$E$240, LAMBDA(rEmisor,rPatron,rConcepto,rTipo, IF( AND( OR( UPPER(TRIM(rEmisor))=UPPER(TRIM(C78)), UPPER(TRIM(rEmisor))=""CUALQUIERA"" ), OR( UPPER(TRIM("&"rTipo))=""SOLO EMISOR"", AND( UPPER(TRIM(rTipo))=""EXACTA"", UPPER(TRIM(AG78))=UPPER(TRIM(rPatron)) ), AND( OR( UPPER(TRIM(rTipo))=""CONTIENE"", UPPER(TRIM(rTipo))=""COINCIDENCIA"" ), ISNUMBER(SEARCH(UPPER(TRIM(rPatron)),UPPER(TRIM(D78)))) ) ) ), rConcept"&"o, """" ) ) ), MAP( reglas!$B$2:$B$240, reglas!$C$2:$C$240, reglas!$D$2:$D$240, reglas!$E$2:$E$240, LAMBDA(rEmisor,rPatron,rConcepto,rTipo, IF( AND( OR( UPPER(TRIM(rEmisor))=UPPER(TRIM(C78)), UPPER(TRIM(rEmisor))=""CUALQUIERA"" ), OR( UPPER(TRIM(rTipo))="&"""SOLO EMISOR"", AND( UPPER(TRIM(rTipo))=""EXACTA"", UPPER(TRIM(D78))=UPPER(TRIM(rPatron)) ), AND( OR( UPPER(TRIM(rTipo))=""CONTIENE"", UPPER(TRIM(rTipo))=""COINCIDENCIA"" ), ISNUMBER(SEARCH(UPPER(TRIM(rPatron)),UPPER(TRIM(D78)))) ) ) ), rConcepto, """" )"&" ) )<>"""" ), 1 ), """" )"),"FLETE MARITIMO") -> FLETE MARITIMO
A79: 1 | B79: MXN | C79: CONFEDERACION LATINOAMERICANA DE AGENTES ADUANALES | D79: CUOTA MENSUAL | E79: 13480 | F79: 0 | G79: LAREDO | H79: {=INDEX(CC!C:C,MATCH(1,(CC!A:A=G79)*(CC!B:B=I79),0))} -> 1302 | I79: PROPIOS | J79: 13480 | K79: =IFERROR(__xludf.DUMMYFUNCTION("IFERROR( INDEX( FILTER( MAP( reglas!$B$2:$B$240, reglas!$C$2:$C$240, reglas!$D$2:$D$240, reglas!$E$2:$E$240, LAMBDA(rEmisor,rPatron,rConcepto,rTipo, IF( AND( OR( UPPER(TRIM(rEmisor))=UPPER(TRIM(C79)), UPPER(TRIM(rEmisor))=""CUALQUIERA"" ), OR( UPPER(TRIM("&"rTipo))=""SOLO EMISOR"", AND( UPPER(TRIM(rTipo))=""EXACTA"", UPPER(TRIM(AG79))=UPPER(TRIM(rPatron)) ), AND( OR( UPPER(TRIM(rTipo))=""CONTIENE"", UPPER(TRIM(rTipo))=""COINCIDENCIA"" ), ISNUMBER(SEARCH(UPPER(TRIM(rPatron)),UPPER(TRIM(D79)))) ) ) ), rConcept"&"o, """" ) ) ), MAP( reglas!$B$2:$B$240, reglas!$C$2:$C$240, reglas!$D$2:$D$240, reglas!$E$2:$E$240, LAMBDA(rEmisor,rPatron,rConcepto,rTipo, IF( AND( OR( UPPER(TRIM(rEmisor))=UPPER(TRIM(C79)), UPPER(TRIM(rEmisor))=""CUALQUIERA"" ), OR( UPPER(TRIM(rTipo))="&"""SOLO EMISOR"", AND( UPPER(TRIM(rTipo))=""EXACTA"", UPPER(TRIM(D79))=UPPER(TRIM(rPatron)) ), AND( OR( UPPER(TRIM(rTipo))=""CONTIENE"", UPPER(TRIM(rTipo))=""COINCIDENCIA"" ), ISNUMBER(SEARCH(UPPER(TRIM(rPatron)),UPPER(TRIM(D79)))) ) ) ), rConcepto, """" )"&" ) )<>"""" ), 1 ), """" )"),"CUOTAS Y SUSCRIPCIONES") -> CUOTAS Y SUSCRIPCIONES
C80: CONFEDERACION LATINOAMERICANA DE AGENTES ADUANALES | D80: CUOTA POR ADUANA, COBRO ADICIONAL POR ADUANA CON SEDES DE CLAA (N.LAREDO,VERACRUZ) | E80: 2282 | F80: 0 | G80: LAREDO | H80: {=INDEX(CC!C:C,MATCH(1,(CC!A:A=G80)*(CC!B:B=I80),0))} -> 1302 | I80: PROPIOS | J80: 1141 | K80: =IFERROR(__xludf.DUMMYFUNCTION("IFERROR( INDEX( FILTER( MAP( reglas!$B$2:$B$240, reglas!$C$2:$C$240, reglas!$D$2:$D$240, reglas!$E$2:$E$240, LAMBDA(rEmisor,rPatron,rConcepto,rTipo, IF( AND( OR( UPPER(TRIM(rEmisor))=UPPER(TRIM(C80)), UPPER(TRIM(rEmisor))=""CUALQUIERA"" ), OR( UPPER(TRIM("&"rTipo))=""SOLO EMISOR"", AND( UPPER(TRIM(rTipo))=""EXACTA"", UPPER(TRIM(AG80))=UPPER(TRIM(rPatron)) ), AND( OR( UPPER(TRIM(rTipo))=""CONTIENE"", UPPER(TRIM(rTipo))=""COINCIDENCIA"" ), ISNUMBER(SEARCH(UPPER(TRIM(rPatron)),UPPER(TRIM(D80)))) ) ) ), rConcept"&"o, """" ) ) ), MAP( reglas!$B$2:$B$240, reglas!$C$2:$C$240, reglas!$D$2:$D$240, reglas!$E$2:$E$240, LAMBDA(rEmisor,rPatron,rConcepto,rTipo, IF( AND( OR( UPPER(TRIM(rEmisor))=UPPER(TRIM(C80)), UPPER(TRIM(rEmisor))=""CUALQUIERA"" ), OR( UPPER(TRIM(rTipo))="&"""SOLO EMISOR"", AND( UPPER(TRIM(rTipo))=""EXACTA"", UPPER(TRIM(D80))=UPPER(TRIM(rPatron)) ), AND( OR( UPPER(TRIM(rTipo))=""CONTIENE"", UPPER(TRIM(rTipo))=""COINCIDENCIA"" ), ISNUMBER(SEARCH(UPPER(TRIM(rPatron)),UPPER(TRIM(D80)))) ) ) ), rConcepto, """" )"&" ) )<>"""" ), 1 ), """" )"),"CUOTAS Y SUSCRIPCIONES") -> CUOTAS Y SUSCRIPCIONES
C81: CONFEDERACION LATINOAMERICANA DE AGENTES ADUANALES | D81: CUOTA POR ADUANA, COBRO ADICIONAL POR ADUANA CON SEDES DE CLAA (N.LAREDO,VERACRUZ) | G81: VERACRUZ | H81: {=INDEX(CC!C:C,MATCH(1,(CC!A:A=G81)*(CC!B:B=I81),0))} -> 1702 | I81: PROPIOS | J81: 1141 | K81: =IFERROR(__xludf.DUMMYFUNCTION("IFERROR( INDEX( FILTER( MAP( reglas!$B$2:$B$240, reglas!$C$2:$C$240, reglas!$D$2:$D$240, reglas!$E$2:$E$240, LAMBDA(rEmisor,rPatron,rConcepto,rTipo, IF( AND( OR( UPPER(TRIM(rEmisor))=UPPER(TRIM(C81)), UPPER(TRIM(rEmisor))=""CUALQUIERA"" ), OR( UPPER(TRIM("&"rTipo))=""SOLO EMISOR"", AND( UPPER(TRIM(rTipo))=""EXACTA"", UPPER(TRIM(AG81))=UPPER(TRIM(rPatron)) ), AND( OR( UPPER(TRIM(rTipo))=""CONTIENE"", UPPER(TRIM(rTipo))=""COINCIDENCIA"" ), ISNUMBER(SEARCH(UPPER(TRIM(rPatron)),UPPER(TRIM(D81)))) ) ) ), rConcept"&"o, """" ) ) ), MAP( reglas!$B$2:$B$240, reglas!$C$2:$C$240, reglas!$D$2:$D$240, reglas!$E$2:$E$240, LAMBDA(rEmisor,rPatron,rConcepto,rTipo, IF( AND( OR( UPPER(TRIM(rEmisor))=UPPER(TRIM(C81)), UPPER(TRIM(rEmisor))=""CUALQUIERA"" ), OR( UPPER(TRIM(rTipo))="&"""SOLO EMISOR"", AND( UPPER(TRIM(rTipo))=""EXACTA"", UPPER(TRIM(D81))=UPPER(TRIM(rPatron)) ), AND( OR( UPPER(TRIM(rTipo))=""CONTIENE"", UPPER(TRIM(rTipo))=""COINCIDENCIA"" ), ISNUMBER(SEARCH(UPPER(TRIM(rPatron)),UPPER(TRIM(D81)))) ) ) ), rConcepto, """" )"&" ) )<>"""" ), 1 ), """" )"),"CUOTAS Y SUSCRIPCIONES") -> CUOTAS Y SUSCRIPCIONES
B82: MXN | C82: AEROPUERTO INTERNACIONAL FELIPE ANGELES | D82: Recuperacion de Gastos Uso Energia Electrica | E82: 289.55 | F82: 0 | G82: AIFA | H82: {=INDEX(CC!C:C,MATCH(1,(CC!A:A=G82)*(CC!B:B=I82),0))} -> 902 | I82: PROPIOS | J82: 289.55 | K82: =IFERROR(__xludf.DUMMYFUNCTION("IFERROR( INDEX( FILTER( MAP( reglas!$B$2:$B$240, reglas!$C$2:$C$240, reglas!$D$2:$D$240, reglas!$E$2:$E$240, LAMBDA(rEmisor,rPatron,rConcepto,rTipo, IF( AND( OR( UPPER(TRIM(rEmisor))=UPPER(TRIM(C82)), UPPER(TRIM(rEmisor))=""CUALQUIERA"" ), OR( UPPER(TRIM("&"rTipo))=""SOLO EMISOR"", AND( UPPER(TRIM(rTipo))=""EXACTA"", UPPER(TRIM(AG82))=UPPER(TRIM(rPatron)) ), AND( OR( UPPER(TRIM(rTipo))=""CONTIENE"", UPPER(TRIM(rTipo))=""COINCIDENCIA"" ), ISNUMBER(SEARCH(UPPER(TRIM(rPatron)),UPPER(TRIM(D82)))) ) ) ), rConcept"&"o, """" ) ) ), MAP( reglas!$B$2:$B$240, reglas!$C$2:$C$240, reglas!$D$2:$D$240, reglas!$E$2:$E$240, LAMBDA(rEmisor,rPatron,rConcepto,rTipo, IF( AND( OR( UPPER(TRIM(rEmisor))=UPPER(TRIM(C82)), UPPER(TRIM(rEmisor))=""CUALQUIERA"" ), OR( UPPER(TRIM(rTipo))="&"""SOLO EMISOR"", AND( UPPER(TRIM(rTipo))=""EXACTA"", UPPER(TRIM(D82))=UPPER(TRIM(rPatron)) ), AND( OR( UPPER(TRIM(rTipo))=""CONTIENE"", UPPER(TRIM(rTipo))=""COINCIDENCIA"" ), ISNUMBER(SEARCH(UPPER(TRIM(rPatron)),UPPER(TRIM(D82)))) ) ) ), rConcepto, """" )"&" ) )<>"""" ), 1 ), """" )"),"ARRENDAMIENTO") -> ARRENDAMIENTO
B83: MXN | C83: CRISTOFER PAZ JIMENEZ | D83: FLETE LOCAL ADUANA AIFA A CUAUTITLÁN, EDO. MÉX. 04/08/2026. | E83: 11500 | F83: 0 | G83: IMILE AIFA | H83: {=INDEX(CC!C:C,MATCH(1,(CC!A:A=G83)*(CC!B:B=I83),0))} -> 1402 | I83: PROPIOS | J83: 11500 | K83: =IFERROR(__xludf.DUMMYFUNCTION("IFERROR( INDEX( FILTER( MAP( reglas!$B$2:$B$240, reglas!$C$2:$C$240, reglas!$D$2:$D$240, reglas!$E$2:$E$240, LAMBDA(rEmisor,rPatron,rConcepto,rTipo, IF( AND( OR( UPPER(TRIM(rEmisor))=UPPER(TRIM(C83)), UPPER(TRIM(rEmisor))=""CUALQUIERA"" ), OR( UPPER(TRIM("&"rTipo))=""SOLO EMISOR"", AND( UPPER(TRIM(rTipo))=""EXACTA"", UPPER(TRIM(AG83))=UPPER(TRIM(rPatron)) ), AND( OR( UPPER(TRIM(rTipo))=""CONTIENE"", UPPER(TRIM(rTipo))=""COINCIDENCIA"" ), ISNUMBER(SEARCH(UPPER(TRIM(rPatron)),UPPER(TRIM(D83)))) ) ) ), rConcept"&"o, """" ) ) ), MAP( reglas!$B$2:$B$240, reglas!$C$2:$C$240, reglas!$D$2:$D$240, reglas!$E$2:$E$240, LAMBDA(rEmisor,rPatron,rConcepto,rTipo, IF( AND( OR( UPPER(TRIM(rEmisor))=UPPER(TRIM(C83)), UPPER(TRIM(rEmisor))=""CUALQUIERA"" ), OR( UPPER(TRIM(rTipo))="&"""SOLO EMISOR"", AND( UPPER(TRIM(rTipo))=""EXACTA"", UPPER(TRIM(D83))=UPPER(TRIM(rPatron)) ), AND( OR( UPPER(TRIM(rTipo))=""CONTIENE"", UPPER(TRIM(rTipo))=""COINCIDENCIA"" ), ISNUMBER(SEARCH(UPPER(TRIM(rPatron)),UPPER(TRIM(D83)))) ) ) ), rConcepto, """" )"&" ) )<>"""" ), 1 ), """" )"),"TRANSPORTE") -> TRANSPORTE
A84: 1 | B84: MXN | C84: L C TERMINAL PORTUARIA DE CONTENEDORES | D84: MUELLAJE | E84: 522 | F84: 0 | G84: MANZANILLO | H84: {=INDEX(CC!C:C,MATCH(1,(CC!A:A=G84)*(CC!B:B=I84),0))} -> 1203 | I84: TERCEROS | J84: 522 | K84: =IFERROR(__xludf.DUMMYFUNCTION("IFERROR( INDEX( FILTER( MAP( reglas!$B$2:$B$240, reglas!$C$2:$C$240, reglas!$D$2:$D$240, reglas!$E$2:$E$240, LAMBDA(rEmisor,rPatron,rConcepto,rTipo, IF( AND( OR( UPPER(TRIM(rEmisor))=UPPER(TRIM(C84)), UPPER(TRIM(rEmisor))=""CUALQUIERA"" ), OR( UPPER(TRIM("&"rTipo))=""SOLO EMISOR"", AND( UPPER(TRIM(rTipo))=""EXACTA"", UPPER(TRIM(AG84))=UPPER(TRIM(rPatron)) ), AND( OR( UPPER(TRIM(rTipo))=""CONTIENE"", UPPER(TRIM(rTipo))=""COINCIDENCIA"" ), ISNUMBER(SEARCH(UPPER(TRIM(rPatron)),UPPER(TRIM(D84)))) ) ) ), rConcept"&"o, """" ) ) ), MAP( reglas!$B$2:$B$240, reglas!$C$2:$C$240, reglas!$D$2:$D$240, reglas!$E$2:$E$240, LAMBDA(rEmisor,rPatron,rConcepto,rTipo, IF( AND( OR( UPPER(TRIM(rEmisor))=UPPER(TRIM(C84)), UPPER(TRIM(rEmisor))=""CUALQUIERA"" ), OR( UPPER(TRIM(rTipo))="&"""SOLO EMISOR"", AND( UPPER(TRIM(rTipo))=""EXACTA"", UPPER(TRIM(D84))=UPPER(TRIM(rPatron)) ), AND( OR( UPPER(TRIM(rTipo))=""CONTIENE"", UPPER(TRIM(rTipo))=""COINCIDENCIA"" ), ISNUMBER(SEARCH(UPPER(TRIM(rPatron)),UPPER(TRIM(D84)))) ) ) ), rConcepto, """" )"&" ) )<>"""" ), 1 ), """" )"),"MANIOBRAS") -> MANIOBRAS
C85: L C TERMINAL PORTUARIA DE CONTENEDORES | D85: COBRO POR IMPLEMENTACION DE CODIGO ISPS | E85: 327.58 | F85: 0 | G85: MANZANILLO | H85: {=INDEX(CC!C:C,MATCH(1,(CC!A:A=G85)*(CC!B:B=I85),0))} -> 1203 | I85: TERCEROS | J85: 327.58 | K85: =IFERROR(__xludf.DUMMYFUNCTION("IFERROR( INDEX( FILTER( MAP( reglas!$B$2:$B$240, reglas!$C$2:$C$240, reglas!$D$2:$D$240, reglas!$E$2:$E$240, LAMBDA(rEmisor,rPatron,rConcepto,rTipo, IF( AND( OR( UPPER(TRIM(rEmisor))=UPPER(TRIM(C85)), UPPER(TRIM(rEmisor))=""CUALQUIERA"" ), OR( UPPER(TRIM("&"rTipo))=""SOLO EMISOR"", AND( UPPER(TRIM(rTipo))=""EXACTA"", UPPER(TRIM(AG85))=UPPER(TRIM(rPatron)) ), AND( OR( UPPER(TRIM(rTipo))=""CONTIENE"", UPPER(TRIM(rTipo))=""COINCIDENCIA"" ), ISNUMBER(SEARCH(UPPER(TRIM(rPatron)),UPPER(TRIM(D85)))) ) ) ), rConcept"&"o, """" ) ) ), MAP( reglas!$B$2:$B$240, reglas!$C$2:$C$240, reglas!$D$2:$D$240, reglas!$E$2:$E$240, LAMBDA(rEmisor,rPatron,rConcepto,rTipo, IF( AND( OR( UPPER(TRIM(rEmisor))=UPPER(TRIM(C85)), UPPER(TRIM(rEmisor))=""CUALQUIERA"" ), OR( UPPER(TRIM(rTipo))="&"""SOLO EMISOR"", AND( UPPER(TRIM(rTipo))=""EXACTA"", UPPER(TRIM(D85))=UPPER(TRIM(rPatron)) ), AND( OR( UPPER(TRIM(rTipo))=""CONTIENE"", UPPER(TRIM(rTipo))=""COINCIDENCIA"" ), ISNUMBER(SEARCH(UPPER(TRIM(rPatron)),UPPER(TRIM(D85)))) ) ) ), rConcepto, """" )"&" ) )<>"""" ), 1 ), """" )"),"MANIOBRAS") -> MANIOBRAS
C86: L C TERMINAL PORTUARIA DE CONTENEDORES | D86: SERV A | E86: 16434 | F86: 0 | G86: MANZANILLO | H86: {=INDEX(CC!C:C,MATCH(1,(CC!A:A=G86)*(CC!B:B=I86),0))} -> 1203 | I86: TERCEROS | J86: 16434 | K86: =IFERROR(__xludf.DUMMYFUNCTION("IFERROR( INDEX( FILTER( MAP( reglas!$B$2:$B$240, reglas!$C$2:$C$240, reglas!$D$2:$D$240, reglas!$E$2:$E$240, LAMBDA(rEmisor,rPatron,rConcepto,rTipo, IF( AND( OR( UPPER(TRIM(rEmisor))=UPPER(TRIM(C86)), UPPER(TRIM(rEmisor))=""CUALQUIERA"" ), OR( UPPER(TRIM("&"rTipo))=""SOLO EMISOR"", AND( UPPER(TRIM(rTipo))=""EXACTA"", UPPER(TRIM(AG86))=UPPER(TRIM(rPatron)) ), AND( OR( UPPER(TRIM(rTipo))=""CONTIENE"", UPPER(TRIM(rTipo))=""COINCIDENCIA"" ), ISNUMBER(SEARCH(UPPER(TRIM(rPatron)),UPPER(TRIM(D86)))) ) ) ), rConcept"&"o, """" ) ) ), MAP( reglas!$B$2:$B$240, reglas!$C$2:$C$240, reglas!$D$2:$D$240, reglas!$E$2:$E$240, LAMBDA(rEmisor,rPatron,rConcepto,rTipo, IF( AND( OR( UPPER(TRIM(rEmisor))=UPPER(TRIM(C86)), UPPER(TRIM(rEmisor))=""CUALQUIERA"" ), OR( UPPER(TRIM(rTipo))="&"""SOLO EMISOR"", AND( UPPER(TRIM(rTipo))=""EXACTA"", UPPER(TRIM(D86))=UPPER(TRIM(rPatron)) ), AND( OR( UPPER(TRIM(rTipo))=""CONTIENE"", UPPER(TRIM(rTipo))=""COINCIDENCIA"" ), ISNUMBER(SEARCH(UPPER(TRIM(rPatron)),UPPER(TRIM(D86)))) ) ) ), rConcepto, """" )"&" ) )<>"""" ), 1 ), """" )"),"MANIOBRAS") -> MANIOBRAS
C87: L C TERMINAL PORTUARIA DE CONTENEDORES | D87: CONTROL ELECTRONICO DE LA INFORMACIÓN | E87: 1844 | F87: 0 | G87: MANZANILLO | H87: {=INDEX(CC!C:C,MATCH(1,(CC!A:A=G87)*(CC!B:B=I87),0))} -> 1203 | I87: TERCEROS | J87: 1844 | K87: =IFERROR(__xludf.DUMMYFUNCTION("IFERROR( INDEX( FILTER( MAP( reglas!$B$2:$B$240, reglas!$C$2:$C$240, reglas!$D$2:$D$240, reglas!$E$2:$E$240, LAMBDA(rEmisor,rPatron,rConcepto,rTipo, IF( AND( OR( UPPER(TRIM(rEmisor))=UPPER(TRIM(C87)), UPPER(TRIM(rEmisor))=""CUALQUIERA"" ), OR( UPPER(TRIM("&"rTipo))=""SOLO EMISOR"", AND( UPPER(TRIM(rTipo))=""EXACTA"", UPPER(TRIM(AG87))=UPPER(TRIM(rPatron)) ), AND( OR( UPPER(TRIM(rTipo))=""CONTIENE"", UPPER(TRIM(rTipo))=""COINCIDENCIA"" ), ISNUMBER(SEARCH(UPPER(TRIM(rPatron)),UPPER(TRIM(D87)))) ) ) ), rConcept"&"o, """" ) ) ), MAP( reglas!$B$2:$B$240, reglas!$C$2:$C$240, reglas!$D$2:$D$240, reglas!$E$2:$E$240, LAMBDA(rEmisor,rPatron,rConcepto,rTipo, IF( AND( OR( UPPER(TRIM(rEmisor))=UPPER(TRIM(C87)), UPPER(TRIM(rEmisor))=""CUALQUIERA"" ), OR( UPPER(TRIM(rTipo))="&"""SOLO EMISOR"", AND( UPPER(TRIM(rTipo))=""EXACTA"", UPPER(TRIM(D87))=UPPER(TRIM(rPatron)) ), AND( OR( UPPER(TRIM(rTipo))=""CONTIENE"", UPPER(TRIM(rTipo))=""COINCIDENCIA"" ), ISNUMBER(SEARCH(UPPER(TRIM(rPatron)),UPPER(TRIM(D87)))) ) ) ), rConcepto, """" )"&" ) )<>"""" ), 1 ), """" )"),"MANIOBRAS") -> MANIOBRAS
B88: MXN | C88: LOGIETY TECHNOLOGY | D88: RENTA DE SOFTWARE PARA CLASIFICACION ARANCELARIA | E88: 5000 | F88: 0 | G88: TOLUCA | H88: {=INDEX(CC!C:C,MATCH(1,(CC!A:A=G88)*(CC!B:B=I88),0))} -> 1002 | I88: PROPIOS | J88: 5000 | K88: =IFERROR(__xludf.DUMMYFUNCTION("IFERROR( INDEX( FILTER( MAP( reglas!$B$2:$B$240, reglas!$C$2:$C$240, reglas!$D$2:$D$240, reglas!$E$2:$E$240, LAMBDA(rEmisor,rPatron,rConcepto,rTipo, IF( AND( OR( UPPER(TRIM(rEmisor))=UPPER(TRIM(C88)), UPPER(TRIM(rEmisor))=""CUALQUIERA"" ), OR( UPPER(TRIM("&"rTipo))=""SOLO EMISOR"", AND( UPPER(TRIM(rTipo))=""EXACTA"", UPPER(TRIM(AG88))=UPPER(TRIM(rPatron)) ), AND( OR( UPPER(TRIM(rTipo))=""CONTIENE"", UPPER(TRIM(rTipo))=""COINCIDENCIA"" ), ISNUMBER(SEARCH(UPPER(TRIM(rPatron)),UPPER(TRIM(D88)))) ) ) ), rConcept"&"o, """" ) ) ), MAP( reglas!$B$2:$B$240, reglas!$C$2:$C$240, reglas!$D$2:$D$240, reglas!$E$2:$E$240, LAMBDA(rEmisor,rPatron,rConcepto,rTipo, IF( AND( OR( UPPER(TRIM(rEmisor))=UPPER(TRIM(C88)), UPPER(TRIM(rEmisor))=""CUALQUIERA"" ), OR( UPPER(TRIM(rTipo))="&"""SOLO EMISOR"", AND( UPPER(TRIM(rTipo))=""EXACTA"", UPPER(TRIM(D88))=UPPER(TRIM(rPatron)) ), AND( OR( UPPER(TRIM(rTipo))=""CONTIENE"", UPPER(TRIM(rTipo))=""COINCIDENCIA"" ), ISNUMBER(SEARCH(UPPER(TRIM(rPatron)),UPPER(TRIM(D88)))) ) ) ), rConcepto, """" )"&" ) )<>"""" ), 1 ), """" )"),"LICENCIAS DE COMPUTO") -> LICENCIAS DE COMPUTO
B89: MXN | C89: CRISTOFER PAZ JIMENEZ | D89: FLETE LOCAL ADUANA IFA A CUAUTITLÁN, EDO. MÉX. 02/08/2026. | E89: 11500 | F89: 0 | G89: IMILE AIFA | H89: {=INDEX(CC!C:C,MATCH(1,(CC!A:A=G89)*(CC!B:B=I89),0))} -> 1402 | I89: PROPIOS | J89: 11500 | K89: =IFERROR(__xludf.DUMMYFUNCTION("IFERROR( INDEX( FILTER( MAP( reglas!$B$2:$B$240, reglas!$C$2:$C$240, reglas!$D$2:$D$240, reglas!$E$2:$E$240, LAMBDA(rEmisor,rPatron,rConcepto,rTipo, IF( AND( OR( UPPER(TRIM(rEmisor))=UPPER(TRIM(C89)), UPPER(TRIM(rEmisor))=""CUALQUIERA"" ), OR( UPPER(TRIM("&"rTipo))=""SOLO EMISOR"", AND( UPPER(TRIM(rTipo))=""EXACTA"", UPPER(TRIM(AG89))=UPPER(TRIM(rPatron)) ), AND( OR( UPPER(TRIM(rTipo))=""CONTIENE"", UPPER(TRIM(rTipo))=""COINCIDENCIA"" ), ISNUMBER(SEARCH(UPPER(TRIM(rPatron)),UPPER(TRIM(D89)))) ) ) ), rConcept"&"o, """" ) ) ), MAP( reglas!$B$2:$B$240, reglas!$C$2:$C$240, reglas!$D$2:$D$240, reglas!$E$2:$E$240, LAMBDA(rEmisor,rPatron,rConcepto,rTipo, IF( AND( OR( UPPER(TRIM(rEmisor))=UPPER(TRIM(C89)), UPPER(TRIM(rEmisor))=""CUALQUIERA"" ), OR( UPPER(TRIM(rTipo))="&"""SOLO EMISOR"", AND( UPPER(TRIM(rTipo))=""EXACTA"", UPPER(TRIM(D89))=UPPER(TRIM(rPatron)) ), AND( OR( UPPER(TRIM(rTipo))=""CONTIENE"", UPPER(TRIM(rTipo))=""COINCIDENCIA"" ), ISNUMBER(SEARCH(UPPER(TRIM(rPatron)),UPPER(TRIM(D89)))) ) ) ), rConcepto, """" )"&" ) )<>"""" ), 1 ), """" )"),"TRANSPORTE") -> TRANSPORTE
A90: 1 | B90: MXN | C90: CONFEDERACION LATINOAMERICANA DE AGENTES ADUANALES | D90: GASTOS ADMINISTRATIVOS | E90: 82.76 | F90: 0 | G90: IMILE AIFA | H90: {=INDEX(CC!C:C,MATCH(1,(CC!A:A=G90)*(CC!B:B=I90),0))} -> 1402 | I90: PROPIOS | J90: 82.76 | K90: =IFERROR(__xludf.DUMMYFUNCTION("IFERROR( INDEX( FILTER( MAP( reglas!$B$2:$B$240, reglas!$C$2:$C$240, reglas!$D$2:$D$240, reglas!$E$2:$E$240, LAMBDA(rEmisor,rPatron,rConcepto,rTipo, IF( AND( OR( UPPER(TRIM(rEmisor))=UPPER(TRIM(C90)), UPPER(TRIM(rEmisor))=""CUALQUIERA"" ), OR( UPPER(TRIM("&"rTipo))=""SOLO EMISOR"", AND( UPPER(TRIM(rTipo))=""EXACTA"", UPPER(TRIM(AG90))=UPPER(TRIM(rPatron)) ), AND( OR( UPPER(TRIM(rTipo))=""CONTIENE"", UPPER(TRIM(rTipo))=""COINCIDENCIA"" ), ISNUMBER(SEARCH(UPPER(TRIM(rPatron)),UPPER(TRIM(D90)))) ) ) ), rConcept"&"o, """" ) ) ), MAP( reglas!$B$2:$B$240, reglas!$C$2:$C$240, reglas!$D$2:$D$240, reglas!$E$2:$E$240, LAMBDA(rEmisor,rPatron,rConcepto,rTipo, IF( AND( OR( UPPER(TRIM(rEmisor))=UPPER(TRIM(C90)), UPPER(TRIM(rEmisor))=""CUALQUIERA"" ), OR( UPPER(TRIM(rTipo))="&"""SOLO EMISOR"", AND( UPPER(TRIM(rTipo))=""EXACTA"", UPPER(TRIM(D90))=UPPER(TRIM(rPatron)) ), AND( OR( UPPER(TRIM(rTipo))=""CONTIENE"", UPPER(TRIM(rTipo))=""COINCIDENCIA"" ), ISNUMBER(SEARCH(UPPER(TRIM(rPatron)),UPPER(TRIM(D90)))) ) ) ), rConcepto, """" )"&" ) )<>"""" ), 1 ), """" )"),"PAPELERIA") -> PAPELERIA
B91: MXN | C91: AEROPUERTO INTERNACIONAL FELIPE ANGELES | D91: Renta Comercial | E91: 27708.66 | F91: 0 | G91: AIFA | H91: {=INDEX(CC!C:C,MATCH(1,(CC!A:A=G91)*(CC!B:B=I91),0))} -> 902 | I91: PROPIOS | J91: 2770.87 | K91: =IFERROR(__xludf.DUMMYFUNCTION("IFERROR( INDEX( FILTER( MAP( reglas!$B$2:$B$240, reglas!$C$2:$C$240, reglas!$D$2:$D$240, reglas!$E$2:$E$240, LAMBDA(rEmisor,rPatron,rConcepto,rTipo, IF( AND( OR( UPPER(TRIM(rEmisor))=UPPER(TRIM(C91)), UPPER(TRIM(rEmisor))=""CUALQUIERA"" ), OR( UPPER(TRIM("&"rTipo))=""SOLO EMISOR"", AND( UPPER(TRIM(rTipo))=""EXACTA"", UPPER(TRIM(AG91))=UPPER(TRIM(rPatron)) ), AND( OR( UPPER(TRIM(rTipo))=""CONTIENE"", UPPER(TRIM(rTipo))=""COINCIDENCIA"" ), ISNUMBER(SEARCH(UPPER(TRIM(rPatron)),UPPER(TRIM(D91)))) ) ) ), rConcept"&"o, """" ) ) ), MAP( reglas!$B$2:$B$240, reglas!$C$2:$C$240, reglas!$D$2:$D$240, reglas!$E$2:$E$240, LAMBDA(rEmisor,rPatron,rConcepto,rTipo, IF( AND( OR( UPPER(TRIM(rEmisor))=UPPER(TRIM(C91)), UPPER(TRIM(rEmisor))=""CUALQUIERA"" ), OR( UPPER(TRIM(rTipo))="&"""SOLO EMISOR"", AND( UPPER(TRIM(rTipo))=""EXACTA"", UPPER(TRIM(D91))=UPPER(TRIM(rPatron)) ), AND( OR( UPPER(TRIM(rTipo))=""CONTIENE"", UPPER(TRIM(rTipo))=""COINCIDENCIA"" ), ISNUMBER(SEARCH(UPPER(TRIM(rPatron)),UPPER(TRIM(D91)))) ) ) ), rConcepto, """" )"&" ) )<>"""" ), 1 ), """" )"),"ARRENDAMIENTO") -> ARRENDAMIENTO
C92: AEROPUERTO INTERNACIONAL FELIPE ANGELES | D92: Renta Comercial | G92: IMILE AIFA | H92: {=INDEX(CC!C:C,MATCH(1,(CC!A:A=G92)*(CC!B:B=I92),0))} -> 1402 | I92: PROPIOS | J92: 12468.9 | K92: =IFERROR(__xludf.DUMMYFUNCTION("IFERROR( INDEX( FILTER( MAP( reglas!$B$2:$B$240, reglas!$C$2:$C$240, reglas!$D$2:$D$240, reglas!$E$2:$E$240, LAMBDA(rEmisor,rPatron,rConcepto,rTipo, IF( AND( OR( UPPER(TRIM(rEmisor))=UPPER(TRIM(C92)), UPPER(TRIM(rEmisor))=""CUALQUIERA"" ), OR( UPPER(TRIM("&"rTipo))=""SOLO EMISOR"", AND( UPPER(TRIM(rTipo))=""EXACTA"", UPPER(TRIM(AG92))=UPPER(TRIM(rPatron)) ), AND( OR( UPPER(TRIM(rTipo))=""CONTIENE"", UPPER(TRIM(rTipo))=""COINCIDENCIA"" ), ISNUMBER(SEARCH(UPPER(TRIM(rPatron)),UPPER(TRIM(D92)))) ) ) ), rConcept"&"o, """" ) ) ), MAP( reglas!$B$2:$B$240, reglas!$C$2:$C$240, reglas!$D$2:$D$240, reglas!$E$2:$E$240, LAMBDA(rEmisor,rPatron,rConcepto,rTipo, IF( AND( OR( UPPER(TRIM(rEmisor))=UPPER(TRIM(C92)), UPPER(TRIM(rEmisor))=""CUALQUIERA"" ), OR( UPPER(TRIM(rTipo))="&"""SOLO EMISOR"", AND( UPPER(TRIM(rTipo))=""EXACTA"", UPPER(TRIM(D92))=UPPER(TRIM(rPatron)) ), AND( OR( UPPER(TRIM(rTipo))=""CONTIENE"", UPPER(TRIM(rTipo))=""COINCIDENCIA"" ), ISNUMBER(SEARCH(UPPER(TRIM(rPatron)),UPPER(TRIM(D92)))) ) ) ), rConcepto, """" )"&" ) )<>"""" ), 1 ), """" )"),"ARRENDAMIENTO") -> ARRENDAMIENTO
C93: AEROPUERTO INTERNACIONAL FELIPE ANGELES | D93: Renta Comercial | G93: TMM | H93: {=INDEX(CC!C:C,MATCH(1,(CC!A:A=G93)*(CC!B:B=I93),0))} -> 2002 | I93: PROPIOS | J93: 12468.9 | K93: =IFERROR(__xludf.DUMMYFUNCTION("IFERROR( INDEX( FILTER( MAP( reglas!$B$2:$B$240, reglas!$C$2:$C$240, reglas!$D$2:$D$240, reglas!$E$2:$E$240, LAMBDA(rEmisor,rPatron,rConcepto,rTipo, IF( AND( OR( UPPER(TRIM(rEmisor))=UPPER(TRIM(C93)), UPPER(TRIM(rEmisor))=""CUALQUIERA"" ), OR( UPPER(TRIM("&"rTipo))=""SOLO EMISOR"", AND( UPPER(TRIM(rTipo))=""EXACTA"", UPPER(TRIM(AG93))=UPPER(TRIM(rPatron)) ), AND( OR( UPPER(TRIM(rTipo))=""CONTIENE"", UPPER(TRIM(rTipo))=""COINCIDENCIA"" ), ISNUMBER(SEARCH(UPPER(TRIM(rPatron)),UPPER(TRIM(D93)))) ) ) ), rConcept"&"o, """" ) ) ), MAP( reglas!$B$2:$B$240, reglas!$C$2:$C$240, reglas!$D$2:$D$240, reglas!$E$2:$E$240, LAMBDA(rEmisor,rPatron,rConcepto,rTipo, IF( AND( OR( UPPER(TRIM(rEmisor))=UPPER(TRIM(C93)), UPPER(TRIM(rEmisor))=""CUALQUIERA"" ), OR( UPPER(TRIM(rTipo))="&"""SOLO EMISOR"", AND( UPPER(TRIM(rTipo))=""EXACTA"", UPPER(TRIM(D93))=UPPER(TRIM(rPatron)) ), AND( OR( UPPER(TRIM(rTipo))=""CONTIENE"", UPPER(TRIM(rTipo))=""COINCIDENCIA"" ), ISNUMBER(SEARCH(UPPER(TRIM(rPatron)),UPPER(TRIM(D93)))) ) ) ), rConcepto, """" )"&" ) )<>"""" ), 1 ), """" )"),"ARRENDAMIENTO") -> ARRENDAMIENTO
A94: 1 | B94: MXN | C94: BANCO NACIONAL DE MEXICO | D94: COMISION COBRADA | E94: 5372 | F94: 0 | G94: STAFF | H94: {=INDEX(CC!C:C,MATCH(1,(CC!A:A=G94)*(CC!B:B=I94),0))} -> 102 | I94: PROPIOS | J94: 5372 | K94: =IFERROR(__xludf.DUMMYFUNCTION("IFERROR( INDEX( FILTER( MAP( reglas!$B$2:$B$240, reglas!$C$2:$C$240, reglas!$D$2:$D$240, reglas!$E$2:$E$240, LAMBDA(rEmisor,rPatron,rConcepto,rTipo, IF( AND( OR( UPPER(TRIM(rEmisor))=UPPER(TRIM(C94)), UPPER(TRIM(rEmisor))=""CUALQUIERA"" ), OR( UPPER(TRIM("&"rTipo))=""SOLO EMISOR"", AND( UPPER(TRIM(rTipo))=""EXACTA"", UPPER(TRIM(AG94))=UPPER(TRIM(rPatron)) ), AND( OR( UPPER(TRIM(rTipo))=""CONTIENE"", UPPER(TRIM(rTipo))=""COINCIDENCIA"" ), ISNUMBER(SEARCH(UPPER(TRIM(rPatron)),UPPER(TRIM(D94)))) ) ) ), rConcept"&"o, """" ) ) ), MAP( reglas!$B$2:$B$240, reglas!$C$2:$C$240, reglas!$D$2:$D$240, reglas!$E$2:$E$240, LAMBDA(rEmisor,rPatron,rConcepto,rTipo, IF( AND( OR( UPPER(TRIM(rEmisor))=UPPER(TRIM(C94)), UPPER(TRIM(rEmisor))=""CUALQUIERA"" ), OR( UPPER(TRIM(rTipo))="&"""SOLO EMISOR"", AND( UPPER(TRIM(rTipo))=""EXACTA"", UPPER(TRIM(D94))=UPPER(TRIM(rPatron)) ), AND( OR( UPPER(TRIM(rTipo))=""CONTIENE"", UPPER(TRIM(rTipo))=""COINCIDENCIA"" ), ISNUMBER(SEARCH(UPPER(TRIM(rPatron)),UPPER(TRIM(D94)))) ) ) ), rConcepto, """" )"&" ) )<>"""" ), 1 ), """" )"),"COMISIONES BANCARIAS") -> COMISIONES BANCARIAS
B95: MXN | C95: OFFICE DEPOT DE MEXICO | D95: COP-IMP BOND CARTA COLOR 1-24H | E95: 55.17 | F95: 0 | G95: STAFF | H95: {=INDEX(CC!C:C,MATCH(1,(CC!A:A=G95)*(CC!B:B=I95),0))} -> 102 | I95: PROPIOS | J95: 55.17 | K95: =IFERROR(__xludf.DUMMYFUNCTION("IFERROR( INDEX( FILTER( MAP( reglas!$B$2:$B$240, reglas!$C$2:$C$240, reglas!$D$2:$D$240, reglas!$E$2:$E$240, LAMBDA(rEmisor,rPatron,rConcepto,rTipo, IF( AND( OR( UPPER(TRIM(rEmisor))=UPPER(TRIM(C95)), UPPER(TRIM(rEmisor))=""CUALQUIERA"" ), OR( UPPER(TRIM("&"rTipo))=""SOLO EMISOR"", AND( UPPER(TRIM(rTipo))=""EXACTA"", UPPER(TRIM(AG95))=UPPER(TRIM(rPatron)) ), AND( OR( UPPER(TRIM(rTipo))=""CONTIENE"", UPPER(TRIM(rTipo))=""COINCIDENCIA"" ), ISNUMBER(SEARCH(UPPER(TRIM(rPatron)),UPPER(TRIM(D95)))) ) ) ), rConcept"&"o, """" ) ) ), MAP( reglas!$B$2:$B$240, reglas!$C$2:$C$240, reglas!$D$2:$D$240, reglas!$E$2:$E$240, LAMBDA(rEmisor,rPatron,rConcepto,rTipo, IF( AND( OR( UPPER(TRIM(rEmisor))=UPPER(TRIM(C95)), UPPER(TRIM(rEmisor))=""CUALQUIERA"" ), OR( UPPER(TRIM(rTipo))="&"""SOLO EMISOR"", AND( UPPER(TRIM(rTipo))=""EXACTA"", UPPER(TRIM(D95))=UPPER(TRIM(rPatron)) ), AND( OR( UPPER(TRIM(rTipo))=""CONTIENE"", UPPER(TRIM(rTipo))=""COINCIDENCIA"" ), ISNUMBER(SEARCH(UPPER(TRIM(rPatron)),UPPER(TRIM(D95)))) ) ) ), rConcepto, """" )"&" ) )<>"""" ), 1 ), """" )"),"PAPELERIA") -> PAPELERIA
B96: MXN | C96: INTEGRATIUM | D96: CONTRATO DE SOPORTE TECNICO ANUAL Póliza de soporte técnico anual sin garantías en equipamiento para Carga Aérea Consolidada CDMX 2026 - 2027 | E96: 3300 | F96: 0 | G96: CDMX | H96: {=INDEX(CC!C:C,MATCH(1,(CC!A:A=G96)*(CC!B:B=I96),0))} -> 1502 | I96: PROPIOS | J96: 3300 | K96: =IFERROR(__xludf.DUMMYFUNCTION("IFERROR( INDEX( FILTER( MAP( reglas!$B$2:$B$240, reglas!$C$2:$C$240, reglas!$D$2:$D$240, reglas!$E$2:$E$240, LAMBDA(rEmisor,rPatron,rConcepto,rTipo, IF( AND( OR( UPPER(TRIM(rEmisor))=UPPER(TRIM(C96)), UPPER(TRIM(rEmisor))=""CUALQUIERA"" ), OR( UPPER(TRIM("&"rTipo))=""SOLO EMISOR"", AND( UPPER(TRIM(rTipo))=""EXACTA"", UPPER(TRIM(AG96))=UPPER(TRIM(rPatron)) ), AND( OR( UPPER(TRIM(rTipo))=""CONTIENE"", UPPER(TRIM(rTipo))=""COINCIDENCIA"" ), ISNUMBER(SEARCH(UPPER(TRIM(rPatron)),UPPER(TRIM(D96)))) ) ) ), rConcept"&"o, """" ) ) ), MAP( reglas!$B$2:$B$240, reglas!$C$2:$C$240, reglas!$D$2:$D$240, reglas!$E$2:$E$240, LAMBDA(rEmisor,rPatron,rConcepto,rTipo, IF( AND( OR( UPPER(TRIM(rEmisor))=UPPER(TRIM(C96)), UPPER(TRIM(rEmisor))=""CUALQUIERA"" ), OR( UPPER(TRIM(rTipo))="&"""SOLO EMISOR"", AND( UPPER(TRIM(rTipo))=""EXACTA"", UPPER(TRIM(D96))=UPPER(TRIM(rPatron)) ), AND( OR( UPPER(TRIM(rTipo))=""CONTIENE"", UPPER(TRIM(rTipo))=""COINCIDENCIA"" ), ISNUMBER(SEARCH(UPPER(TRIM(rPatron)),UPPER(TRIM(D96)))) ) ) ), rConcepto, """" )"&" ) )<>"""" ), 1 ), """" )"),"MANTENIMIENTO EQ DE COMPUTO") -> MANTENIMIENTO EQ DE COMPUTO
C97: INTEGRATIUM | D97: CONTRATO DE SOPORTE TECNICO ANUAL Póliza de soporte técnico anual sin garantías en equipamiento para Carga Aérea Consolidada Toluca 1 2026 - 2027 | E97: 564.66 | F97: 0 | G97: TOLUCA | H97: {=INDEX(CC!C:C,MATCH(1,(CC!A:A=G97)*(CC!B:B=I97),0))} -> 1002 | I97: PROPIOS | J97: 564.66 | K97: =IFERROR(__xludf.DUMMYFUNCTION("IFERROR( INDEX( FILTER( MAP( reglas!$B$2:$B$240, reglas!$C$2:$C$240, reglas!$D$2:$D$240, reglas!$E$2:$E$240, LAMBDA(rEmisor,rPatron,rConcepto,rTipo, IF( AND( OR( UPPER(TRIM(rEmisor))=UPPER(TRIM(C97)), UPPER(TRIM(rEmisor))=""CUALQUIERA"" ), OR( UPPER(TRIM("&"rTipo))=""SOLO EMISOR"", AND( UPPER(TRIM(rTipo))=""EXACTA"", UPPER(TRIM(AG97))=UPPER(TRIM(rPatron)) ), AND( OR( UPPER(TRIM(rTipo))=""CONTIENE"", UPPER(TRIM(rTipo))=""COINCIDENCIA"" ), ISNUMBER(SEARCH(UPPER(TRIM(rPatron)),UPPER(TRIM(D97)))) ) ) ), rConcept"&"o, """" ) ) ), MAP( reglas!$B$2:$B$240, reglas!$C$2:$C$240, reglas!$D$2:$D$240, reglas!$E$2:$E$240, LAMBDA(rEmisor,rPatron,rConcepto,rTipo, IF( AND( OR( UPPER(TRIM(rEmisor))=UPPER(TRIM(C97)), UPPER(TRIM(rEmisor))=""CUALQUIERA"" ), OR( UPPER(TRIM(rTipo))="&"""SOLO EMISOR"", AND( UPPER(TRIM(rTipo))=""EXACTA"", UPPER(TRIM(D97))=UPPER(TRIM(rPatron)) ), AND( OR( UPPER(TRIM(rTipo))=""CONTIENE"", UPPER(TRIM(rTipo))=""COINCIDENCIA"" ), ISNUMBER(SEARCH(UPPER(TRIM(rPatron)),UPPER(TRIM(D97)))) ) ) ), rConcepto, """" )"&" ) )<>"""" ), 1 ), """" )"),"MANTENIMIENTO EQ DE COMPUTO") -> MANTENIMIENTO EQ DE COMPUTO
C98: INTEGRATIUM | D98: CONTRATO DE SOPORTE TECNICO ANUAL Póliza de soporte técnico anual sin garantías en equipamiento para Carga Aérea Consolidada Toluca 2 2025 - 2026 | E98: 513.33 | F98: 0 | G98: TOLUCA | H98: {=INDEX(CC!C:C,MATCH(1,(CC!A:A=G98)*(CC!B:B=I98),0))} -> 1002 | I98: PROPIOS | J98: 513.33 | K98: =IFERROR(__xludf.DUMMYFUNCTION("IFERROR( INDEX( FILTER( MAP( reglas!$B$2:$B$240, reglas!$C$2:$C$240, reglas!$D$2:$D$240, reglas!$E$2:$E$240, LAMBDA(rEmisor,rPatron,rConcepto,rTipo, IF( AND( OR( UPPER(TRIM(rEmisor))=UPPER(TRIM(C98)), UPPER(TRIM(rEmisor))=""CUALQUIERA"" ), OR( UPPER(TRIM("&"rTipo))=""SOLO EMISOR"", AND( UPPER(TRIM(rTipo))=""EXACTA"", UPPER(TRIM(AG98))=UPPER(TRIM(rPatron)) ), AND( OR( UPPER(TRIM(rTipo))=""CONTIENE"", UPPER(TRIM(rTipo))=""COINCIDENCIA"" ), ISNUMBER(SEARCH(UPPER(TRIM(rPatron)),UPPER(TRIM(D98)))) ) ) ), rConcept"&"o, """" ) ) ), MAP( reglas!$B$2:$B$240, reglas!$C$2:$C$240, reglas!$D$2:$D$240, reglas!$E$2:$E$240, LAMBDA(rEmisor,rPatron,rConcepto,rTipo, IF( AND( OR( UPPER(TRIM(rEmisor))=UPPER(TRIM(C98)), UPPER(TRIM(rEmisor))=""CUALQUIERA"" ), OR( UPPER(TRIM(rTipo))="&"""SOLO EMISOR"", AND( UPPER(TRIM(rTipo))=""EXACTA"", UPPER(TRIM(D98))=UPPER(TRIM(rPatron)) ), AND( OR( UPPER(TRIM(rTipo))=""CONTIENE"", UPPER(TRIM(rTipo))=""COINCIDENCIA"" ), ISNUMBER(SEARCH(UPPER(TRIM(rPatron)),UPPER(TRIM(D98)))) ) ) ), rConcepto, """" )"&" ) )<>"""" ), 1 ), """" )"),"MANTENIMIENTO EQ DE COMPUTO") -> MANTENIMIENTO EQ DE COMPUTO
A99: 1 | B99: MXN | C99: FEDERAL EXPRESS HOLDINGS (MEXICO) Y COMPAÑIA | D99: Manejo | E99: 634.89 | F99: 0 | G99: TOLUCA | H99: {=INDEX(CC!C:C,MATCH(1,(CC!A:A=G99)*(CC!B:B=I99),0))} -> 1002 | I99: PROPIOS | J99: 634.89 | K99: =IFERROR(__xludf.DUMMYFUNCTION("IFERROR( INDEX( FILTER( MAP( reglas!$B$2:$B$240, reglas!$C$2:$C$240, reglas!$D$2:$D$240, reglas!$E$2:$E$240, LAMBDA(rEmisor,rPatron,rConcepto,rTipo, IF( AND( OR( UPPER(TRIM(rEmisor))=UPPER(TRIM(C99)), UPPER(TRIM(rEmisor))=""CUALQUIERA"" ), OR( UPPER(TRIM("&"rTipo))=""SOLO EMISOR"", AND( UPPER(TRIM(rTipo))=""EXACTA"", UPPER(TRIM(AG99))=UPPER(TRIM(rPatron)) ), AND( OR( UPPER(TRIM(rTipo))=""CONTIENE"", UPPER(TRIM(rTipo))=""COINCIDENCIA"" ), ISNUMBER(SEARCH(UPPER(TRIM(rPatron)),UPPER(TRIM(D99)))) ) ) ), rConcept"&"o, """" ) ) ), MAP( reglas!$B$2:$B$240, reglas!$C$2:$C$240, reglas!$D$2:$D$240, reglas!$E$2:$E$240, LAMBDA(rEmisor,rPatron,rConcepto,rTipo, IF( AND( OR( UPPER(TRIM(rEmisor))=UPPER(TRIM(C99)), UPPER(TRIM(rEmisor))=""CUALQUIERA"" ), OR( UPPER(TRIM(rTipo))="&"""SOLO EMISOR"", AND( UPPER(TRIM(rTipo))=""EXACTA"", UPPER(TRIM(D99))=UPPER(TRIM(rPatron)) ), AND( OR( UPPER(TRIM(rTipo))=""CONTIENE"", UPPER(TRIM(rTipo))=""COINCIDENCIA"" ), ISNUMBER(SEARCH(UPPER(TRIM(rPatron)),UPPER(TRIM(D99)))) ) ) ), rConcepto, """" )"&" ) )<>"""" ), 1 ), """" )"),"MANIOBRAS") -> MANIOBRAS
A100: 1 | B100: MXN | C100: APM TERMINALS LAZARO CARDENAS | D100: FFAU1450514-CODIGO ISPS | E100: 163.79 | F100: 0 | G100: LAZARO | H100: {=INDEX(CC!C:C,MATCH(1,(CC!A:A=G100)*(CC!B:B=I100),0))} -> 1103 | I100: TERCEROS | J100: 163.79 | K100: =IFERROR(__xludf.DUMMYFUNCTION("IFERROR( INDEX( FILTER( MAP( reglas!$B$2:$B$240, reglas!$C$2:$C$240, reglas!$D$2:$D$240, reglas!$E$2:$E$240, LAMBDA(rEmisor,rPatron,rConcepto,rTipo, IF( AND( OR( UPPER(TRIM(rEmisor))=UPPER(TRIM(C100)), UPPER(TRIM(rEmisor))=""CUALQUIERA"" ), OR( UPPER(TRIM"&"(rTipo))=""SOLO EMISOR"", AND( UPPER(TRIM(rTipo))=""EXACTA"", UPPER(TRIM(AG100))=UPPER(TRIM(rPatron)) ), AND( OR( UPPER(TRIM(rTipo))=""CONTIENE"", UPPER(TRIM(rTipo))=""COINCIDENCIA"" ), ISNUMBER(SEARCH(UPPER(TRIM(rPatron)),UPPER(TRIM(D100)))) ) ) ), rConc"&"epto, """" ) ) ), MAP( reglas!$B$2:$B$240, reglas!$C$2:$C$240, reglas!$D$2:$D$240, reglas!$E$2:$E$240, LAMBDA(rEmisor,rPatron,rConcepto,rTipo, IF( AND( OR( UPPER(TRIM(rEmisor))=UPPER(TRIM(C100)), UPPER(TRIM(rEmisor))=""CUALQUIERA"" ), OR( UPPER(TRIM(rTipo"&"))=""SOLO EMISOR"", AND( UPPER(TRIM(rTipo))=""EXACTA"", UPPER(TRIM(D100))=UPPER(TRIM(rPatron)) ), AND( OR( UPPER(TRIM(rTipo))=""CONTIENE"", UPPER(TRIM(rTipo))=""COINCIDENCIA"" ), ISNUMBER(SEARCH(UPPER(TRIM(rPatron)),UPPER(TRIM(D100)))) ) ) ), rConcepto, "&""""" ) ) )<>"""" ), 1 ), """" )"),"MANIOBRAS") -> MANIOBRAS
...

Sheet corresponsalias
A1: Source.Name | B1: Emisor.Attribute:Nombre | C1: Attribute:SubTotal | D1: Attribute:Folio | E1: ADUANA | F1: Attribute:Serie | G1: Attribute:Fecha | H1: Attribute:Total | I1: Attribute:Moneda | J1: Attribute:Exportacion | K1: Attribute:MetodoPago | L1: Attribute:LugarExpedicion | M1: Attribute:FormaPago | N1: Attribute:Sello | O1: Attribute:Certificado
A2: 3491be23-5c9a-4a51-a06a-51c5839d62b1.xml | B2: AGENCIA ADUANAL BAJA SON | C2: 3569.57 | D2: 5228 | F2: I | G2: 46237.41 | H2: 3855.14 | I2: MXN | J2: 1 | K2: PUE | L2: 21210 | M2: 3 | N2: CmekJhEYKwVxwvtP1U2HnTPTppXs9dy9np7x1OAsJyrYk6CeDw7mYoJwhW3+JkRRkbf54I+7ESP4Ghz5U8pg6Dx5RblrVp5A+kPewV9WRObGlyoaorOaRDPk8YJK3yWMFFk7Uk3VvnsNS3v2Omj/amT3bmCP1Qxd58TTNlGmZS18Bgg1ecv971MbSu7zYOD5Y8bMbrl/hIggxvE/TwYUctm2vpYePZzdW7ARgMc4w4FxlYoaA7EZWR9ll1MPQmxU7GXnsK76ZI0aKun0684iWNb69Ux9v/o+sWmzfZmEDRwYh1p5dvkt6YSHrMjvzbQY7HPJWk6KcJ3Qo1E+WjlpNA== | O2: MIIGIjCCBAqgAwIBAgIUMDAwMDEwMDAwMDA3MDgzODk5NTcwDQYJKoZIhvcNAQELBQAwggGVMTUwMwYDVQQDDCxBQyBERUwgU0VSVklDSU8gREUgQURNSU5JU1RSQUNJT04gVFJJQlVUQVJJQTEuMCwGA1UECgwlU0VSVklDSU8gREUgQURNSU5JU1RSQUNJT04gVFJJQlVUQVJJQTEaMBgGA1UECwwRU0FULUlFUyBBdXRob3JpdHkxMjAwBgkqhkiG9w0BCQEWI3NlcnZpY2lvc2FsY29udHJpYnV5ZW50ZUBzYXQuZ29iLm14MSYwJAYDVQQJDB1Bdi4gSGlkYWxnbyA3NywgQ29sLiBHdWVycmVybzEOMAwGA1UEEQwFMDYzMDAxCzAJBgNVBAYTAk1YMQ0wCwYDVQQIDARDRE1YMRMwEQYDVQQHDApDVUFVSFRFTU9DMRUwEwYDVQQtEwxTQVQ5NzA3MDFOTjMxXDBaBgkqhkiG9w0BCQITTXJlc3BvbnNhYmxlOiBBRE1JTklTVFJBQ0lPTiBDRU5UUkFMIERFIFNFUlZJQ0lPUyBUUklCVVRBUklPUyBBTCBDT05UUklCVVlFTlRFMB4XDTI0MDcwMjIzMjAzNFoXDTI4MDcwMjIzMjAzNFowgd8xJDAiBgNVBAMTG0FHRU5DSUEgQURVQU5BTCBCQUpBIFNPTiBTQzEkMCIGA1UEKRMbQUdFTkNJQSBBRFVBTkFMIEJBSkEgU09OIFNDMSQwIgYDVQQKExtBR0VOQ0lBIEFEVUFOQUwgQkFKQSBTT04gU0MxJTAjBgNVBC0THEFBQjE2MDMyMjhLMSAvIFNVVkI3MzA1MjNMRzcxHjAcBgNVBAUTFSAvIFNVVkI3MzA1MjNIQkNTTE4wMjEkMCIGA1UECxMbQUdFTkNJQSBBRFVBTkFMIEJBSkEgU09OIFNDMIIBIjANBgkqhkiG9w0BAQEFAAOCAQ8AMIIBCgKCAQEAvAG8MW4Cs9lM+0qEhT14rw1ZNTF5Hhdl6Ta5L+4NsvUb8xQ0leRPegIH8GDRY6qAz5uxOP34dtNZTP7GbVjQLabboN5Dg/zx2RL5JF8ymcDq/F0cQmDCFKuvxU+e+0cUqWdxPH5MLAt5PYg1mtPqy49SU0WUKDvceTuQnfBcFRZNCsD7d4rZBwI/HvC0aevPr8Bar99UAUvYFfkDCTZ6S/+FETTc7nsgroJ52EersfEowjl16S+WepM3pf2x5Q5DD7Wbf6IY49r4IQLrb7NMr6+O/aUlrcVuXDFhLJj5Hw9iEMnsDphefx4JrtSP2Y+p8dImGiniToSDeo9PTme3HQIDAQABox0wGzAMBgNVHRMBAf8EAjAAMAsGA1UdDwQEAwIGwDANBgkqhkiG9w0BAQsFAAOCAgEARjRW+S0031knqNQ3VIzZ8HsANU3D/97KGmlGDK0pVMp2mB+NHOFTqa3QFdcKvT0pSI8cEJimaivGh0iqsG9Z52eqUUKXj/GVRNu/xBEuOasTMXThkVUswD4Gwt8XjWVXSLNcOhDkcG+RVtXDS5Sab8rctM1d0XrhHeJ6bnVq6wCknQOqWtT5P98w4RvO4UUjrDBSNtt6iChoLCKxxLboyk4+CdNvXKLbkfrcfZ8IVo4Sy2aZwmC4vrGbaT325Qvko/FEq33d5rg0celAFM3U6OtGSC5L7Cn6uAx5zBaLMQeQjdFz+ulA6YwQJq0OvnxPhk7gulv+0y6yBA6hQA9Ng09sHAJW2iXaUTmTPqiVMS/6FctlFNfP4eYZ80abFxbn6zb4MnNiJKXgOaMw71LuX2h5N+4PqCfqpu76b9WsjBdBErQymxHP/CPIlbi0C5OaiKEJhl8D6laJaqdRMlhTb+PeqiUwdS/7xF6Lk8HeE3MKGiaZKRV9miq8JWb8OTHpG84J6zNpZtd9Vllp+cadiPYSfKPpqXyNJtzafeJNd23ztOGiDaO8HfgGOW/Ly60Nq7EPw9Kj8CtvTDIrdWwWU6kKuVXaa5KXXo4mc5Fa9HlyX2rGaCHQjvzoQAZhLXdUaEpQxBm0PJR9cwrXaOG1t+aTQB0ZVwEVBMpp83KWrI8=
A3: 4debc04a-3922-42e7-99be-ff6758978c76.xml | B3: AGENCIA ADUANAL BAJA SON | C3: 1713.95 | D3: 5227 | F3: I | G3: 46235.455 | H3: 1851.07 | I3: MXN | J3: 1 | K3: PUE | L3: 21210 | M3: 3 | N3: m9+AGBOSa4Jg4g5GVu8G/bM1EogR91WouTir/kVa1fGjdW3r+djTi54Fho1rbohEPS+1F7oSKDwNNY1c+Mg8cm67kWOb/INmEMrm5HcHL+TDttJmRC7SaX/UT37pN9Rq4tdPNY63hb0wmq+8v9N6OxFG+0C5N/zGy6fx2Log1GduBmbRgBdOA5A5yFs+QqkCbcTG2Nh3wk3SkDoNaWoIkJkGOdaHwzMbP58IH2yEVFcHx5VBAaoUzSwdIz4yb+elj2EaCqenwiMJN0kuXq7GIrU4nBIH3BXG3f905Wx1UIvstRs5VTITTneo41tktDa1JUrETV7u+u9sg5ZDo33zLQ== | O3: MIIGIjCCBAqgAwIBAgIUMDAwMDEwMDAwMDA3MDgzODk5NTcwDQYJKoZIhvcNAQELBQAwggGVMTUwMwYDVQQDDCxBQyBERUwgU0VSVklDSU8gREUgQURNSU5JU1RSQUNJT04gVFJJQlVUQVJJQTEuMCwGA1UECgwlU0VSVklDSU8gREUgQURNSU5JU1RSQUNJT04gVFJJQlVUQVJJQTEaMBgGA1UECwwRU0FULUlFUyBBdXRob3JpdHkxMjAwBgkqhkiG9w0BCQEWI3NlcnZpY2lvc2FsY29udHJpYnV5ZW50ZUBzYXQuZ29iLm14MSYwJAYDVQQJDB1Bdi4gSGlkYWxnbyA3NywgQ29sLiBHdWVycmVybzEOMAwGA1UEEQwFMDYzMDAxCzAJBgNVBAYTAk1YMQ0wCwYDVQQIDARDRE1YMRMwEQYDVQQHDApDVUFVSFRFTU9DMRUwEwYDVQQtEwxTQVQ5NzA3MDFOTjMxXDBaBgkqhkiG9w0BCQITTXJlc3BvbnNhYmxlOiBBRE1JTklTVFJBQ0lPTiBDRU5UUkFMIERFIFNFUlZJQ0lPUyBUUklCVVRBUklPUyBBTCBDT05UUklCVVlFTlRFMB4XDTI0MDcwMjIzMjAzNFoXDTI4MDcwMjIzMjAzNFowgd8xJDAiBgNVBAMTG0FHRU5DSUEgQURVQU5BTCBCQUpBIFNPTiBTQzEkMCIGA1UEKRMbQUdFTkNJQSBBRFVBTkFMIEJBSkEgU09OIFNDMSQwIgYDVQQKExtBR0VOQ0lBIEFEVUFOQUwgQkFKQSBTT04gU0MxJTAjBgNVBC0THEFBQjE2MDMyMjhLMSAvIFNVVkI3MzA1MjNMRzcxHjAcBgNVBAUTFSAvIFNVVkI3MzA1MjNIQkNTTE4wMjEkMCIGA1UECxMbQUdFTkNJQSBBRFVBTkFMIEJBSkEgU09OIFNDMIIBIjANBgkqhkiG9w0BAQEFAAOCAQ8AMIIBCgKCAQEAvAG8MW4Cs9lM+0qEhT14rw1ZNTF5Hhdl6Ta5L+4NsvUb8xQ0leRPegIH8GDRY6qAz5uxOP34dtNZTP7GbVjQLabboN5Dg/zx2RL5JF8ymcDq/F0cQmDCFKuvxU+e+0cUqWdxPH5MLAt5PYg1mtPqy49SU0WUKDvceTuQnfBcFRZNCsD7d4rZBwI/HvC0aevPr8Bar99UAUvYFfkDCTZ6S/+FETTc7nsgroJ52EersfEowjl16S+WepM3pf2x5Q5DD7Wbf6IY49r4IQLrb7NMr6+O/aUlrcVuXDFhLJj5Hw9iEMnsDphefx4JrtSP2Y+p8dImGiniToSDeo9PTme3HQIDAQABox0wGzAMBgNVHRMBAf8EAjAAMAsGA1UdDwQEAwIGwDANBgkqhkiG9w0BAQsFAAOCAgEARjRW+S0031knqNQ3VIzZ8HsANU3D/97KGmlGDK0pVMp2mB+NHOFTqa3QFdcKvT0pSI8cEJimaivGh0iqsG9Z52eqUUKXj/GVRNu/xBEuOasTMXThkVUswD4Gwt8XjWVXSLNcOhDkcG+RVtXDS5Sab8rctM1d0XrhHeJ6bnVq6wCknQOqWtT5P98w4RvO4UUjrDBSNtt6iChoLCKxxLboyk4+CdNvXKLbkfrcfZ8IVo4Sy2aZwmC4vrGbaT325Qvko/FEq33d5rg0celAFM3U6OtGSC5L7Cn6uAx5zBaLMQeQjdFz+ulA6YwQJq0OvnxPhk7gulv+0y6yBA6hQA9Ng09sHAJW2iXaUTmTPqiVMS/6FctlFNfP4eYZ80abFxbn6zb4MnNiJKXgOaMw71LuX2h5N+4PqCfqpu76b9WsjBdBErQymxHP/CPIlbi0C5OaiKEJhl8D6laJaqdRMlhTb+PeqiUwdS/7xF6Lk8HeE3MKGiaZKRV9miq8JWb8OTHpG84J6zNpZtd9Vllp+cadiPYSfKPpqXyNJtzafeJNd23ztOGiDaO8HfgGOW/Ly60Nq7EPw9Kj8CtvTDIrdWwWU6kKuVXaa5KXXo4mc5Fa9HlyX2rGaCHQjvzoQAZhLXdUaEpQxBm0PJR9cwrXaOG1t+aTQB0ZVwEVBMpp83KWrI8=
A4: 6908a8ea-03b4-4996-981e-1dd9b5ad680a.xml | B4: AGENCIA ADUANAL BAJA SON | C4: 1686.07 | D4: 5226 | F4: I | G4: 46235.453 | H4: 1820.96 | I4: MXN | J4: 1 | K4: PUE | L4: 21210 | M4: 3 | N4: QBPo39/m4qUcTNPd7Fmm89kEwvjHXSvphAQ71ZvW9ZgIE5HIJAkvuPz6QAUmRie4YD8vfDKKbWnXHfqSnwy2J9XURnMg/tgUsj/yXSpTVLqjf6Kn7Mtkqh5l9ZvKcl3iCHskieIaGiVx+3/0bbAiCtLVKl1ZJF7LuRdKl4JQol3yyY1jlJeLHlMod49UgB+W9ykCrgCGY65qQ6OINpYBwtjJwI/4aGFFf1bHv8VFDR80lidsC7l9CO6Ya4FDERU9ieS+4uolgbrSyKrMZ/B+KKVg3QB0Vn6BSAcQFxGCwVJzCGDL3xc5wUFSXaWW2E4pXQx4oyE9DycuGGempP58+A== | O4: MIIGIjCCBAqgAwIBAgIUMDAwMDEwMDAwMDA3MDgzODk5NTcwDQYJKoZIhvcNAQELBQAwggGVMTUwMwYDVQQDDCxBQyBERUwgU0VSVklDSU8gREUgQURNSU5JU1RSQUNJT04gVFJJQlVUQVJJQTEuMCwGA1UECgwlU0VSVklDSU8gREUgQURNSU5JU1RSQUNJT04gVFJJQlVUQVJJQTEaMBgGA1UECwwRU0FULUlFUyBBdXRob3JpdHkxMjAwBgkqhkiG9w0BCQEWI3NlcnZpY2lvc2FsY29udHJpYnV5ZW50ZUBzYXQuZ29iLm14MSYwJAYDVQQJDB1Bdi4gSGlkYWxnbyA3NywgQ29sLiBHdWVycmVybzEOMAwGA1UEEQwFMDYzMDAxCzAJBgNVBAYTAk1YMQ0wCwYDVQQIDARDRE1YMRMwEQYDVQQHDApDVUFVSFRFTU9DMRUwEwYDVQQtEwxTQVQ5NzA3MDFOTjMxXDBaBgkqhkiG9w0BCQITTXJlc3BvbnNhYmxlOiBBRE1JTklTVFJBQ0lPTiBDRU5UUkFMIERFIFNFUlZJQ0lPUyBUUklCVVRBUklPUyBBTCBDT05UUklCVVlFTlRFMB4XDTI0MDcwMjIzMjAzNFoXDTI4MDcwMjIzMjAzNFowgd8xJDAiBgNVBAMTG0FHRU5DSUEgQURVQU5BTCBCQUpBIFNPTiBTQzEkMCIGA1UEKRMbQUdFTkNJQSBBRFVBTkFMIEJBSkEgU09OIFNDMSQwIgYDVQQKExtBR0VOQ0lBIEFEVUFOQUwgQkFKQSBTT04gU0MxJTAjBgNVBC0THEFBQjE2MDMyMjhLMSAvIFNVVkI3MzA1MjNMRzcxHjAcBgNVBAUTFSAvIFNVVkI3MzA1MjNIQkNTTE4wMjEkMCIGA1UECxMbQUdFTkNJQSBBRFVBTkFMIEJBSkEgU09OIFNDMIIBIjANBgkqhkiG9w0BAQEFAAOCAQ8AMIIBCgKCAQEAvAG8MW4Cs9lM+0qEhT14rw1ZNTF5Hhdl6Ta5L+4NsvUb8xQ0leRPegIH8GDRY6qAz5uxOP34dtNZTP7GbVjQLabboN5Dg/zx2RL5JF8ymcDq/F0cQmDCFKuvxU+e+0cUqWdxPH5MLAt5PYg1mtPqy49SU0WUKDvceTuQnfBcFRZNCsD7d4rZBwI/HvC0aevPr8Bar99UAUvYFfkDCTZ6S/+FETTc7nsgroJ52EersfEowjl16S+WepM3pf2x5Q5DD7Wbf6IY49r4IQLrb7NMr6+O/aUlrcVuXDFhLJj5Hw9iEMnsDphefx4JrtSP2Y+p8dImGiniToSDeo9PTme3HQIDAQABox0wGzAMBgNVHRMBAf8EAjAAMAsGA1UdDwQEAwIGwDANBgkqhkiG9w0BAQsFAAOCAgEARjRW+S0031knqNQ3VIzZ8HsANU3D/97KGmlGDK0pVMp2mB+NHOFTqa3QFdcKvT0pSI8cEJimaivGh0iqsG9Z52eqUUKXj/GVRNu/xBEuOasTMXThkVUswD4Gwt8XjWVXSLNcOhDkcG+RVtXDS5Sab8rctM1d0XrhHeJ6bnVq6wCknQOqWtT5P98w4RvO4UUjrDBSNtt6iChoLCKxxLboyk4+CdNvXKLbkfrcfZ8IVo4Sy2aZwmC4vrGbaT325Qvko/FEq33d5rg0celAFM3U6OtGSC5L7Cn6uAx5zBaLMQeQjdFz+ulA6YwQJq0OvnxPhk7gulv+0y6yBA6hQA9Ng09sHAJW2iXaUTmTPqiVMS/6FctlFNfP4eYZ80abFxbn6zb4MnNiJKXgOaMw71LuX2h5N+4PqCfqpu76b9WsjBdBErQymxHP/CPIlbi0C5OaiKEJhl8D6laJaqdRMlhTb+PeqiUwdS/7xF6Lk8HeE3MKGiaZKRV9miq8JWb8OTHpG84J6zNpZtd9Vllp+cadiPYSfKPpqXyNJtzafeJNd23ztOGiDaO8HfgGOW/Ly60Nq7EPw9Kj8CtvTDIrdWwWU6kKuVXaa5KXXo4mc5Fa9HlyX2rGaCHQjvzoQAZhLXdUaEpQxBm0PJR9cwrXaOG1t+aTQB0ZVwEVBMpp83KWrI8=
A5: a06f1e59-8a33-4cb2-b4ef-0ac592cb44af.xml | B5: AGENCIA ADUANAL BAJA SON | C5: 2986.23 | D5: 5232 | F5: I | G5: 46237.724 | H5: 3225.13 | I5: MXN | J5: 1 | K5: PUE | L5: 21210 | M5: 3 | N5: iWvicT1Jn9xAkQ1nDvBqnUkkVYObyyWQsbI/Wo0OjeMQFhf2IpLW0db6J5k13ccGPxiUCA3emdI4leIrKCTL9oP4/wvA04NeBOsmOa9iFo/8+La76xSpiKDp5O7MoezxyuKP3F37x3miB04sSALuN/q/yChsNvg44MDBM0GHmrlIhlTeac6IjsmSh+E05X4K47saAAZLN7n0qANQp1PIdHGttjFEGbHBdQ3TtDFXb8RXEEztypsS2FcJhWvdGBQh/QzbVYtDenONAaCki4my6/XfA3UPsnecG8muuL39lwYfNVOQk4mYNWIYuW1fFj1OeuzCjS6/Aa5MuRn3jfH3jQ== | O5: MIIGIjCCBAqgAwIBAgIUMDAwMDEwMDAwMDA3MDgzODk5NTcwDQYJKoZIhvcNAQELBQAwggGVMTUwMwYDVQQDDCxBQyBERUwgU0VSVklDSU8gREUgQURNSU5JU1RSQUNJT04gVFJJQlVUQVJJQTEuMCwGA1UECgwlU0VSVklDSU8gREUgQURNSU5JU1RSQUNJT04gVFJJQlVUQVJJQTEaMBgGA1UECwwRU0FULUlFUyBBdXRob3JpdHkxMjAwBgkqhkiG9w0BCQEWI3NlcnZpY2lvc2FsY29udHJpYnV5ZW50ZUBzYXQuZ29iLm14MSYwJAYDVQQJDB1Bdi4gSGlkYWxnbyA3NywgQ29sLiBHdWVycmVybzEOMAwGA1UEEQwFMDYzMDAxCzAJBgNVBAYTAk1YMQ0wCwYDVQQIDARDRE1YMRMwEQYDVQQHDApDVUFVSFRFTU9DMRUwEwYDVQQtEwxTQVQ5NzA3MDFOTjMxXDBaBgkqhkiG9w0BCQITTXJlc3BvbnNhYmxlOiBBRE1JTklTVFJBQ0lPTiBDRU5UUkFMIERFIFNFUlZJQ0lPUyBUUklCVVRBUklPUyBBTCBDT05UUklCVVlFTlRFMB4XDTI0MDcwMjIzMjAzNFoXDTI4MDcwMjIzMjAzNFowgd8xJDAiBgNVBAMTG0FHRU5DSUEgQURVQU5BTCBCQUpBIFNPTiBTQzEkMCIGA1UEKRMbQUdFTkNJQSBBRFVBTkFMIEJBSkEgU09OIFNDMSQwIgYDVQQKExtBR0VOQ0lBIEFEVUFOQUwgQkFKQSBTT04gU0MxJTAjBgNVBC0THEFBQjE2MDMyMjhLMSAvIFNVVkI3MzA1MjNMRzcxHjAcBgNVBAUTFSAvIFNVVkI3MzA1MjNIQkNTTE4wMjEkMCIGA1UECxMbQUdFTkNJQSBBRFVBTkFMIEJBSkEgU09OIFNDMIIBIjANBgkqhkiG9w0BAQEFAAOCAQ8AMIIBCgKCAQEAvAG8MW4Cs9lM+0qEhT14rw1ZNTF5Hhdl6Ta5L+4NsvUb8xQ0leRPegIH8GDRY6qAz5uxOP34dtNZTP7GbVjQLabboN5Dg/zx2RL5JF8ymcDq/F0cQmDCFKuvxU+e+0cUqWdxPH5MLAt5PYg1mtPqy49SU0WUKDvceTuQnfBcFRZNCsD7d4rZBwI/HvC0aevPr8Bar99UAUvYFfkDCTZ6S/+FETTc7nsgroJ52EersfEowjl16S+WepM3pf2x5Q5DD7Wbf6IY49r4IQLrb7NMr6+O/aUlrcVuXDFhLJj5Hw9iEMnsDphefx4JrtSP2Y+p8dImGiniToSDeo9PTme3HQIDAQABox0wGzAMBgNVHRMBAf8EAjAAMAsGA1UdDwQEAwIGwDANBgkqhkiG9w0BAQsFAAOCAgEARjRW+S0031knqNQ3VIzZ8HsANU3D/97KGmlGDK0pVMp2mB+NHOFTqa3QFdcKvT0pSI8cEJimaivGh0iqsG9Z52eqUUKXj/GVRNu/xBEuOasTMXThkVUswD4Gwt8XjWVXSLNcOhDkcG+RVtXDS5Sab8rctM1d0XrhHeJ6bnVq6wCknQOqWtT5P98w4RvO4UUjrDBSNtt6iChoLCKxxLboyk4+CdNvXKLbkfrcfZ8IVo4Sy2aZwmC4vrGbaT325Qvko/FEq33d5rg0celAFM3U6OtGSC5L7Cn6uAx5zBaLMQeQjdFz+ulA6YwQJq0OvnxPhk7gulv+0y6yBA6hQA9Ng09sHAJW2iXaUTmTPqiVMS/6FctlFNfP4eYZ80abFxbn6zb4MnNiJKXgOaMw71LuX2h5N+4PqCfqpu76b9WsjBdBErQymxHP/CPIlbi0C5OaiKEJhl8D6laJaqdRMlhTb+PeqiUwdS/7xF6Lk8HeE3MKGiaZKRV9miq8JWb8OTHpG84J6zNpZtd9Vllp+cadiPYSfKPpqXyNJtzafeJNd23ztOGiDaO8HfgGOW/Ly60Nq7EPw9Kj8CtvTDIrdWwWU6kKuVXaa5KXXo4mc5Fa9HlyX2rGaCHQjvzoQAZhLXdUaEpQxBm0PJR9cwrXaOG1t+aTQB0ZVwEVBMpp83KWrI8=
A6: c32580e0-8b66-49db-8a97-eb71465b1009.xml | B6: AGENCIA ADUANAL BAJA SON | C6: 1365.3 | D6: 5233 | F6: I | G6: 46237.726 | H6: 1474.52 | I6: MXN | J6: 1 | K6: PUE | L6: 21210 | M6: 3 | N6: IZydxb5qA6y0KugtylHL8SHeoibqTyfVw7MXgVwich5J3wFFo/jTk4bwHTGpRxLUXv74baMIihlzw0x6J2oZoI1vr0+tAG6qWdnBEYZbvAcD5Mh++PUElwg+X0xPFvsAlXKkklYHdaQjfQaFjy0B3Kq0y5zyUf4UEWxKs9/TWF9T2jNJV+bMYmleaV5uiX+WxGeJFDhmk4HSoTE3+T1yCGe3unJuh2zQH3FS3Pm1tGNcJ/hnubOxdvNEC+tb+qp5mT7PQ0Iq2hhm0cqMKCd0aRX85Dz5I9Ug3ipv5tsmQ4t3rsarZFzstBuKE+f+NksdLL4kD6IAA+WmDY0el0ETlg== | O6: MIIGIjCCBAqgAwIBAgIUMDAwMDEwMDAwMDA3MDgzODk5NTcwDQYJKoZIhvcNAQELBQAwggGVMTUwMwYDVQQDDCxBQyBERUwgU0VSVklDSU8gREUgQURNSU5JU1RSQUNJT04gVFJJQlVUQVJJQTEuMCwGA1UECgwlU0VSVklDSU8gREUgQURNSU5JU1RSQUNJT04gVFJJQlVUQVJJQTEaMBgGA1UECwwRU0FULUlFUyBBdXRob3JpdHkxMjAwBgkqhkiG9w0BCQEWI3NlcnZpY2lvc2FsY29udHJpYnV5ZW50ZUBzYXQuZ29iLm14MSYwJAYDVQQJDB1Bdi4gSGlkYWxnbyA3NywgQ29sLiBHdWVycmVybzEOMAwGA1UEEQwFMDYzMDAxCzAJBgNVBAYTAk1YMQ0wCwYDVQQIDARDRE1YMRMwEQYDVQQHDApDVUFVSFRFTU9DMRUwEwYDVQQtEwxTQVQ5NzA3MDFOTjMxXDBaBgkqhkiG9w0BCQITTXJlc3BvbnNhYmxlOiBBRE1JTklTVFJBQ0lPTiBDRU5UUkFMIERFIFNFUlZJQ0lPUyBUUklCVVRBUklPUyBBTCBDT05UUklCVVlFTlRFMB4XDTI0MDcwMjIzMjAzNFoXDTI4MDcwMjIzMjAzNFowgd8xJDAiBgNVBAMTG0FHRU5DSUEgQURVQU5BTCBCQUpBIFNPTiBTQzEkMCIGA1UEKRMbQUdFTkNJQSBBRFVBTkFMIEJBSkEgU09OIFNDMSQwIgYDVQQKExtBR0VOQ0lBIEFEVUFOQUwgQkFKQSBTT04gU0MxJTAjBgNVBC0THEFBQjE2MDMyMjhLMSAvIFNVVkI3MzA1MjNMRzcxHjAcBgNVBAUTFSAvIFNVVkI3MzA1MjNIQkNTTE4wMjEkMCIGA1UECxMbQUdFTkNJQSBBRFVBTkFMIEJBSkEgU09OIFNDMIIBIjANBgkqhkiG9w0BAQEFAAOCAQ8AMIIBCgKCAQEAvAG8MW4Cs9lM+0qEhT14rw1ZNTF5Hhdl6Ta5L+4NsvUb8xQ0leRPegIH8GDRY6qAz5uxOP34dtNZTP7GbVjQLabboN5Dg/zx2RL5JF8ymcDq/F0cQmDCFKuvxU+e+0cUqWdxPH5MLAt5PYg1mtPqy49SU0WUKDvceTuQnfBcFRZNCsD7d4rZBwI/HvC0aevPr8Bar99UAUvYFfkDCTZ6S/+FETTc7nsgroJ52EersfEowjl16S+WepM3pf2x5Q5DD7Wbf6IY49r4IQLrb7NMr6+O/aUlrcVuXDFhLJj5Hw9iEMnsDphefx4JrtSP2Y+p8dImGiniToSDeo9PTme3HQIDAQABox0wGzAMBgNVHRMBAf8EAjAAMAsGA1UdDwQEAwIGwDANBgkqhkiG9w0BAQsFAAOCAgEARjRW+S0031knqNQ3VIzZ8HsANU3D/97KGmlGDK0pVMp2mB+NHOFTqa3QFdcKvT0pSI8cEJimaivGh0iqsG9Z52eqUUKXj/GVRNu/xBEuOasTMXThkVUswD4Gwt8XjWVXSLNcOhDkcG+RVtXDS5Sab8rctM1d0XrhHeJ6bnVq6wCknQOqWtT5P98w4RvO4UUjrDBSNtt6iChoLCKxxLboyk4+CdNvXKLbkfrcfZ8IVo4Sy2aZwmC4vrGbaT325Qvko/FEq33d5rg0celAFM3U6OtGSC5L7Cn6uAx5zBaLMQeQjdFz+ulA6YwQJq0OvnxPhk7gulv+0y6yBA6hQA9Ng09sHAJW2iXaUTmTPqiVMS/6FctlFNfP4eYZ80abFxbn6zb4MnNiJKXgOaMw71LuX2h5N+4PqCfqpu76b9WsjBdBErQymxHP/CPIlbi0C5OaiKEJhl8D6laJaqdRMlhTb+PeqiUwdS/7xF6Lk8HeE3MKGiaZKRV9miq8JWb8OTHpG84J6zNpZtd9Vllp+cadiPYSfKPpqXyNJtzafeJNd23ztOGiDaO8HfgGOW/Ly60Nq7EPw9Kj8CtvTDIrdWwWU6kKuVXaa5KXXo4mc5Fa9HlyX2rGaCHQjvzoQAZhLXdUaEpQxBm0PJR9cwrXaOG1t+aTQB0ZVwEVBMpp83KWrI8=
A7: 041068be-9055-11f1-bee5-eb83ffc70b68.xml | B7: ALMANZA VILLARREAL AGENCIA ADUANAL | C7: 2934.44 | D7: 349570 | G7: 46238.734 | H7: 3403.95 | I7: MXN | J7: 1 | K7: PUE | L7: 88786 | M7: 3 | N7: APzDkar4RiV+Vfr90JCT4wVvjbIkrDrgR3VeC9h0zTAeGQf/gf6eDnn7GYRZnvPChKajgSHkra4oBCp4Kmb5Hp3rT8coHJtHVqhnZ25MhN0TasLCSUHbbUr9VD5rtrin/9BhY+Z4TX6vGJ9QKxWsgk1BoJRNu8DAx2mUQAkRRQpFuUoz11ekH0n8XAeXtvn0jDD7aX4EMeiH3IvjoBM3L1P+kmBLBsWLFve6O1oiF6ONd8pEoICgy0qB64M1SeZVCpWyNvYK1Go5bLciGXXd05eUmwEbsETcPLDlLOE/6qKbtEo1H6HgD5TXsYhD2I8qgDFJU3b9I+wHTd23V7WBdw== | O7: MIIGLDCCBBSgAwIBAgIUMDAwMDEwMDAwMDA3MTE2Mzc1NDkwDQYJKoZIhvcNAQELBQAwggGVMTUwMwYDVQQDDCxBQyBERUwgU0VSVklDSU8gREUgQURNSU5JU1RSQUNJT04gVFJJQlVUQVJJQTEuMCwGA1UECgwlU0VSVklDSU8gREUgQURNSU5JU1RSQUNJT04gVFJJQlVUQVJJQTEaMBgGA1UECwwRU0FULUlFUyBBdXRob3JpdHkxMjAwBgkqhkiG9w0BCQEWI3NlcnZpY2lvc2FsY29udHJpYnV5ZW50ZUBzYXQuZ29iLm14MSYwJAYDVQQJDB1Bdi4gSGlkYWxnbyA3NywgQ29sLiBHdWVycmVybzEOMAwGA1UEEQwFMDYzMDAxCzAJBgNVBAYTAk1YMQ0wCwYDVQQIDARDRE1YMRMwEQYDVQQHDApDVUFVSFRFTU9DMRUwEwYDVQQtEwxTQVQ5NzA3MDFOTjMxXDBaBgkqhkiG9w0BCQITTXJlc3BvbnNhYmxlOiBBRE1JTklTVFJBQ0lPTiBDRU5UUkFMIERFIFNFUlZJQ0lPUyBUUklCVVRBUklPUyBBTCBDT05UUklCVVlFTlRFMB4XDTI0MTEyNTIyNDQwNFoXDTI4MTEyNTIyNDQwNFowgekxLjAsBgNVBAMTJUFMTUFOWkEgVklMTEFSUkVBTCBBR0VOQ0lBIEFEVUFOQUwgU0MxLjAsBgNVBCkTJUFMTUFOWkEgVklMTEFSUkVBTCBBR0VOQ0lBIEFEVUFOQUwgU0MxLjAsBgNVBAoTJUFMTUFOWkEgVklMTEFSUkVBTCBBR0VOQ0lBIEFEVUFOQUwgU0MxJTAjBgNVBC0THEFWQTk1MDcyMUw4MCAvIFBFRkE2MDExMTc1VDAxHjAcBgNVBAUTFSAvIFBFRkE2MDExMTdNTkxSTE4wODEQMA4GA1UECxMHUkVZTk9TQTCCASIwDQYJKoZIhvcNAQEBBQADggEPADCCAQoCggEBAL+0vq5F4QzJb0h+J2HMGuQlzkumxuo/2eqaXRdqui9xS/hwsUO0/sgBagdnmcpruMIX+EGXnzzQGlGQmo779xclWQGPs/68u+roF39aFFcQAnbUtHKQmfVyrZXS+BHyYVP5dj/0EF9FjfXj2KkbxFh++WHp2HX6fLOu13cFn8s6k/DA7qjNxWb/OMkAAXFOp66Ln0KsWFF3zCnOlg+jMkaQXL6THHlwuSumFSCzbzhrwloaWDlHIfrfbVBAjfRL3Ns9+IB/0dpUmMZ579fEhx21hecT+HN2XmV7dXe2J3+iXWcGEI7Chswc5HbldbOihyTACU4yM7gbmCtYIxn0HgsCAwEAAaMdMBswDAYDVR0TAQH/BAIwADALBgNVHQ8EBAMCBsAwDQYJKoZIhvcNAQELBQADggIBALDXFcX9KOIKcOtWKZJyqdqj51X/AZnziXe7SGUboJ/oQytMF/r67K8HpcTZ8WWRU0UKia5laARmr5rDzfFjp7f8DB1CYYDWEpsZT7xAUDufRc6Jz6r5xpgSrTfc+u10Y1ywzXorfCfE7m8ko8TmiTBU9OHJv98aR+TeVH08hrrJKiSMT0NOeTez3DNXVtGPa56nHNmttcAhlYSvSCz+cUU6/5H51W/WM2q0FjFwg+9T/Y4smIOFdOllOESnPGvBm99SWhlSgMujzzLst92V8NzpnajND4DQ/ON0OWo1rnOVXNALHmjYnEBEFZKWoCJWywtkrk0LGaIJ7xUesaXjZy8iQX6/l3bfr1Zh2rmEAiAmgK+c7wOgF5E+lv1VKOqPEF5HqhaZdNjuh+Yygr+eRUdehmeefRP8E1TxouatuGbHwzfE6oOrvNGhgzLt/xb1BH//hgBgz0sfiwyRSdkCyvEnszGp0v9UDdDVIsVU7iZaR9aXnOJ+bp0RY0icheZAYJn8OtNfnFeH8udNvnTd4t/r1B773NKE9F1XcJM7K2wEfc8rO9o0l8Klsx+orp87TadKDnn0b5UZL7I7spwJhn0O21ifnV8LliChmO/8G4DQ0h3aLaDCX0D9gzlvUEim9eJ56n/0U+IxSHIXavlwrJh1NDqjp5XMq7PhxVljkuzP
A8: 249e9daf-a264-11f1-96d4-c7519918643c.xml | B8: ALMANZA VILLARREAL AGENCIA ADUANAL | C8: 2430.52 | D8: 353483 | G8: 46261.716 | H8: 2819.4 | I8: MXN | J8: 1 | K8: PUE | L8: 88786 | M8: 3 | N8: RyqNFrPH8KCli9m8bGAujW3veHPrcSDiLZ7jyEZLbVSvqCl5lO3Wm8JlWTzMgLMO1Rd+b5kWUE/FYCe8Qz2MSGItKdxlEHP84NW/Gpx6FJJTfsS3IhnpIOgCSszjQUVc0GrucGhsMv2QSX2lW5BdwH3JLRDTZk4sX/P9399axti1eCrtVa5dY02mknexlRhbk6OV5GXqI1lhOWcPQsI5llgXhOW0e7apO4KyfeLFuGqPTQGh0bj/KcwS4S7kaA6NXmyxVHR2+YNF5h2wpxBI191IJSNLpcluZ9Qzhz4dwPciYR+VHE40oGJxtsn9rApzyD3WXULM1H4RY/2qLJhRfw== | O8: MIIGLDCCBBSgAwIBAgIUMDAwMDEwMDAwMDA3MTE2Mzc1NDkwDQYJKoZIhvcNAQELBQAwggGVMTUwMwYDVQQDDCxBQyBERUwgU0VSVklDSU8gREUgQURNSU5JU1RSQUNJT04gVFJJQlVUQVJJQTEuMCwGA1UECgwlU0VSVklDSU8gREUgQURNSU5JU1RSQUNJT04gVFJJQlVUQVJJQTEaMBgGA1UECwwRU0FULUlFUyBBdXRob3JpdHkxMjAwBgkqhkiG9w0BCQEWI3NlcnZpY2lvc2FsY29udHJpYnV5ZW50ZUBzYXQuZ29iLm14MSYwJAYDVQQJDB1Bdi4gSGlkYWxnbyA3NywgQ29sLiBHdWVycmVybzEOMAwGA1UEEQwFMDYzMDAxCzAJBgNVBAYTAk1YMQ0wCwYDVQQIDARDRE1YMRMwEQYDVQQHDApDVUFVSFRFTU9DMRUwEwYDVQQtEwxTQVQ5NzA3MDFOTjMxXDBaBgkqhkiG9w0BCQITTXJlc3BvbnNhYmxlOiBBRE1JTklTVFJBQ0lPTiBDRU5UUkFMIERFIFNFUlZJQ0lPUyBUUklCVVRBUklPUyBBTCBDT05UUklCVVlFTlRFMB4XDTI0MTEyNTIyNDQwNFoXDTI4MTEyNTIyNDQwNFowgekxLjAsBgNVBAMTJUFMTUFOWkEgVklMTEFSUkVBTCBBR0VOQ0lBIEFEVUFOQUwgU0MxLjAsBgNVBCkTJUFMTUFOWkEgVklMTEFSUkVBTCBBR0VOQ0lBIEFEVUFOQUwgU0MxLjAsBgNVBAoTJUFMTUFOWkEgVklMTEFSUkVBTCBBR0VOQ0lBIEFEVUFOQUwgU0MxJTAjBgNVBC0THEFWQTk1MDcyMUw4MCAvIFBFRkE2MDExMTc1VDAxHjAcBgNVBAUTFSAvIFBFRkE2MDExMTdNTkxSTE4wODEQMA4GA1UECxMHUkVZTk9TQTCCASIwDQYJKoZIhvcNAQEBBQADggEPADCCAQoCggEBAL+0vq5F4QzJb0h+J2HMGuQlzkumxuo/2eqaXRdqui9xS/hwsUO0/sgBagdnmcpruMIX+EGXnzzQGlGQmo779xclWQGPs/68u+roF39aFFcQAnbUtHKQmfVyrZXS+BHyYVP5dj/0EF9FjfXj2KkbxFh++WHp2HX6fLOu13cFn8s6k/DA7qjNxWb/OMkAAXFOp66Ln0KsWFF3zCnOlg+jMkaQXL6THHlwuSumFSCzbzhrwloaWDlHIfrfbVBAjfRL3Ns9+IB/0dpUmMZ579fEhx21hecT+HN2XmV7dXe2J3+iXWcGEI7Chswc5HbldbOihyTACU4yM7gbmCtYIxn0HgsCAwEAAaMdMBswDAYDVR0TAQH/BAIwADALBgNVHQ8EBAMCBsAwDQYJKoZIhvcNAQELBQADggIBALDXFcX9KOIKcOtWKZJyqdqj51X/AZnziXe7SGUboJ/oQytMF/r67K8HpcTZ8WWRU0UKia5laARmr5rDzfFjp7f8DB1CYYDWEpsZT7xAUDufRc6Jz6r5xpgSrTfc+u10Y1ywzXorfCfE7m8ko8TmiTBU9OHJv98aR+TeVH08hrrJKiSMT0NOeTez3DNXVtGPa56nHNmttcAhlYSvSCz+cUU6/5H51W/WM2q0FjFwg+9T/Y4smIOFdOllOESnPGvBm99SWhlSgMujzzLst92V8NzpnajND4DQ/ON0OWo1rnOVXNALHmjYnEBEFZKWoCJWywtkrk0LGaIJ7xUesaXjZy8iQX6/l3bfr1Zh2rmEAiAmgK+c7wOgF5E+lv1VKOqPEF5HqhaZdNjuh+Yygr+eRUdehmeefRP8E1TxouatuGbHwzfE6oOrvNGhgzLt/xb1BH//hgBgz0sfiwyRSdkCyvEnszGp0v9UDdDVIsVU7iZaR9aXnOJ+bp0RY0icheZAYJn8OtNfnFeH8udNvnTd4t/r1B773NKE9F1XcJM7K2wEfc8rO9o0l8Klsx+orp87TadKDnn0b5UZL7I7spwJhn0O21ifnV8LliChmO/8G4DQ0h3aLaDCX0D9gzlvUEim9eJ56n/0U+IxSHIXavlwrJh1NDqjp5XMq7PhxVljkuzP
